Workbook

Sheet Inputs
A1: RMBS Interview Model Inputs
A2: Section 1: Pool structure
A3: Initial Pool Balance | B3: =B4*B5 -> 300000000
A4: Loan Count | B4: 1000
A5: Balance Per Loan | B5: 300000
A6: WAC (annual) | B6: 0.0575
A7: Remaining Term (months) | B7: 300
A8: Servicing/Admin Fee (annual) | B8: 0.005
A9: Class A Share | B9: 0.8
A10: Class B Share | B10: 0.15
A11: Equity Share | B11: 0.05
A13: Section 2: V1 scenario
A14: Active Scenario | B14: Base
A15: CPR (annual, active scenario) | B15: =INDEX(Scenarios!B2:B4,MATCH(B14,Scenarios!A2:A4,0)) -> 0.08
A16: CDR (annual, active scenario) | B16: =INDEX(Scenarios!C2:C4,MATCH(B14,Scenarios!A2:A4,0)) -> 0.015
A17: Severity (active scenario) | B17: =INDEX(Scenarios!D2:D4,MATCH(B14,Scenarios!A2:A4,0)) -> 0.25
A18: SMM (monthly) | B18: =1-(1-B15)^(1/12) -> 0.0069243826
A19: MDR (monthly) | B19: =1-(1-B16)^(1/12) -> 0.001258677
A22: Section 3: V2 parameters
A23: V2 Trigger Loss Threshold | B23: 0.03
A24: V2 Trigger DQ Threshold | B24: 0.06
A25: V2 Initial DQ30 Share | B25: 0.01
A26: V2 Initial DQ60 Share | B26: 0.005
A27: V2 Roll to 30 (annual) | B27: =INDEX(Scenarios_V2!D2:D4,MATCH(B14,Scenarios_V2!A2:A4,0)) -> 0.04
A28: V2 Default from 60 (annual) | B28: =INDEX(Scenarios_V2!E2:E4,MATCH(B14,Scenarios_V2!A2:A4,0)) -> 0.1
A29: V2 Cure30 (monthly) | B29: =INDEX(Scenarios_V2!F2:F4,MATCH(B14,Scenarios_V2!A2:A4,0)) -> 0.35
A30: V2 Roll30->60 (monthly) | B30: =INDEX(Scenarios_V2!G2:G4,MATCH(B14,Scenarios_V2!A2:A4,0)) -> 0.2
A31: V2 Cure60 (monthly) | B31: =INDEX(Scenarios_V2!H2:H4,MATCH(B14,Scenarios_V2!A2:A4,0)) -> 0.12
A32: V2 SMM (monthly) | B32: =INDEX(Scenarios_V2!B2:B4,MATCH(B14,Scenarios_V2!A2:A4,0)) -> 0.08
A33: V2 RollTo30 MDR (monthly) | B33: =1-(1-B27)^(1/12) -> 0.0033960532
A34: V2 Default60 MDR (monthly) | B34: =1-(1-B28)^(1/12) -> 0.008741611
A35: V2 Severity (active scenario) | B35: =INDEX(Scenarios_V2!C2:C4,MATCH(B14,Scenarios_V2!A2:A4,0)) -> 0.25
A37: Notes
A38: All downstream formulas should reference these inputs.
A39: Change B12 to Base, Mild_Stress, or Severe_Stress.

Sheet LoanPool
A1: Month | B1: Begin_Balance | C1: Scheduled_Payment | D1: Interest | E1: Scheduled_Principal | F1: Prepayment | G1: Default | H1: Loss | I1: Total_Principal_Outflow | J1: End_Balance | K1: Fee | L1: Interest_Available | M1: Principal_Available
A2: 1 | B2: =Inputs!B3 -> 300000000 | C2: =IF(A2<=Inputs!B7,IF(B2>0,-PMT(Inputs!B6/12,Inputs!B7-A2+1,B2),0),0) -> 1887319.2 | D2: =B2*Inputs!B6/12 -> 1437500 | E2: =MAX(C2-D2,0) -> 449819.21 | F2: =MAX((B2-E2)*Inputs!B18,0) -> 2074200.1 | G2: =MAX((B2-E2-F2)*Inputs!B19,0) -> 374426.18 | H2: =G2*Inputs!B17 -> 93606.545 | I2: =MIN(B2,E2+F2+G2) -> 2898445.5 | J2: =MAX(B2-I2,0) -> 2.9710155e+08 | K2: =B2*Inputs!B8/12 -> 125000 | L2: =MAX(D2-K2,0) -> 1312500 | M2: =MAX(I2-H2,0) -> 2804838.9
A3: 2 | B3: =J2 -> 2.9710155e+08 | C3: =IF(A3<=Inputs!B7,IF(B3>0,-PMT(Inputs!B6/12,Inputs!B7-A3+1,B3),0),0) -> 1871891.6 | D3: =B3*Inputs!B6/12 -> 1423611.6 | E3: =MAX(C3-D3,0) -> 448280 | F3: =MAX((B3-E3)*Inputs!B18,0) -> 2054140.8 | G3: =MAX((B3-E3-F3)*Inputs!B19,0) -> 370805.16 | H3: =G3*Inputs!B17 -> 92701.29 | I3: =MIN(B3,E3+F3+G3) -> 2873225.9 | J3: =MAX(B3-I3,0) -> 2.9422833e+08 | K3: =B3*Inputs!B8/12 -> 123792.31 | L3: =MAX(D3-K3,0) -> 1299819.3 | M3: =MAX(I3-H3,0) -> 2780524.6
A4: 3 | B4: =J3 -> 2.9422833e+08 | C4: =IF(A4<=Inputs!B7,IF(B4>0,-PMT(Inputs!B6/12,Inputs!B7-A4+1,B4),0),0) -> 1856590.1 | D4: =B4*Inputs!B6/12 -> 1409844.1 | E4: =MAX(C4-D4,0) -> 446746.05 | F4: =MAX((B4-E4)*Inputs!B18,0) -> 2034256.1 | G4: =MAX((B4-E4-F4)*Inputs!B19,0) -> 367215.65 | H4: =G4*Inputs!B17 -> 91803.914 | I4: =MIN(B4,E4+F4+G4) -> 2848217.8 | J4: =MAX(B4-I4,0) -> 2.9138011e+08 | K4: =B4*Inputs!B8/12 -> 122595.14 | L4: =MAX(D4-K4,0) -> 1287248.9 | M4: =MAX(I4-H4,0) -> 2756413.9
A5: 4 | B5: =J4 -> 2.9138011e+08 | C5: =IF(A5<=Inputs!B7,IF(B5>0,-PMT(Inputs!B6/12,Inputs!B7-A5+1,B5),0),0) -> 1841413.7 | D5: =B5*Inputs!B6/12 -> 1396196.4 | E5: =MAX(C5-D5,0) -> 445217.35 | F5: =MAX((B5-E5)*Inputs!B18,0) -> 2014544.5 | G5: =MAX((B5-E5-F5)*Inputs!B19,0) -> 363657.4 | H5: =G5*Inputs!B17 -> 90914.351 | I5: =MIN(B5,E5+F5+G5) -> 2823419.3 | J5: =MAX(B5-I5,0) -> 2.8855669e+08 | K5: =B5*Inputs!B8/12 -> 121408.38 | L5: =MAX(D5-K5,0) -> 1274788 | M5: =MAX(I5-H5,0) -> 2732504.9
A6: 5 | B6: =J5 -> 2.8855669e+08 | C6: =IF(A6<=Inputs!B7,IF(B6>0,-PMT(Inputs!B6/12,Inputs!B7-A6+1,B6),0),0) -> 1826361.4 | D6: =B6*Inputs!B6/12 -> 1382667.5 | E6: =MAX(C6-D6,0) -> 443693.89 | F6: =MAX((B6-E6)*Inputs!B18,0) -> 1995004.6 | G6: =MAX((B6-E6-F6)*Inputs!B19,0) -> 360130.14 | H6: =G6*Inputs!B17 -> 90032.536 | I6: =MIN(B6,E6+F6+G6) -> 2798828.7 | J6: =MAX(B6-I6,0) -> 2.8575786e+08 | K6: =B6*Inputs!B8/12 -> 120231.95 | L6: =MAX(D6-K6,0) -> 1262435.5 | M6: =MAX(I6-H6,0) -> 2708796.1
A7: 6 | B7: =J6 -> 2.8575786e+08 | C7: =IF(A7<=Inputs!B7,IF(B7>0,-PMT(Inputs!B6/12,Inputs!B7-A7+1,B7),0),0) -> 1811432.1 | D7: =B7*Inputs!B6/12 -> 1369256.4 | E7: =MAX(C7-D7,0) -> 442175.64 | F7: =MAX((B7-E7)*Inputs!B18,0) -> 1975635 | G7: =MAX((B7-E7-F7)*Inputs!B19,0) -> 356633.61 | H7: =G7*Inputs!B17 -> 89158.403 | I7: =MIN(B7,E7+F7+G7) -> 2774444.2 | J7: =MAX(B7-I7,0) -> 2.8298342e+08 | K7: =B7*Inputs!B8/12 -> 119065.78 | L7: =MAX(D7-K7,0) -> 1250190.7 | M7: =MAX(I7-H7,0) -> 2685285.8
A8: 7 | B8: =J7 -> 2.8298342e+08 | C8: =IF(A8<=Inputs!B7,IF(B8>0,-PMT(Inputs!B6/12,Inputs!B7-A8+1,B8),0),0) -> 1796624.8 | D8: =B8*Inputs!B6/12 -> 1355962.2 | E8: =MAX(C8-D8,0) -> 440662.58 | F8: =MAX((B8-E8)*Inputs!B18,0) -> 1956434.2 | G8: =MAX((B8-E8-F8)*Inputs!B19,0) -> 353167.56 | H8: =G8*Inputs!B17 -> 88291.889 | I8: =MIN(B8,E8+F8+G8) -> 2750264.3 | J8: =MAX(B8-I8,0) -> 2.8023315e+08 | K8: =B8*Inputs!B8/12 -> 117909.76 | L8: =MAX(D8-K8,0) -> 1238052.5 | M8: =MAX(I8-H8,0) -> 2661972.4
A9: 8 | B9: =J8 -> 2.8023315e+08 | C9: =IF(A9<=Inputs!B7,IF(B9>0,-PMT(Inputs!B6/12,Inputs!B7-A9+1,B9),0),0) -> 1781938.6 | D9: =B9*Inputs!B6/12 -> 1342783.9 | E9: =MAX(C9-D9,0) -> 439154.7 | F9: =MAX((B9-E9)*Inputs!B18,0) -> 1937400.7 | G9: =MAX((B9-E9-F9)*Inputs!B19,0) -> 349731.72 | H9: =G9*Inputs!B17 -> 87432.929 | I9: =MIN(B9,E9+F9+G9) -> 2726287.1 | J9: =MAX(B9-I9,0) -> 2.7750687e+08 | K9: =B9*Inputs!B8/12 -> 116763.81 | L9: =MAX(D9-K9,0) -> 1226020.1 | M9: =MAX(I9-H9,0) -> 2638854.2
A10: 9 | B10: =J9 -> 2.7750687e+08 | C10: =IF(A10<=Inputs!B7,IF(B10>0,-PMT(Inputs!B6/12,Inputs!B7-A10+1,B10),0),0) -> 1767372.4 | D10: =B10*Inputs!B6/12 -> 1329720.4 | E10: =MAX(C10-D10,0) -> 437651.98 | F10: =MAX((B10-E10)*Inputs!B18,0) -> 1918533.3 | G10: =MAX((B10-E10-F10)*Inputs!B19,0) -> 346325.84 | H10: =G10*Inputs!B17 -> 86581.46 | I10: =MIN(B10,E10+F10+G10) -> 2702511.1 | J10: =MAX(B10-I10,0) -> 2.7480436e+08 | K10: =B10*Inputs!B8/12 -> 115627.86 | L10: =MAX(D10-K10,0) -> 1214092.5 | M10: =MAX(I10-H10,0) -> 2615929.6
A11: 10 | B11: =J10 -> 2.7480436e+08 | C11: =IF(A11<=Inputs!B7,IF(B11>0,-PMT(Inputs!B6/12,Inputs!B7-A11+1,B11),0),0) -> 1752925.3 | D11: =B11*Inputs!B6/12 -> 1316770.9 | E11: =MAX(C11-D11,0) -> 436154.4 | F11: =MAX((B11-E11)*Inputs!B18,0) -> 1899830.4 | G11: =MAX((B11-E11-F11)*Inputs!B19,0) -> 342949.68 | H11: =G11*Inputs!B17 -> 85737.419 | I11: =MIN(B11,E11+F11+G11) -> 2678934.5 | J11: =MAX(B11-I11,0) -> 2.7212542e+08 | K11: =B11*Inputs!B8/12 -> 114501.82 | L11: =MAX(D11-K11,0) -> 1202269.1 | M11: =MAX(I11-H11,0) -> 2593197.1
A12: 11 | B12: =J11 -> 2.7212542e+08 | C12: =IF(A12<=Inputs!B7,IF(B12>0,-PMT(Inputs!B6/12,Inputs!B7-A12+1,B12),0),0) -> 1738596.3 | D12: =B12*Inputs!B6/12 -> 1303934.3 | E12: =MAX(C12-D12,0) -> 434661.95 | F12: =MAX((B12-E12)*Inputs!B18,0) -> 1881290.8 | G12: =MAX((B12-E12-F12)*Inputs!B19,0) -> 339602.98 | H12: =G12*Inputs!B17 -> 84900.744 | I12: =MIN(B12,E12+F12+G12) -> 2655555.7 | J12: =MAX(B12-I12,0) -> 2.6946987e+08 | K12: =B12*Inputs!B8/12 -> 113385.59 | L12: =MAX(D12-K12,0) -> 1190548.7 | M12: =MAX(I12-H12,0) -> 2570655
A13: 12 | B13: =J12 -> 2.6946987e+08 | C13: =IF(A13<=Inputs!B7,IF(B13>0,-PMT(Inputs!B6/12,Inputs!B7-A13+1,B13),0),0) -> 1724384.4 | D13: =B13*Inputs!B6/12 -> 1291209.8 | E13: =MAX(C13-D13,0) -> 433174.6 | F13: =MAX((B13-E13)*Inputs!B18,0) -> 1862913 | G13: =MAX((B13-E13-F13)*Inputs!B19,0) -> 336285.49 | H13: =G13*Inputs!B17 -> 84071.374 | I13: =MIN(B13,E13+F13+G13) -> 2632373.1 | J13: =MAX(B13-I13,0) -> 2.6683749e+08 | K13: =B13*Inputs!B8/12 -> 112279.11 | L13: =MAX(D13-K13,0) -> 1178930.7 | M13: =MAX(I13-H13,0) -> 2548301.7
A14: 13 | B14: =J13 -> 2.6683749e+08 | C14: =IF(A14<=Inputs!B7,IF(B14>0,-PMT(Inputs!B6/12,Inputs!B7-A14+1,B14),0),0) -> 1710288.7 | D14: =B14*Inputs!B6/12 -> 1278596.3 | E14: =MAX(C14-D14,0) -> 431692.35 | F14: =MAX((B14-E14)*Inputs!B18,0) -> 1844695.7 | G14: =MAX((B14-E14-F14)*Inputs!B19,0) -> 332996.98 | H14: =G14*Inputs!B17 -> 83249.246 | I14: =MIN(B14,E14+F14+G14) -> 2609385 | J14: =MAX(B14-I14,0) -> 2.6422811e+08 | K14: =B14*Inputs!B8/12 -> 111182.29 | L14: =MAX(D14-K14,0) -> 1167414 | M14: =MAX(I14-H14,0) -> 2526135.8
A15: 14 | B15: =J14 -> 2.6422811e+08 | C15: =IF(A15<=Inputs!B7,IF(B15>0,-PMT(Inputs!B6/12,Inputs!B7-A15+1,B15),0),0) -> 1696308.2 | D15: =B15*Inputs!B6/12 -> 1266093 | E15: =MAX(C15-D15,0) -> 430215.16 | F15: =MAX((B15-E15)*Inputs!B18,0) -> 1826637.5 | G15: =MAX((B15-E15-F15)*Inputs!B19,0) -> 329737.2 | H15: =G15*Inputs!B17 -> 82434.3 | I15: =MIN(B15,E15+F15+G15) -> 2586589.9 | J15: =MAX(B15-I15,0) -> 2.6164152e+08 | K15: =B15*Inputs!B8/12 -> 110095.04 | L15: =MAX(D15-K15,0) -> 1155998 | M15: =MAX(I15-H15,0) -> 2504155.6
A16: 15 | B16: =J15 -> 2.6164152e+08 | C16: =IF(A16<=Inputs!B7,IF(B16>0,-PMT(Inputs!B6/12,Inputs!B7-A16+1,B16),0),0) -> 1682442 | D16: =B16*Inputs!B6/12 -> 1253698.9 | E16: =MAX(C16-D16,0) -> 428743.03 | F16: =MAX((B16-E16)*Inputs!B18,0) -> 1808737.2 | G16: =MAX((B16-E16-F16)*Inputs!B19,0) -> 326505.9 | H16: =G16*Inputs!B17 -> 81626.475 | I16: =MIN(B16,E16+F16+G16) -> 2563986.1 | J16: =MAX(B16-I16,0) -> 2.5907753e+08 | K16: =B16*Inputs!B8/12 -> 109017.3 | L16: =MAX(D16-K16,0) -> 1144681.6 | M16: =MAX(I16-H16,0) -> 2482359.7
A17: 16 | B17: =J16 -> 2.5907753e+08 | C17: =IF(A17<=Inputs!B7,IF(B17>0,-PMT(Inputs!B6/12,Inputs!B7-A17+1,B17),0),0) -> 1668689.1 | D17: =B17*Inputs!B6/12 -> 1241413.2 | E17: =MAX(C17-D17,0) -> 427275.94 | F17: =MAX((B17-E17)*Inputs!B18,0) -> 1790993.3 | G17: =MAX((B17-E17-F17)*Inputs!B19,0) -> 323302.85 | H17: =G17*Inputs!B17 -> 80825.713 | I17: =MIN(B17,E17+F17+G17) -> 2541572.1 | J17: =MAX(B17-I17,0) -> 2.5653596e+08 | K17: =B17*Inputs!B8/12 -> 107948.97 | L17: =MAX(D17-K17,0) -> 1133464.2 | M17: =MAX(I17-H17,0) -> 2460746.4
A18: 17 | B18: =J17 -> 2.5653596e+08 | C18: =IF(A18<=Inputs!B7,IF(B18>0,-PMT(Inputs!B6/12,Inputs!B7-A18+1,B18),0),0) -> 1655048.7 | D18: =B18*Inputs!B6/12 -> 1229234.8 | E18: =MAX(C18-D18,0) -> 425813.87 | F18: =MAX((B18-E18)*Inputs!B18,0) -> 1773404.6 | G18: =MAX((B18-E18-F18)*Inputs!B19,0) -> 320127.81 | H18: =G18*Inputs!B17 -> 80031.953 | I18: =MIN(B18,E18+F18+G18) -> 2519346.3 | J18: =MAX(B18-I18,0) -> 2.5401661e+08 | K18: =B18*Inputs!B8/12 -> 106889.98 | L18: =MAX(D18-K18,0) -> 1122344.8 | M18: =MAX(I18-H18,0) -> 2439314.4
A19: 18 | B19: =J18 -> 2.5401661e+08 | C19: =IF(A19<=Inputs!B7,IF(B19>0,-PMT(Inputs!B6/12,Inputs!B7-A19+1,B19),0),0) -> 1641519.7 | D19: =B19*Inputs!B6/12 -> 1217162.9 | E19: =MAX(C19-D19,0) -> 424356.8 | F19: =MAX((B19-E19)*Inputs!B18,0) -> 1755969.8 | G19: =MAX((B19-E19-F19)*Inputs!B19,0) -> 316980.55 | H19: =G19*Inputs!B17 -> 79245.137 | I19: =MIN(B19,E19+F19+G19) -> 2497307.2 | J19: =MAX(B19-I19,0) -> 2.5151931e+08 | K19: =B19*Inputs!B8/12 -> 105840.26 | L19: =MAX(D19-K19,0) -> 1111322.7 | M19: =MAX(I19-H19,0) -> 2418062
A20: 19 | B20: =J19 -> 2.5151931e+08 | C20: =IF(A20<=Inputs!B7,IF(B20>0,-PMT(Inputs!B6/12,Inputs!B7-A20+1,B20),0),0) -> 1628101.4 | D20: =B20*Inputs!B6/12 -> 1205196.7 | E20: =MAX(C20-D20,0) -> 422904.71 | F20: =MAX((B20-E20)*Inputs!B18,0) -> 1738687.6 | G20: =MAX((B20-E20-F20)*Inputs!B19,0) -> 313860.82 | H20: =G20*Inputs!B17 -> 78465.206 | I20: =MIN(B20,E20+F20+G20) -> 2475453.1 | J20: =MAX(B20-I20,0) -> 2.4904385e+08 | K20: =B20*Inputs!B8/12 -> 104799.71 | L20: =MAX(D20-K20,0) -> 1100397 | M20: =MAX(I20-H20,0) -> 2396987.9
A21: 20 | B21: =J20 -> 2.4904385e+08 | C21: =IF(A21<=Inputs!B7,IF(B21>0,-PMT(Inputs!B6/12,Inputs!B7-A21+1,B21),0),0) -> 1614792.7 | D21: =B21*Inputs!B6/12 -> 1193335.1 | E21: =MAX(C21-D21,0) -> 421457.6 | F21: =MAX((B21-E21)*Inputs!B18,0) -> 1721556.6 | G21: =MAX((B21-E21-F21)*Inputs!B19,0) -> 310768.41 | H21: =G21*Inputs!B17 -> 77692.103 | I21: =MIN(B21,E21+F21+G21) -> 2453782.6 | J21: =MAX(B21-I21,0) -> 2.4659007e+08 | K21: =B21*Inputs!B8/12 -> 103768.27 | L21: =MAX(D21-K21,0) -> 1089566.9 | M21: =MAX(I21-H21,0) -> 2376090.5
A22: 21 | B22: =J21 -> 2.4659007e+08 | C22: =IF(A22<=Inputs!B7,IF(B22>0,-PMT(Inputs!B6/12,Inputs!B7-A22+1,B22),0),0) -> 1601592.9 | D22: =B22*Inputs!B6/12 -> 1181577.4 | E22: =MAX(C22-D22,0) -> 420015.43 | F22: =MAX((B22-E22)*Inputs!B18,0) -> 1704575.7 | G22: =MAX((B22-E22-F22)*Inputs!B19,0) -> 307703.08 | H22: =G22*Inputs!B17 -> 76925.77 | I22: =MIN(B22,E22+F22+G22) -> 2432294.2 | J22: =MAX(B22-I22,0) -> 2.4415778e+08 | K22: =B22*Inputs!B8/12 -> 102745.86 | L22: =MAX(D22-K22,0) -> 1078831.6 | M22: =MAX(I22-H22,0) -> 2355368.4
A23: 22 | B23: =J22 -> 2.4415778e+08 | C23: =IF(A23<=Inputs!B7,IF(B23>0,-PMT(Inputs!B6/12,Inputs!B7-A23+1,B23),0),0) -> 1588500.9 | D23: =B23*Inputs!B6/12 -> 1169922.7 | E23: =MAX(C23-D23,0) -> 418578.21 | F23: =MAX((B23-E23)*Inputs!B18,0) -> 1687743.5 | G23: =MAX((B23-E23-F23)*Inputs!B19,0) -> 304664.6 | H23: =G23*Inputs!B17 -> 76166.151 | I23: =MIN(B23,E23+F23+G23) -> 2410986.3 | J23: =MAX(B23-I23,0) -> 2.4174679e+08 | K23: =B23*Inputs!B8/12 -> 101732.41 | L23: =MAX(D23-K23,0) -> 1068190.3 | M23: =MAX(I23-H23,0) -> 2334820.1
A24: 23 | B24: =J23 -> 2.4174679e+08 | C24: =IF(A24<=Inputs!B7,IF(B24>0,-PMT(Inputs!B6/12,Inputs!B7-A24+1,B24),0),0) -> 1575515.9 | D24: =B24*Inputs!B6/12 -> 1158370 | E24: =MAX(C24-D24,0) -> 417145.9 | F24: =MAX((B24-E24)*Inputs!B18,0) -> 1671058.8 | G24: =MAX((B24-E24-F24)*Inputs!B19,0) -> 301652.75 | H24: =G24*Inputs!B17 -> 75413.188 | I24: =MIN(B24,E24+F24+G24) -> 2389857.4 | J24: =MAX(B24-I24,0) -> 2.3935693e+08 | K24: =B24*Inputs!B8/12 -> 100727.83 | L24: =MAX(D24-K24,0) -> 1057642.2 | M24: =MAX(I24-H24,0) -> 2314444.3
A25: 24 | B25: =J24 -> 2.3935693e+08 | C25: =IF(A25<=Inputs!B7,IF(B25>0,-PMT(Inputs!B6/12,Inputs!B7-A25+1,B25),0),0) -> 1562637.1 | D25: =B25*Inputs!B6/12 -> 1146918.6 | E25: =MAX(C25-D25,0) -> 415718.49 | F25: =MAX((B25-E25)*Inputs!B18,0) -> 1654520.4 | G25: =MAX((B25-E25-F25)*Inputs!B19,0) -> 298667.31 | H25: =G25*Inputs!B17 -> 74666.827 | I25: =MIN(B25,E25+F25+G25) -> 2368906.2 | J25: =MAX(B25-I25,0) -> 2.3698803e+08 | K25: =B25*Inputs!B8/12 -> 99732.055 | L25: =MAX(D25-K25,0) -> 1047186.6 | M25: =MAX(I25-H25,0) -> 2294239.4
A26: 25 | B26: =J25 -> 2.3698803e+08 | C26: =IF(A26<=Inputs!B7,IF(B26>0,-PMT(Inputs!B6/12,Inputs!B7-A26+1,B26),0),0) -> 1549863.6 | D26: =B26*Inputs!B6/12 -> 1135567.6 | E26: =MAX(C26-D26,0) -> 414295.96 | F26: =MAX((B26-E26)*Inputs!B18,0) -> 1638127 | G26: =MAX((B26-E26-F26)*Inputs!B19,0) -> 295708.04 | H26: =G26*Inputs!B17 -> 73927.011 | I26: =MIN(B26,E26+F26+G26) -> 2348131 | J26: =MAX(B26-I26,0) -> 2.346399e+08 | K26: =B26*Inputs!B8/12 -> 98745.011 | L26: =MAX(D26-K26,0) -> 1036822.6 | M26: =MAX(I26-H26,0) -> 2274204
A27: 26 | B27: =J26 -> 2.346399e+08 | C27: =IF(A27<=Inputs!B7,IF(B27>0,-PMT(Inputs!B6/12,Inputs!B7-A27+1,B27),0),0) -> 1537194.5 | D27: =B27*Inputs!B6/12 -> 1124316.2 | E27: =MAX(C27-D27,0) -> 412878.31 | F27: =MAX((B27-E27)*Inputs!B18,0) -> 1621877.5 | G27: =MAX((B27-E27-F27)*Inputs!B19,0) -> 292774.74 | H27: =G27*Inputs!B17 -> 73193.686 | I27: =MIN(B27,E27+F27+G27) -> 2327530.5 | J27: =MAX(B27-I27,0) -> 2.3231236e+08 | K27: =B27*Inputs!B8/12 -> 97766.623 | L27: =MAX(D27-K27,0) -> 1026549.5 | M27: =MAX(I27-H27,0) -> 2254336.9
A28: 27 | B28: =J27 -> 2.3231236e+08 | C28: =IF(A28<=Inputs!B7,IF(B28>0,-PMT(Inputs!B6/12,Inputs!B7-A28+1,B28),0),0) -> 1524628.9 | D28: =B28*Inputs!B6/12 -> 1113163.4 | E28: =MAX(C28-D28,0) -> 411465.5 | F28: =MAX((B28-E28)*Inputs!B18,0) -> 1605770.6 | G28: =MAX((B28-E28-F28)*Inputs!B19,0) -> 289867.19 | H28: =G28*Inputs!B17 -> 72466.797 | I28: =MIN(B28,E28+F28+G28) -> 2307103.2 | J28: =MAX(B28-I28,0) -> 2.3000526e+08 | K28: =B28*Inputs!B8/12 -> 96796.819 | L28: =MAX(D28-K28,0) -> 1016366.6 | M28: =MAX(I28-H28,0) -> 2234636.4
A29: 28 | B29: =J28 -> 2.3000526e+08 | C29: =IF(A29<=Inputs!B7,IF(B29>0,-PMT(Inputs!B6/12,Inputs!B7-A29+1,B29),0),0) -> 1512166.1 | D29: =B29*Inputs!B6/12 -> 1102108.5 | E29: =MAX(C29-D29,0) -> 410057.53 | F29: =MAX((B29-E29)*Inputs!B18,0) -> 1589805 | G29: =MAX((B29-E29-F29)*Inputs!B19,0) -> 286985.16 | H29: =G29*Inputs!B17 -> 71746.289 | I29: =MIN(B29,E29+F29+G29) -> 2286847.7 | J29: =MAX(B29-I29,0) -> 2.2771841e+08 | K29: =B29*Inputs!B8/12 -> 95835.526 | L29: =MAX(D29-K29,0) -> 1006273 | M29: =MAX(I29-H29,0) -> 2215101.4
A30: 29 | B30: =J29 -> 2.2771841e+08 | C30: =IF(A30<=Inputs!B7,IF(B30>0,-PMT(Inputs!B6/12,Inputs!B7-A30+1,B30),0),0) -> 1499805.1 | D30: =B30*Inputs!B6/12 -> 1091150.7 | E30: =MAX(C30-D30,0) -> 408654.37 | F30: =MAX((B30-E30)*Inputs!B18,0) -> 1573979.7 | G30: =MAX((B30-E30-F30)*Inputs!B19,0) -> 284128.44 | H30: =G30*Inputs!B17 -> 71032.11 | I30: =MIN(B30,E30+F30+G30) -> 2266762.6 | J30: =MAX(B30-I30,0) -> 2.2545165e+08 | K30: =B30*Inputs!B8/12 -> 94882.672 | L30: =MAX(D30-K30,0) -> 996268.06 | M30: =MAX(I30-H30,0) -> 2195730.5
A31: 30 | B31: =J30 -> 2.2545165e+08 | C31: =IF(A31<=Inputs!B7,IF(B31>0,-PMT(Inputs!B6/12,Inputs!B7-A31+1,B31),0),0) -> 1487545.2 | D31: =B31*Inputs!B6/12 -> 1080289.2 | E31: =MAX(C31-D31,0) -> 407256.02 | F31: =MAX((B31-E31)*Inputs!B18,0) -> 1558293.5 | G31: =MAX((B31-E31-F31)*Inputs!B19,0) -> 281296.82 | H31: =G31*Inputs!B17 -> 70324.205 | I31: =MIN(B31,E31+F31+G31) -> 2246846.3 | J31: =MAX(B31-I31,0) -> 2.232048e+08 | K31: =B31*Inputs!B8/12 -> 93938.188 | L31: =MAX(D31-K31,0) -> 986350.97 | M31: =MAX(I31-H31,0) -> 2176522.1
A32: 31 | B32: =J31 -> 2.232048e+08 | C32: =IF(A32<=Inputs!B7,IF(B32>0,-PMT(Inputs!B6/12,Inputs!B7-A32+1,B32),0),0) -> 1475385.5 | D32: =B32*Inputs!B6/12 -> 1069523 | E32: =MAX(C32-D32,0) -> 405862.45 | F32: =MAX((B32-E32)*Inputs!B18,0) -> 1542745.1 | G32: =MAX((B32-E32-F32)*Inputs!B19,0) -> 278490.09 | H32: =G32*Inputs!B17 -> 69622.523 | I32: =MIN(B32,E32+F32+G32) -> 2227097.7 | J32: =MAX(B32-I32,0) -> 2.2097771e+08 | K32: =B32*Inputs!B8/12 -> 93002.002 | L32: =MAX(D32-K32,0) -> 976521.02 | M32: =MAX(I32-H32,0) -> 2157475.1
A33: 32 | B33: =J32 -> 2.2097771e+08 | C33: =IF(A33<=Inputs!B7,IF(B33>0,-PMT(Inputs!B6/12,Inputs!B7-A33+1,B33),0),0) -> 1463325.2 | D33: =B33*Inputs!B6/12 -> 1058851.5 | E33: =MAX(C33-D33,0) -> 404473.66 | F33: =MAX((B33-E33)*Inputs!B18,0) -> 1527333.5 | G33: =MAX((B33-E33-F33)*Inputs!B19,0) -> 275708.04 | H33: =G33*Inputs!B17 -> 68927.01 | I33: =MIN(B33,E33+F33+G33) -> 2207515.2 | J33: =MAX(B33-I33,0) -> 2.1877019e+08 | K33: =B33*Inputs!B8/12 -> 92074.045 | L33: =MAX(D33-K33,0) -> 966777.47 | M33: =MAX(I33-H33,0) -> 2138588.2
A34: 33 | B34: =J33 -> 2.1877019e+08 | C34: =IF(A34<=Inputs!B7,IF(B34>0,-PMT(Inputs!B6/12,Inputs!B7-A34+1,B34),0),0) -> 1451363.4 | D34: =B34*Inputs!B6/12 -> 1048273.8 | E34: =MAX(C34-D34,0) -> 403089.61 | F34: =MAX((B34-E34)*Inputs!B18,0) -> 1512057.4 | G34: =MAX((B34-E34-F34)*Inputs!B19,0) -> 272950.46 | H34: =G34*Inputs!B17 -> 68237.615 | I34: =MIN(B34,E34+F34+G34) -> 2188097.4 | J34: =MAX(B34-I34,0) -> 2.1658209e+08 | K34: =B34*Inputs!B8/12 -> 91154.247 | L34: =MAX(D34-K34,0) -> 957119.59 | M34: =MAX(I34-H34,0) -> 2119859.8
A35: 34 | B35: =J34 -> 2.1658209e+08 | C35: =IF(A35<=Inputs!B7,IF(B35>0,-PMT(Inputs!B6/12,Inputs!B7-A35+1,B35),0),0) -> 1439499.5 | D35: =B35*Inputs!B6/12 -> 1037789.2 | E35: =MAX(C35-D35,0) -> 401710.3 | F35: =MAX((B35-E35)*Inputs!B18,0) -> 1496915.7 | G35: =MAX((B35-E35-F35)*Inputs!B19,0) -> 270217.15 | H35: =G35*Inputs!B17 -> 67554.287 | I35: =MIN(B35,E35+F35+G35) -> 2168843.1 | J35: =MAX(B35-I35,0) -> 2.1441325e+08 | K35: =B35*Inputs!B8/12 -> 90242.539 | L35: =MAX(D35-K35,0) -> 947546.66 | M35: =MAX(I35-H35,0) -> 2101288.9
A36: 35 | B36: =J35 -> 2.1441325e+08 | C36: =IF(A36<=Inputs!B7,IF(B36>0,-PMT(Inputs!B6/12,Inputs!B7-A36+1,B36),0),0) -> 1427732.5 | D36: =B36*Inputs!B6/12 -> 1027396.8 | E36: =MAX(C36-D36,0) -> 400335.71 | F36: =MAX((B36-E36)*Inputs!B18,0) -> 1481907.3 | G36: =MAX((B36-E36-F36)*Inputs!B19,0) -> 267507.9 | H36: =G36*Inputs!B17 -> 66876.974 | I36: =MIN(B36,E36+F36+G36) -> 2149750.9 | J36: =MAX(B36-I36,0) -> 2.122635e+08 | K36: =B36*Inputs!B8/12 -> 89338.855 | L36: =MAX(D36-K36,0) -> 938057.98 | M36: =MAX(I36-H36,0) -> 2082873.9
A37: 36 | B37: =J36 -> 2.122635e+08 | C37: =IF(A37<=Inputs!B7,IF(B37>0,-PMT(Inputs!B6/12,Inputs!B7-A37+1,B37),0),0) -> 1416061.8 | D37: =B37*Inputs!B6/12 -> 1017095.9 | E37: =MAX(C37-D37,0) -> 398965.82 | F37: =MAX((B37-E37)*Inputs!B18,0) -> 1467031.1 | G37: =MAX((B37-E37-F37)*Inputs!B19,0) -> 264822.5 | H37: =G37*Inputs!B17 -> 66205.626 | I37: =MIN(B37,E37+F37+G37) -> 2130819.4 | J37: =MAX(B37-I37,0) -> 2.1013268e+08 | K37: =B37*Inputs!B8/12 -> 88443.125 | L37: =MAX(D37-K37,0) -> 928652.82 | M37: =MAX(I37-H37,0) -> 2064613.8
A38: 37 | B38: =J37 -> 2.1013268e+08 | C38: =IF(A38<=Inputs!B7,IF(B38>0,-PMT(Inputs!B6/12,Inputs!B7-A38+1,B38),0),0) -> 1404486.4 | D38: =B38*Inputs!B6/12 -> 1006885.8 | E38: =MAX(C38-D38,0) -> 397600.62 | F38: =MAX((B38-E38)*Inputs!B18,0) -> 1452285.9 | G38: =MAX((B38-E38-F38)*Inputs!B19,0) -> 262160.77 | H38: =G38*Inputs!B17 -> 65540.192 | I38: =MIN(B38,E38+F38+G38) -> 2112047.3 | J38: =MAX(B38-I38,0) -> 2.0802063e+08 | K38: =B38*Inputs!B8/12 -> 87555.284 | L38: =MAX(D38-K38,0) -> 919330.48 | M38: =MAX(I38-H38,0) -> 2046507.1
A39: 38 | B39: =J38 -> 2.0802063e+08 | C39: =IF(A39<=Inputs!B7,IF(B39>0,-PMT(Inputs!B6/12,Inputs!B7-A39+1,B39),0),0) -> 1393005.6 | D39: =B39*Inputs!B6/12 -> 996765.54 | E39: =MAX(C39-D39,0) -> 396240.09 | F39: =MAX((B39-E39)*Inputs!B18,0) -> 1437670.7 | G39: =MAX((B39-E39-F39)*Inputs!B19,0) -> 259522.49 | H39: =G39*Inputs!B17 -> 64880.622 | I39: =MIN(B39,E39+F39+G39) -> 2093433.3 | J39: =MAX(B39-I39,0) -> 2.059272e+08 | K39: =B39*Inputs!B8/12 -> 86675.264 | L39: =MAX(D39-K39,0) -> 910090.27 | M39: =MAX(I39-H39,0) -> 2028552.7
A40: 39 | B40: =J39 -> 2.059272e+08 | C40: =IF(A40<=Inputs!B7,IF(B40>0,-PMT(Inputs!B6/12,Inputs!B7-A40+1,B40),0),0) -> 1381618.7 | D40: =B40*Inputs!B6/12 -> 986734.5 | E40: =MAX(C40-D40,0) -> 394884.22 | F40: =MAX((B40-E40)*Inputs!B18,0) -> 1423184.4 | G40: =MAX((B40-E40-F40)*Inputs!B19,0) -> 256907.47 | H40: =G40*Inputs!B17 -> 64226.868 | I40: =MIN(B40,E40+F40+G40) -> 2074976.1 | J40: =MAX(B40-I40,0) -> 2.0385222e+08 | K40: =B40*Inputs!B8/12 -> 85803 | L40: =MAX(D40-K40,0) -> 900931.5 | M40: =MAX(I40-H40,0) -> 2010749.2
A41: 40 | B41: =J40 -> 2.0385222e+08 | C41: =IF(A41<=Inputs!B7,IF(B41>0,-PMT(Inputs!B6/12,Inputs!B7-A41+1,B41),0),0) -> 1370324.9 | D41: =B41*Inputs!B6/12 -> 976791.91 | E41: =MAX(C41-D41,0) -> 393532.99 | F41: =MAX((B41-E41)*Inputs!B18,0) -> 1408825.8 | G41: =MAX((B41-E41-F41)*Inputs!B19,0) -> 254315.52 | H41: =G41*Inputs!B17 -> 63578.881 | I41: =MIN(B41,E41+F41+G41) -> 2056674.3 | J41: =MAX(B41-I41,0) -> 2.0179555e+08 | K41: =B41*Inputs!B8/12 -> 84938.427 | L41: =MAX(D41-K41,0) -> 891853.48 | M41: =MAX(I41-H41,0) -> 1993095.5
A42: 41 | B42: =J41 -> 2.0179555e+08 | C42: =IF(A42<=Inputs!B7,IF(B42>0,-PMT(Inputs!B6/12,Inputs!B7-A42+1,B42),0),0) -> 1359123.4 | D42: =B42*Inputs!B6/12 -> 966937.01 | E42: =MAX(C42-D42,0) -> 392186.38 | F42: =MAX((B42-E42)*Inputs!B18,0) -> 1394594 | G42: =MAX((B42-E42-F42)*Inputs!B19,0) -> 251746.44 | H42: =G42*Inputs!B17 -> 62936.61 | I42: =MIN(B42,E42+F42+G42) -> 2038526.8 | J42: =MAX(B42-I42,0) -> 1.9975702e+08 | K42: =B42*Inputs!B8/12 -> 84081.479 | L42: =MAX(D42-K42,0) -> 882855.53 | M42: =MAX(I42-H42,0) -> 1975590.2
A43: 42 | B43: =J42 -> 1.9975702e+08 | C43: =IF(A43<=Inputs!B7,IF(B43>0,-PMT(Inputs!B6/12,Inputs!B7-A43+1,B43),0),0) -> 1348013.4 | D43: =B43*Inputs!B6/12 -> 957169.07 | E43: =MAX(C43-D43,0) -> 390844.38 | F43: =MAX((B43-E43)*Inputs!B18,0) -> 1380487.7 | G43: =MAX((B43-E43-F43)*Inputs!B19,0) -> 249200.04 | H43: =G43*Inputs!B17 -> 62300.01 | I43: =MIN(B43,E43+F43+G43) -> 2020532.1 | J43: =MAX(B43-I43,0) -> 1.9773649e+08 | K43: =B43*Inputs!B8/12 -> 83232.093 | L43: =MAX(D43-K43,0) -> 873936.98 | M43: =MAX(I43-H43,0) -> 1958232.1
A44: 43 | B44: =J43 -> 1.9773649e+08 | C44: =IF(A44<=Inputs!B7,IF(B44>0,-PMT(Inputs!B6/12,Inputs!B7-A44+1,B44),0),0) -> 1336994.3 | D44: =B44*Inputs!B6/12 -> 947487.35 | E44: =MAX(C44-D44,0) -> 389506.97 | F44: =MAX((B44-E44)*Inputs!B18,0) -> 1366506 | G44: =MAX((B44-E44-F44)*Inputs!B19,0) -> 246676.12 | H44: =G44*Inputs!B17 -> 61669.031 | I44: =MIN(B44,E44+F44+G44) -> 2002689.1 | J44: =MAX(B44-I44,0) -> 1.957338e+08 | K44: =B44*Inputs!B8/12 -> 82390.205 | L44: =MAX(D44-K44,0) -> 865097.15 | M44: =MAX(I44-H44,0) -> 1941020.1
A45: 44 | B45: =J44 -> 1.957338e+08 | C45: =IF(A45<=Inputs!B7,IF(B45>0,-PMT(Inputs!B6/12,Inputs!B7-A45+1,B45),0),0) -> 1326065.3 | D45: =B45*Inputs!B6/12 -> 937891.14 | E45: =MAX(C45-D45,0) -> 388174.13 | F45: =MAX((B45-E45)*Inputs!B18,0) -> 1352647.9 | G45: =MAX((B45-E45-F45)*Inputs!B19,0) -> 244174.51 | H45: =G45*Inputs!B17 -> 61043.626 | I45: =MIN(B45,E45+F45+G45) -> 1984996.5 | J45: =MAX(B45-I45,0) -> 1.9374881e+08 | K45: =B45*Inputs!B8/12 -> 81555.751 | L45: =MAX(D45-K45,0) -> 856335.38 | M45: =MAX(I45-H45,0) -> 1923952.9
A46: 45 | B46: =J45 -> 1.9374881e+08 | C46: =IF(A46<=Inputs!B7,IF(B46>0,-PMT(Inputs!B6/12,Inputs!B7-A46+1,B46),0),0) -> 1315225.6 | D46: =B46*Inputs!B6/12 -> 928379.69 | E46: =MAX(C46-D46,0) -> 386845.86 | F46: =MAX((B46-E46)*Inputs!B18,0) -> 1338912.2 | G46: =MAX((B46-E46-F46)*Inputs!B19,0) -> 241695 | H46: =G46*Inputs!B17 -> 60423.749 | I46: =MIN(B46,E46+F46+G46) -> 1967453.1 | J46: =MAX(B46-I46,0) -> 1.9178135e+08 | K46: =B46*Inputs!B8/12 -> 80728.669 | L46: =MAX(D46-K46,0) -> 847651.02 | M46: =MAX(I46-H46,0) -> 1907029.3
A47: 46 | B47: =J46 -> 1.9178135e+08 | C47: =IF(A47<=Inputs!B7,IF(B47>0,-PMT(Inputs!B6/12,Inputs!B7-A47+1,B47),0),0) -> 1304474.4 | D47: =B47*Inputs!B6/12 -> 918952.31 | E47: =MAX(C47-D47,0) -> 385522.13 | F47: =MAX((B47-E47)*Inputs!B18,0) -> 1325298 | G47: =MAX((B47-E47-F47)*Inputs!B19,0) -> 239237.41 | H47: =G47*Inputs!B17 -> 59809.353 | I47: =MIN(B47,E47+F47+G47) -> 1950057.5 | J47: =MAX(B47-I47,0) -> 1.898313e+08 | K47: =B47*Inputs!B8/12 -> 79908.897 | L47: =MAX(D47-K47,0) -> 839043.42 | M47: =MAX(I47-H47,0) -> 1890248.2
A48: 47 | B48: =J47 -> 1.898313e+08 | C48: =IF(A48<=Inputs!B7,IF(B48>0,-PMT(Inputs!B6/12,Inputs!B7-A48+1,B48),0),0) -> 1293811.2 | D48: =B48*Inputs!B6/12 -> 909608.29 | E48: =MAX(C48-D48,0) -> 384202.94 | F48: =MAX((B48-E48)*Inputs!B18,0) -> 1311804.2 | G48: =MAX((B48-E48-F48)*Inputs!B19,0) -> 236801.56 | H48: =G48*Inputs!B17 -> 59200.391 | I48: =MIN(B48,E48+F48+G48) -> 1932808.7 | J48: =MAX(B48-I48,0) -> 1.8789849e+08 | K48: =B48*Inputs!B8/12 -> 79096.373 | L48: =MAX(D48-K48,0) -> 830511.92 | M48: =MAX(I48-H48,0) -> 1873608.3
A49: 48 | B49: =J48 -> 1.8789849e+08 | C49: =IF(A49<=Inputs!B7,IF(B49>0,-PMT(Inputs!B6/12,Inputs!B7-A49+1,B49),0),0) -> 1283235.2 | D49: =B49*Inputs!B6/12 -> 900346.91 | E49: =MAX(C49-D49,0) -> 382888.25 | F49: =MAX((B49-E49)*Inputs!B18,0) -> 1298429.8 | G49: =MAX((B49-E49-F49)*Inputs!B19,0) -> 234387.27 | H49: =G49*Inputs!B17 -> 58596.818 | I49: =MIN(B49,E49+F49+G49) -> 1915705.3 | J49: =MAX(B49-I49,0) -> 1.8598278e+08 | K49: =B49*Inputs!B8/12 -> 78291.036 | L49: =MAX(D49-K49,0) -> 822055.88 | M49: =MAX(I49-H49,0) -> 1857108.5
A50: 49 | B50: =J49 -> 1.8598278e+08 | C50: =IF(A50<=Inputs!B7,IF(B50>0,-PMT(Inputs!B6/12,Inputs!B7-A50+1,B50),0),0) -> 1272745.6 | D50: =B50*Inputs!B6/12 -> 891167.49 | E50: =MAX(C50-D50,0) -> 381578.07 | F50: =MAX((B50-E50)*Inputs!B18,0) -> 1285173.7 | G50: =MAX((B50-E50-F50)*Inputs!B19,0) -> 231994.35 | H50: =G50*Inputs!B17 -> 57998.588 | I50: =MIN(B50,E50+F50+G50) -> 1898746.2 | J50: =MAX(B50-I50,0) -> 1.8408403e+08 | K50: =B50*Inputs!B8/12 -> 77492.825 | L50: =MAX(D50-K50,0) -> 813674.67 | M50: =MAX(I50-H50,0) -> 1840747.6
A51: 50 | B51: =J50 -> 1.8408403e+08 | C51: =IF(A51<=Inputs!B7,IF(B51>0,-PMT(Inputs!B6/12,Inputs!B7-A51+1,B51),0),0) -> 1262341.7 | D51: =B51*Inputs!B6/12 -> 882069.33 | E51: =MAX(C51-D51,0) -> 380272.37 | F51: =MAX((B51-E51)*Inputs!B18,0) -> 1272035.1 | G51: =MAX((B51-E51-F51)*Inputs!B19,0) -> 229622.62 | H51: =G51*Inputs!B17 -> 57405.656 | I51: =MIN(B51,E51+F51+G51) -> 1881930.1 | J51: =MAX(B51-I51,0) -> 1.822021e+08 | K51: =B51*Inputs!B8/12 -> 76701.681 | L51: =MAX(D51-K51,0) -> 805367.65 | M51: =MAX(I51-H51,0) -> 1824524.5
A52: 51 | B52: =J51 -> 1.822021e+08 | C52: =IF(A52<=Inputs!B7,IF(B52>0,-PMT(Inputs!B6/12,Inputs!B7-A52+1,B52),0),0) -> 1252022.9 | D52: =B52*Inputs!B6/12 -> 873051.75 | E52: =MAX(C52-D52,0) -> 378971.13 | F52: =MAX((B52-E52)*Inputs!B18,0) -> 1259012.9 | G52: =MAX((B52-E52-F52)*Inputs!B19,0) -> 227271.91 | H52: =G52*Inputs!B17 -> 56817.977 | I52: =MIN(B52,E52+F52+G52) -> 1865256 | J52: =MAX(B52-I52,0) -> 1.8033685e+08 | K52: =B52*Inputs!B8/12 -> 75917.544 | L52: =MAX(D52-K52,0) -> 797134.21 | M52: =MAX(I52-H52,0) -> 1808438
A53: 52 | B53: =J52 -> 1.8033685e+08 | C53: =IF(A53<=Inputs!B7,IF(B53>0,-PMT(Inputs!B6/12,Inputs!B7-A53+1,B53),0),0) -> 1241788.4 | D53: =B53*Inputs!B6/12 -> 864114.07 | E53: =MAX(C53-D53,0) -> 377674.35 | F53: =MAX((B53-E53)*Inputs!B18,0) -> 1246106.2 | G53: =MAX((B53-E53-F53)*Inputs!B19,0) -> 224942.03 | H53: =G53*Inputs!B17 -> 56235.508 | I53: =MIN(B53,E53+F53+G53) -> 1848722.6 | J53: =MAX(B53-I53,0) -> 1.7848813e+08 | K53: =B53*Inputs!B8/12 -> 75140.354 | L53: =MAX(D53-K53,0) -> 788973.71 | M53: =MAX(I53-H53,0) -> 1792487.1
A54: 53 | B54: =J53 -> 1.7848813e+08 | C54: =IF(A54<=Inputs!B7,IF(B54>0,-PMT(Inputs!B6/12,Inputs!B7-A54+1,B54),0),0) -> 1231637.6 | D54: =B54*Inputs!B6/12 -> 855255.6 | E54: =MAX(C54-D54,0) -> 376382.01 | F54: =MAX((B54-E54)*Inputs!B18,0) -> 1233313.9 | G54: =MAX((B54-E54-F54)*Inputs!B19,0) -> 222632.82 | H54: =G54*Inputs!B17 -> 55658.204 | I54: =MIN(B54,E54+F54+G54) -> 1832328.7 | J54: =MAX(B54-I54,0) -> 1.766558e+08 | K54: =B54*Inputs!B8/12 -> 74370.053 | L54: =MAX(D54-K54,0) -> 780885.55 | M54: =MAX(I54-H54,0) -> 1776670.5
A55: 54 | B55: =J54 -> 1.766558e+08 | C55: =IF(A55<=Inputs!B7,IF(B55>0,-PMT(Inputs!B6/12,Inputs!B7-A55+1,B55),0),0) -> 1221569.8 | D55: =B55*Inputs!B6/12 -> 846475.7 | E55: =MAX(C55-D55,0) -> 375094.09 | F55: =MAX((B55-E55)*Inputs!B18,0) -> 1220635 | G55: =MAX((B55-E55-F55)*Inputs!B19,0) -> 220344.08 | H55: =G55*Inputs!B17 -> 55086.021 | I55: =MIN(B55,E55+F55+G55) -> 1816073.2 | J55: =MAX(B55-I55,0) -> 1.7483972e+08 | K55: =B55*Inputs!B8/12 -> 73606.582 | L55: =MAX(D55-K55,0) -> 772869.11 | M55: =MAX(I55-H55,0) -> 1760987.2
A56: 55 | B56: =J55 -> 1.7483972e+08 | C56: =IF(A56<=Inputs!B7,IF(B56>0,-PMT(Inputs!B6/12,Inputs!B7-A56+1,B56),0),0) -> 1211584.3 | D56: =B56*Inputs!B6/12 -> 837773.68 | E56: =MAX(C56-D56,0) -> 373810.57 | F56: =MAX((B56-E56)*Inputs!B18,0) -> 1208068.7 | G56: =MAX((B56-E56-F56)*Inputs!B19,0) -> 218075.67 | H56: =G56*Inputs!B17 -> 54518.917 | I56: =MIN(B56,E56+F56+G56) -> 1799955 | J56: =MAX(B56-I56,0) -> 1.7303977e+08 | K56: =B56*Inputs!B8/12 -> 72849.885 | L56: =MAX(D56-K56,0) -> 764923.79 | M56: =MAX(I56-H56,0) -> 1745436.1
A57: 56 | B57: =J56 -> 1.7303977e+08 | C57: =IF(A57<=Inputs!B7,IF(B57>0,-PMT(Inputs!B6/12,Inputs!B7-A57+1,B57),0),0) -> 1201680.3 | D57: =B57*Inputs!B6/12 -> 829148.89 | E57: =MAX(C57-D57,0) -> 372531.45 | F57: =MAX((B57-E57)*Inputs!B18,0) -> 1195614 | G57: =MAX((B57-E57-F57)*Inputs!B19,0) -> 215827.39 | H57: =G57*Inputs!B17 -> 53956.848 | I57: =MIN(B57,E57+F57+G57) -> 1783972.9 | J57: =MAX(B57-I57,0) -> 1.712558e+08 | K57: =B57*Inputs!B8/12 -> 72099.904 | L57: =MAX(D57-K57,0) -> 757048.99 | M57: =MAX(I57-H57,0) -> 1730016
A58: 57 | B58: =J57 -> 1.712558e+08 | C58: =IF(A58<=Inputs!B7,IF(B58>0,-PMT(Inputs!B6/12,Inputs!B7-A58+1,B58),0),0) -> 1191857.4 | D58: =B58*Inputs!B6/12 -> 820600.69 | E58: =MAX(C58-D58,0) -> 371256.71 | F58: =MAX((B58-E58)*Inputs!B18,0) -> 1183269.9 | G58: =MAX((B58-E58-F58)*Inputs!B19,0) -> 213599.09 | H58: =G58*Inputs!B17 -> 53399.772 | I58: =MIN(B58,E58+F58+G58) -> 1768125.7 | J58: =MAX(B58-I58,0) -> 1.6948767e+08 | K58: =B58*Inputs!B8/12 -> 71356.582 | L58: =MAX(D58-K58,0) -> 749244.11 | M58: =MAX(I58-H58,0) -> 1714726
A59: 58 | B59: =J58 -> 1.6948767e+08 | C59: =IF(A59<=Inputs!B7,IF(B59>0,-PMT(Inputs!B6/12,Inputs!B7-A59+1,B59),0),0) -> 1182114.7 | D59: =B59*Inputs!B6/12 -> 812128.42 | E59: =MAX(C59-D59,0) -> 369986.32 | F59: =MAX((B59-E59)*Inputs!B18,0) -> 1171035.6 | G59: =MAX((B59-E59-F59)*Inputs!B19,0) -> 211390.59 | H59: =G59*Inputs!B17 -> 52847.647 | I59: =MIN(B59,E59+F59+G59) -> 1752412.5 | J59: =MAX(B59-I59,0) -> 1.6773526e+08 | K59: =B59*Inputs!B8/12 -> 70619.863 | L59: =MAX(D59-K59,0) -> 741508.56 | M59: =MAX(I59-H59,0) -> 1699564.8
A60: 59 | B60: =J59 -> 1.6773526e+08 | C60: =IF(A60<=Inputs!B7,IF(B60>0,-PMT(Inputs!B6/12,Inputs!B7-A60+1,B60),0),0) -> 1172451.7 | D60: =B60*Inputs!B6/12 -> 803731.45 | E60: =MAX(C60-D60,0) -> 368720.29 | F60: =MAX((B60-E60)*Inputs!B18,0) -> 1158909.9 | G60: =MAX((B60-E60-F60)*Inputs!B19,0) -> 209201.72 | H60: =G60*Inputs!B17 -> 52300.43 | I60: =MIN(B60,E60+F60+G60) -> 1736832 | J60: =MAX(B60-I60,0) -> 1.6599843e+08 | K60: =B60*Inputs!B8/12 -> 69889.691 | L60: =MAX(D60-K60,0) -> 733841.75 | M60: =MAX(I60-H60,0) -> 1684531.5
A61: 60 | B61: =J60 -> 1.6599843e+08 | C61: =IF(A61<=Inputs!B7,IF(B61>0,-PMT(Inputs!B6/12,Inputs!B7-A61+1,B61),0),0) -> 1162867.7 | D61: =B61*Inputs!B6/12 -> 795409.13 | E61: =MAX(C61-D61,0) -> 367458.58 | F61: =MAX((B61-E61)*Inputs!B18,0) -> 1146892.2 | G61: =MAX((B61-E61-F61)*Inputs!B19,0) -> 207032.33 | H61: =G61*Inputs!B17 -> 51758.081 | I61: =MIN(B61,E61+F61+G61) -> 1721383.1 | J61: =MAX(B61-I61,0) -> 1.6427704e+08 | K61: =B61*Inputs!B8/12 -> 69166.011 | L61: =MAX(D61-K61,0) -> 726243.12 | M61: =MAX(I61-H61,0) -> 1669625
A62: 61 | B62: =J61 -> 1.6427704e+08 | C62: =IF(A62<=Inputs!B7,IF(B62>0,-PMT(Inputs!B6/12,Inputs!B7-A62+1,B62),0),0) -> 1153362 | D62: =B62*Inputs!B6/12 -> 787160.83 | E62: =MAX(C62-D62,0) -> 366201.2 | F62: =MAX((B62-E62)*Inputs!B18,0) -> 1134981.4 | G62: =MAX((B62-E62-F62)*Inputs!B19,0) -> 204882.23 | H62: =G62*Inputs!B17 -> 51220.559 | I62: =MIN(B62,E62+F62+G62) -> 1706064.8 | J62: =MAX(B62-I62,0) -> 1.6257098e+08 | K62: =B62*Inputs!B8/12 -> 68448.768 | L62: =MAX(D62-K62,0) -> 718712.06 | M62: =MAX(I62-H62,0) -> 1654844.3
A63: 62 | B63: =J62 -> 1.6257098e+08 | C63: =IF(A63<=Inputs!B7,IF(B63>0,-PMT(Inputs!B6/12,Inputs!B7-A63+1,B63),0),0) -> 1143934 | D63: =B63*Inputs!B6/12 -> 778985.94 | E63: =MAX(C63-D63,0) -> 364948.11 | F63: =MAX((B63-E63)*Inputs!B18,0) -> 1123176.6 | G63: =MAX((B63-E63-F63)*Inputs!B19,0) -> 202751.29 | H63: =G63*Inputs!B17 -> 50687.821 | I63: =MIN(B63,E63+F63+G63) -> 1690876 | J63: =MAX(B63-I63,0) -> 1.608801e+08 | K63: =B63*Inputs!B8/12 -> 67737.908 | L63: =MAX(D63-K63,0) -> 711248.03 | M63: =MAX(I63-H63,0) -> 1640188.2
A64: 63 | B64: =J63 -> 1.608801e+08 | C64: =IF(A64<=Inputs!B7,IF(B64>0,-PMT(Inputs!B6/12,Inputs!B7-A64+1,B64),0),0) -> 1134583.1 | D64: =B64*Inputs!B6/12 -> 770883.82 | E64: =MAX(C64-D64,0) -> 363699.32 | F64: =MAX((B64-E64)*Inputs!B18,0) -> 1111477 | G64: =MAX((B64-E64-F64)*Inputs!B19,0) -> 200639.32 | H64: =G64*Inputs!B17 -> 50159.829 | I64: =MIN(B64,E64+F64+G64) -> 1675815.6 | J64: =MAX(B64-I64,0) -> 1.5920429e+08 | K64: =B64*Inputs!B8/12 -> 67033.376 | L64: =MAX(D64-K64,0) -> 703850.45 | M64: =MAX(I64-H64,0) -> 1625655.8
A65: 64 | B65: =J64 -> 1.5920429e+08 | C65: =IF(A65<=Inputs!B7,IF(B65>0,-PMT(Inputs!B6/12,Inputs!B7-A65+1,B65),0),0) -> 1125308.7 | D65: =B65*Inputs!B6/12 -> 762853.87 | E65: =MAX(C65-D65,0) -> 362454.79 | F65: =MAX((B65-E65)*Inputs!B18,0) -> 1099881.6 | G65: =MAX((B65-E65-F65)*Inputs!B19,0) -> 198546.17 | H65: =G65*Inputs!B17 -> 49636.542 | I65: =MIN(B65,E65+F65+G65) -> 1660882.6 | J65: =MAX(B65-I65,0) -> 1.575434e+08 | K65: =B65*Inputs!B8/12 -> 66335.119 | L65: =MAX(D65-K65,0) -> 696518.75 | M65: =MAX(I65-H65,0) -> 1611246
A66: 65 | B66: =J65 -> 1.575434e+08 | C66: =IF(A66<=Inputs!B7,IF(B66>0,-PMT(Inputs!B6/12,Inputs!B7-A66+1,B66),0),0) -> 1116110 | D66: =B66*Inputs!B6/12 -> 754895.48 | E66: =MAX(C66-D66,0) -> 361214.53 | F66: =MAX((B66-E66)*Inputs!B18,0) -> 1088389.6 | G66: =MAX((B66-E66-F66)*Inputs!B19,0) -> 196471.68 | H66: =G66*Inputs!B17 -> 49117.92 | I66: =MIN(B66,E66+F66+G66) -> 1646075.8 | J66: =MAX(B66-I66,0) -> 1.5589733e+08 | K66: =B66*Inputs!B8/12 -> 65643.085 | L66: =MAX(D66-K66,0) -> 689252.39 | M66: =MAX(I66-H66,0) -> 1596957.9
A67: 66 | B67: =J66 -> 1.5589733e+08 | C67: =IF(A67<=Inputs!B7,IF(B67>0,-PMT(Inputs!B6/12,Inputs!B7-A67+1,B67),0),0) -> 1106986.5 | D67: =B67*Inputs!B6/12 -> 747008.03 | E67: =MAX(C67-D67,0) -> 359978.51 | F67: =MAX((B67-E67)*Inputs!B18,0) -> 1077000.1 | G67: =MAX((B67-E67-F67)*Inputs!B19,0) -> 194415.69 | H67: =G67*Inputs!B17 -> 48603.923 | I67: =MIN(B67,E67+F67+G67) -> 1631394.3 | J67: =MAX(B67-I67,0) -> 1.5426593e+08 | K67: =B67*Inputs!B8/12 -> 64957.22 | L67: =MAX(D67-K67,0) -> 682050.81 | M67: =MAX(I67-H67,0) -> 1582790.4
A68: 67 | B68: =J67 -> 1.5426593e+08 | C68: =IF(A68<=Inputs!B7,IF(B68>0,-PMT(Inputs!B6/12,Inputs!B7-A68+1,B68),0),0) -> 1097937.6 | D68: =B68*Inputs!B6/12 -> 739190.93 | E68: =MAX(C68-D68,0) -> 358746.72 | F68: =MAX((B68-E68)*Inputs!B18,0) -> 1065712.3 | G68: =MAX((B68-E68-F68)*Inputs!B19,0) -> 192378.05 | H68: =G68*Inputs!B17 -> 48094.513 | I68: =MIN(B68,E68+F68+G68) -> 1616837 | J68: =MAX(B68-I68,0) -> 1.526491e+08 | K68: =B68*Inputs!B8/12 -> 64277.473 | L68: =MAX(D68-K68,0) -> 674913.46 | M68: =MAX(I68-H68,0) -> 1568742.5
A69: 68 | B69: =J68 -> 1.526491e+08 | C69: =IF(A69<=Inputs!B7,IF(B69>0,-PMT(Inputs!B6/12,Inputs!B7-A69+1,B69),0),0) -> 1088962.7 | D69: =B69*Inputs!B6/12 -> 731443.59 | E69: =MAX(C69-D69,0) -> 357519.14 | F69: =MAX((B69-E69)*Inputs!B18,0) -> 1054525.2 | G69: =MAX((B69-E69-F69)*Inputs!B19,0) -> 190358.6 | H69: =G69*Inputs!B17 -> 47589.651 | I69: =MIN(B69,E69+F69+G69) -> 1602402.9 | J69: =MAX(B69-I69,0) -> 1.5104669e+08 | K69: =B69*Inputs!B8/12 -> 63603.79 | L69: =MAX(D69-K69,0) -> 667839.8 | M69: =MAX(I69-H69,0) -> 1554813.2
A70: 69 | B70: =J69 -> 1.5104669e+08 | C70: =IF(A70<=Inputs!B7,IF(B70>0,-PMT(Inputs!B6/12,Inputs!B7-A70+1,B70),0),0) -> 1080061.2 | D70: =B70*Inputs!B6/12 -> 723765.41 | E70: =MAX(C70-D70,0) -> 356295.76 | F70: =MAX((B70-E70)*Inputs!B18,0) -> 1043438 | G70: =MAX((B70-E70-F70)*Inputs!B19,0) -> 188357.19 | H70: =G70*Inputs!B17 -> 47089.297 | I70: =MIN(B70,E70+F70+G70) -> 1588090.9 | J70: =MAX(B70-I70,0) -> 1.494586e+08 | K70: =B70*Inputs!B8/12 -> 62936.123 | L70: =MAX(D70-K70,0) -> 660829.29 | M70: =MAX(I70-H70,0) -> 1541001.6
A71: 70 | B71: =J70 -> 1.494586e+08 | C71: =IF(A71<=Inputs!B7,IF(B71>0,-PMT(Inputs!B6/12,Inputs!B7-A71+1,B71),0),0) -> 1071232.4 | D71: =B71*Inputs!B6/12 -> 716155.81 | E71: =MAX(C71-D71,0) -> 355076.58 | F71: =MAX((B71-E71)*Inputs!B18,0) -> 1032449.9 | G71: =MAX((B71-E71-F71)*Inputs!B19,0) -> 186373.66 | H71: =G71*Inputs!B17 -> 46593.415 | I71: =MIN(B71,E71+F71+G71) -> 1573900.1 | J71: =MAX(B71-I71,0) -> 1.478847e+08 | K71: =B71*Inputs!B8/12 -> 62274.418 | L71: =MAX(D71-K71,0) -> 653881.39 | M71: =MAX(I71-H71,0) -> 1527306.7
A72: 71 | B72: =J71 -> 1.478847e+08 | C72: =IF(A72<=Inputs!B7,IF(B72>0,-PMT(Inputs!B6/12,Inputs!B7-A72+1,B72),0),0) -> 1062475.8 | D72: =B72*Inputs!B6/12 -> 708614.2 | E72: =MAX(C72-D72,0) -> 353861.56 | F72: =MAX((B72-E72)*Inputs!B18,0) -> 1021560 | G72: =MAX((B72-E72-F72)*Inputs!B19,0) -> 184407.87 | H72: =G72*Inputs!B17 -> 46101.966 | I72: =MIN(B72,E72+F72+G72) -> 1559829.4 | J72: =MAX(B72-I72,0) -> 1.4632487e+08 | K72: =B72*Inputs!B8/12 -> 61618.626 | L72: =MAX(D72-K72,0) -> 646995.58 | M72: =MAX(I72-H72,0) -> 1513727.5
A73: 72 | B73: =J72 -> 1.4632487e+08 | C73: =IF(A73<=Inputs!B7,IF(B73>0,-PMT(Inputs!B6/12,Inputs!B7-A73+1,B73),0),0) -> 1053790.7 | D73: =B73*Inputs!B6/12 -> 701140.02 | E73: =MAX(C73-D73,0) -> 352650.7 | F73: =MAX((B73-E73)*Inputs!B18,0) -> 1010767.5 | G73: =MAX((B73-E73-F73)*Inputs!B19,0) -> 182459.65 | H73: =G73*Inputs!B17 -> 45614.913 | I73: =MIN(B73,E73+F73+G73) -> 1545877.9 | J73: =MAX(B73-I73,0) -> 1.44779e+08 | K73: =B73*Inputs!B8/12 -> 60968.697 | L73: =MAX(D73-K73,0) -> 640171.32 | M73: =MAX(I73-H73,0) -> 1500263
A74: 73 | B74: =J73 -> 1.44779e+08 | C74: =IF(A74<=Inputs!B7,IF(B74>0,-PMT(Inputs!B6/12,Inputs!B7-A74+1,B74),0),0) -> 1045176.7 | D74: =B74*Inputs!B6/12 -> 693732.69 | E74: =MAX(C74-D74,0) -> 351443.98 | F74: =MAX((B74-E74)*Inputs!B18,0) -> 1000071.6 | G74: =MAX((B74-E74-F74)*Inputs!B19,0) -> 180528.87 | H74: =G74*Inputs!B17 -> 45132.218 | I74: =MIN(B74,E74+F74+G74) -> 1532044.5 | J74: =MAX(B74-I74,0) -> 1.4324695e+08 | K74: =B74*Inputs!B8/12 -> 60324.582 | L74: =MAX(D74-K74,0) -> 633408.11 | M74: =MAX(I74-H74,0) -> 1486912.3
A75: 74 | B75: =J74 -> 1.4324695e+08 | C75: =IF(A75<=Inputs!B7,IF(B75>0,-PMT(Inputs!B6/12,Inputs!B7-A75+1,B75),0),0) -> 1036633 | D75: =B75*Inputs!B6/12 -> 686391.64 | E75: =MAX(C75-D75,0) -> 350241.39 | F75: =MAX((B75-E75)*Inputs!B18,0) -> 989471.5 | G75: =MAX((B75-E75-F75)*Inputs!B19,0) -> 178615.38 | H75: =G75*Inputs!B17 -> 44653.845 | I75: =MIN(B75,E75+F75+G75) -> 1518328.3 | J75: =MAX(B75-I75,0) -> 1.4172862e+08 | K75: =B75*Inputs!B8/12 -> 59686.23 | L75: =MAX(D75-K75,0) -> 626705.41 | M75: =MAX(I75-H75,0) -> 1473674.4
A76: 75 | B76: =J75 -> 1.4172862e+08 | C76: =IF(A76<=Inputs!B7,IF(B76>0,-PMT(Inputs!B6/12,Inputs!B7-A76+1,B76),0),0) -> 1028159.2 | D76: =B76*Inputs!B6/12 -> 679116.32 | E76: =MAX(C76-D76,0) -> 349042.92 | F76: =MAX((B76-E76)*Inputs!B18,0) -> 978966.31 | G76: =MAX((B76-E76-F76)*Inputs!B19,0) -> 176719.03 | H76: =G76*Inputs!B17 -> 44179.756 | I76: =MIN(B76,E76+F76+G76) -> 1504728.3 | J76: =MAX(B76-I76,0) -> 1.4022389e+08 | K76: =B76*Inputs!B8/12 -> 59053.593 | L76: =MAX(D76-K76,0) -> 620062.73 | M76: =MAX(I76-H76,0) -> 1460548.5
A77: 76 | B77: =J76 -> 1.4022389e+08 | C77: =IF(A77<=Inputs!B7,IF(B77>0,-PMT(Inputs!B6/12,Inputs!B7-A77+1,B77),0),0) -> 1019754.7 | D77: =B77*Inputs!B6/12 -> 671906.16 | E77: =MAX(C77-D77,0) -> 347848.55 | F77: =MAX((B77-E77)*Inputs!B18,0) -> 968555.26 | G77: =MAX((B77-E77-F77)*Inputs!B19,0) -> 174839.67 | H77: =G77*Inputs!B17 -> 43709.917 | I77: =MIN(B77,E77+F77+G77) -> 1491243.5 | J77: =MAX(B77-I77,0) -> 1.3873265e+08 | K77: =B77*Inputs!B8/12 -> 58426.623 | L77: =MAX(D77-K77,0) -> 613479.54 | M77: =MAX(I77-H77,0) -> 1447533.6
A78: 77 | B78: =J77 -> 1.3873265e+08 | C78: =IF(A78<=Inputs!B7,IF(B78>0,-PMT(Inputs!B6/12,Inputs!B7-A78+1,B78),0),0) -> 1011418.9 | D78: =B78*Inputs!B6/12 -> 664760.62 | E78: =MAX(C78-D78,0) -> 346658.27 | F78: =MAX((B78-E78)*Inputs!B18,0) -> 958237.57 | G78: =MAX((B78-E78-F78)*Inputs!B19,0) -> 172977.16 | H78: =G78*Inputs!B17 -> 43244.289 | I78: =MIN(B78,E78+F78+G78) -> 1477873 | J78: =MAX(B78-I78,0) -> 1.3725478e+08 | K78: =B78*Inputs!B8/12 -> 57805.271 | L78: =MAX(D78-K78,0) -> 606955.35 | M78: =MAX(I78-H78,0) -> 1434628.7
A79: 78 | B79: =J78 -> 1.3725478e+08 | C79: =IF(A79<=Inputs!B7,IF(B79>0,-PMT(Inputs!B6/12,Inputs!B7-A79+1,B79),0),0) -> 1003151.2 | D79: =B79*Inputs!B6/12 -> 657679.15 | E79: =MAX(C79-D79,0) -> 345472.06 | F79: =MAX((B79-E79)*Inputs!B18,0) -> 948012.42 | G79: =MAX((B79-E79-F79)*Inputs!B19,0) -> 171131.36 | H79: =G79*Inputs!B17 -> 42782.839 | I79: =MIN(B79,E79+F79+G79) -> 1464615.8 | J79: =MAX(B79-I79,0) -> 1.3579016e+08 | K79: =B79*Inputs!B8/12 -> 57189.491 | L79: =MAX(D79-K79,0) -> 600489.66 | M79: =MAX(I79-H79,0) -> 1421833
A80: 79 | B80: =J79 -> 1.3579016e+08 | C80: =IF(A80<=Inputs!B7,IF(B80>0,-PMT(Inputs!B6/12,Inputs!B7-A80+1,B80),0),0) -> 994951.1 | D80: =B80*Inputs!B6/12 -> 650661.2 | E80: =MAX(C80-D80,0) -> 344289.9 | F80: =MAX((B80-E80)*Inputs!B18,0) -> 937879.05 | G80: =MAX((B80-E80-F80)*Inputs!B19,0) -> 169302.12 | H80: =G80*Inputs!B17 -> 42325.53 | I80: =MIN(B80,E80+F80+G80) -> 1451471.1 | J80: =MAX(B80-I80,0) -> 1.3433869e+08 | K80: =B80*Inputs!B8/12 -> 56579.234 | L80: =MAX(D80-K80,0) -> 594081.96 | M80: =MAX(I80-H80,0) -> 1409145.5
A81: 80 | B81: =J80 -> 1.3433869e+08 | C81: =IF(A81<=Inputs!B7,IF(B81>0,-PMT(Inputs!B6/12,Inputs!B7-A81+1,B81),0),0) -> 986818.03 | D81: =B81*Inputs!B6/12 -> 643706.23 | E81: =MAX(C81-D81,0) -> 343111.8 | F81: =MAX((B81-E81)*Inputs!B18,0) -> 927836.66 | G81: =MAX((B81-E81-F81)*Inputs!B19,0) -> 167489.31 | H81: =G81*Inputs!B17 -> 41872.327 | I81: =MIN(B81,E81+F81+G81) -> 1438437.8 | J81: =MAX(B81-I81,0) -> 1.3290025e+08 | K81: =B81*Inputs!B8/12 -> 55974.455 | L81: =MAX(D81-K81,0) -> 587731.77 | M81: =MAX(I81-H81,0) -> 1396565.4
A82: 81 | B82: =J81 -> 1.3290025e+08 | C82: =IF(A82<=Inputs!B7,IF(B82>0,-PMT(Inputs!B6/12,Inputs!B7-A82+1,B82),0),0) -> 978751.44 | D82: =B82*Inputs!B6/12 -> 636813.72 | E82: =MAX(C82-D82,0) -> 341937.72 | F82: =MAX((B82-E82)*Inputs!B18,0) -> 917884.5 | G82: =MAX((B82-E82-F82)*Inputs!B19,0) -> 165692.79 | H82: =G82*Inputs!B17 -> 41423.196 | I82: =MIN(B82,E82+F82+G82) -> 1425515 | J82: =MAX(B82-I82,0) -> 1.3147474e+08 | K82: =B82*Inputs!B8/12 -> 55375.106 | L82: =MAX(D82-K82,0) -> 581438.61 | M82: =MAX(I82-H82,0) -> 1384091.8
A83: 82 | B83: =J82 -> 1.3147474e+08 | C83: =IF(A83<=Inputs!B7,IF(B83>0,-PMT(Inputs!B6/12,Inputs!B7-A83+1,B83),0),0) -> 970750.78 | D83: =B83*Inputs!B6/12 -> 629983.12 | E83: =MAX(C83-D83,0) -> 340767.66 | F83: =MAX((B83-E83)*Inputs!B18,0) -> 908021.79 | G83: =MAX((B83-E83-F83)*Inputs!B19,0) -> 163912.41 | H83: =G83*Inputs!B17 -> 40978.102 | I83: =MIN(B83,E83+F83+G83) -> 1412701.9 | J83: =MAX(B83-I83,0) -> 1.3006204e+08 | K83: =B83*Inputs!B8/12 -> 54781.141 | L83: =MAX(D83-K83,0) -> 575201.98 | M83: =MAX(I83-H83,0) -> 1371723.8
A84: 83 | B84: =J83 -> 1.3006204e+08 | C84: =IF(A84<=Inputs!B7,IF(B84>0,-PMT(Inputs!B6/12,Inputs!B7-A84+1,B84),0),0) -> 962815.53 | D84: =B84*Inputs!B6/12 -> 623213.93 | E84: =MAX(C84-D84,0) -> 339601.61 | F84: =MAX((B84-E84)*Inputs!B18,0) -> 898247.78 | G84: =MAX((B84-E84-F84)*Inputs!B19,0) -> 162148.04 | H84: =G84*Inputs!B17 -> 40537.011 | I84: =MIN(B84,E84+F84+G84) -> 1399997.4 | J84: =MAX(B84-I84,0) -> 1.2866204e+08 | K84: =B84*Inputs!B8/12 -> 54192.515 | L84: =MAX(D84-K84,0) -> 569021.41 | M84: =MAX(I84-H84,0) -> 1359460.4
A85: 84 | B85: =J84 -> 1.2866204e+08 | C85: =IF(A85<=Inputs!B7,IF(B85>0,-PMT(Inputs!B6/12,Inputs!B7-A85+1,B85),0),0) -> 954945.15 | D85: =B85*Inputs!B6/12 -> 616505.61 | E85: =MAX(C85-D85,0) -> 338439.54 | F85: =MAX((B85-E85)*Inputs!B18,0) -> 888561.71 | G85: =MAX((B85-E85-F85)*Inputs!B19,0) -> 160399.55 | H85: =G85*Inputs!B17 -> 40099.888 | I85: =MIN(B85,E85+F85+G85) -> 1387400.8 | J85: =MAX(B85-I85,0) -> 1.2727464e+08 | K85: =B85*Inputs!B8/12 -> 53609.183 | L85: =MAX(D85-K85,0) -> 562896.42 | M85: =MAX(I85-H85,0) -> 1347300.9
A86: 85 | B86: =J85 -> 1.2727464e+08 | C86: =IF(A86<=Inputs!B7,IF(B86>0,-PMT(Inputs!B6/12,Inputs!B7-A86+1,B86),0),0) -> 947139.1 | D86: =B86*Inputs!B6/12 -> 609857.64 | E86: =MAX(C86-D86,0) -> 337281.45 | F86: =MAX((B86-E86)*Inputs!B18,0) -> 878962.83 | G86: =MAX((B86-E86-F86)*Inputs!B19,0) -> 158666.8 | H86: =G86*Inputs!B17 -> 39666.701 | I86: =MIN(B86,E86+F86+G86) -> 1374911.1 | J86: =MAX(B86-I86,0) -> 1.2589973e+08 | K86: =B86*Inputs!B8/12 -> 53031.099 | L86: =MAX(D86-K86,0) -> 556826.54 | M86: =MAX(I86-H86,0) -> 1335244.4
A87: 86 | B87: =J86 -> 1.2589973e+08 | C87: =IF(A87<=Inputs!B7,IF(B87>0,-PMT(Inputs!B6/12,Inputs!B7-A87+1,B87),0),0) -> 939396.86 | D87: =B87*Inputs!B6/12 -> 603269.53 | E87: =MAX(C87-D87,0) -> 336127.33 | F87: =MAX((B87-E87)*Inputs!B18,0) -> 869450.41 | G87: =MAX((B87-E87-F87)*Inputs!B19,0) -> 156949.66 | H87: =G87*Inputs!B17 -> 39237.415 | I87: =MIN(B87,E87+F87+G87) -> 1362527.4 | J87: =MAX(B87-I87,0) -> 1.245372e+08 | K87: =B87*Inputs!B8/12 -> 52458.22 | L87: =MAX(D87-K87,0) -> 550811.31 | M87: =MAX(I87-H87,0) -> 1323290
A88: 87 | B88: =J87 -> 1.245372e+08 | C88: =IF(A88<=Inputs!B7,IF(B88>0,-PMT(Inputs!B6/12,Inputs!B7-A88+1,B88),0),0) -> 931717.9 | D88: =B88*Inputs!B6/12 -> 596740.75 | E88: =MAX(C88-D88,0) -> 334977.15 | F88: =MAX((B88-E88)*Inputs!B18,0) -> 860023.71 | G88: =MAX((B88-E88-F88)*Inputs!B19,0) -> 155247.99 | H88: =G88*Inputs!B17 -> 38811.998 | I88: =MIN(B88,E88+F88+G88) -> 1350248.9 | J88: =MAX(B88-I88,0) -> 1.2318695e+08 | K88: =B88*Inputs!B8/12 -> 51890.5 | L88: =MAX(D88-K88,0) -> 544850.25 | M88: =MAX(I88-H88,0) -> 1311436.9
A89: 88 | B89: =J88 -> 1.2318695e+08 | C89: =IF(A89<=Inputs!B7,IF(B89>0,-PMT(Inputs!B6/12,Inputs!B7-A89+1,B89),0),0) -> 924101.72 | D89: =B89*Inputs!B6/12 -> 590270.81 | E89: =MAX(C89-D89,0) -> 333830.91 | F89: =MAX((B89-E89)*Inputs!B18,0) -> 850682.01 | G89: =MAX((B89-E89-F89)*Inputs!B19,0) -> 153561.67 | H89: =G89*Inputs!B17 -> 38390.416 | I89: =MIN(B89,E89+F89+G89) -> 1338074.6 | J89: =MAX(B89-I89,0) -> 1.2184888e+08 | K89: =B89*Inputs!B8/12 -> 51327.896 | L89: =MAX(D89-K89,0) -> 538942.91 | M89: =MAX(I89-H89,0) -> 1299684.2
A90: 89 | B90: =J89 -> 1.2184888e+08 | C90: =IF(A90<=Inputs!B7,IF(B90>0,-PMT(Inputs!B6/12,Inputs!B7-A90+1,B90),0),0) -> 916547.8 | D90: =B90*Inputs!B6/12 -> 583859.2 | E90: =MAX(C90-D90,0) -> 332688.6 | F90: =MAX((B90-E90)*Inputs!B18,0) -> 841424.58 | G90: =MAX((B90-E90-F90)*Inputs!B19,0) -> 151890.55 | H90: =G90*Inputs!B17 -> 37972.638 | I90: =MIN(B90,E90+F90+G90) -> 1326003.7 | J90: =MAX(B90-I90,0) -> 1.2052287e+08 | K90: =B90*Inputs!B8/12 -> 50770.365 | L90: =MAX(D90-K90,0) -> 533088.84 | M90: =MAX(I90-H90,0) -> 1288031.1
A91: 90 | B91: =J90 -> 1.2052287e+08 | C91: =IF(A91<=Inputs!B7,IF(B91>0,-PMT(Inputs!B6/12,Inputs!B7-A91+1,B91),0),0) -> 909055.62 | D91: =B91*Inputs!B6/12 -> 577505.43 | E91: =MAX(C91-D91,0) -> 331550.19 | F91: =MAX((B91-E91)*Inputs!B18,0) -> 832250.71 | G91: =MAX((B91-E91-F91)*Inputs!B19,0) -> 150234.52 | H91: =G91*Inputs!B17 -> 37558.63 | I91: =MIN(B91,E91+F91+G91) -> 1314035.4 | J91: =MAX(B91-I91,0) -> 1.1920884e+08 | K91: =B91*Inputs!B8/12 -> 50217.864 | L91: =MAX(D91-K91,0) -> 527287.57 | M91: =MAX(I91-H91,0) -> 1276476.8
A92: 91 | B92: =J91 -> 1.1920884e+08 | C92: =IF(A92<=Inputs!B7,IF(B92>0,-PMT(Inputs!B6/12,Inputs!B7-A92+1,B92),0),0) -> 901624.69 | D92: =B92*Inputs!B6/12 -> 571209.01 | E92: =MAX(C92-D92,0) -> 330415.67 | F92: =MAX((B92-E92)*Inputs!B18,0) -> 823159.68 | G92: =MAX((B92-E92-F92)*Inputs!B19,0) -> 148593.45 | H92: =G92*Inputs!B17 -> 37148.361 | I92: =MIN(B92,E92+F92+G92) -> 1302168.8 | J92: =MAX(B92-I92,0) -> 1.1790667e+08 | K92: =B92*Inputs!B8/12 -> 49670.349 | L92: =MAX(D92-K92,0) -> 521538.66 | M92: =MAX(I92-H92,0) -> 1265020.4
A93: 92 | B93: =J92 -> 1.1790667e+08 | C93: =IF(A93<=Inputs!B7,IF(B93>0,-PMT(Inputs!B6/12,Inputs!B7-A93+1,B93),0),0) -> 894254.49 | D93: =B93*Inputs!B6/12 -> 564969.45 | E93: =MAX(C93-D93,0) -> 329285.04 | F93: =MAX((B93-E93)*Inputs!B18,0) -> 814150.79 | G93: =MAX((B93-E93-F93)*Inputs!B19,0) -> 146967.2 | H93: =G93*Inputs!B17 -> 36741.799 | I93: =MIN(B93,E93+F93+G93) -> 1290403 | J93: =MAX(B93-I93,0) -> 1.1661627e+08 | K93: =B93*Inputs!B8/12 -> 49127.779 | L93: =MAX(D93-K93,0) -> 515841.68 | M93: =MAX(I93-H93,0) -> 1253661.2
A94: 93 | B94: =J93 -> 1.1661627e+08 | C94: =IF(A94<=Inputs!B7,IF(B94>0,-PMT(Inputs!B6/12,Inputs!B7-A94+1,B94),0),0) -> 886944.55 | D94: =B94*Inputs!B6/12 -> 558786.27 | E94: =MAX(C94-D94,0) -> 328158.28 | F94: =MAX((B94-E94)*Inputs!B18,0) -> 805223.35 | G94: =MAX((B94-E94-F94)*Inputs!B19,0) -> 145355.65 | H94: =G94*Inputs!B17 -> 36338.913 | I94: =MIN(B94,E94+F94+G94) -> 1278737.3 | J94: =MAX(B94-I94,0) -> 1.1533753e+08 | K94: =B94*Inputs!B8/12 -> 48590.111 | L94: =MAX(D94-K94,0) -> 510196.16 | M94: =MAX(I94-H94,0) -> 1242398.4
A95: 94 | B95: =J94 -> 1.1533753e+08 | C95: =IF(A95<=Inputs!B7,IF(B95>0,-PMT(Inputs!B6/12,Inputs!B7-A95+1,B95),0),0) -> 879694.36 | D95: =B95*Inputs!B6/12 -> 552658.99 | E95: =MAX(C95-D95,0) -> 327035.37 | F95: =MAX((B95-E95)*Inputs!B18,0) -> 796376.66 | G95: =MAX((B95-E95-F95)*Inputs!B19,0) -> 143758.68 | H95: =G95*Inputs!B17 -> 35939.671 | I95: =MIN(B95,E95+F95+G95) -> 1267170.7 | J95: =MAX(B95-I95,0) -> 1.1407036e+08 | K95: =B95*Inputs!B8/12 -> 48057.303 | L95: =MAX(D95-K95,0) -> 504601.69 | M95: =MAX(I95-H95,0) -> 1231231
A96: 95 | B96: =J95 -> 1.1407036e+08 | C96: =IF(A96<=Inputs!B7,IF(B96>0,-PMT(Inputs!B6/12,Inputs!B7-A96+1,B96),0),0) -> 872503.44 | D96: =B96*Inputs!B6/12 -> 546587.13 | E96: =MAX(C96-D96,0) -> 325916.31 | F96: =MAX((B96-E96)*Inputs!B18,0) -> 787610.03 | G96: =MAX((B96-E96-F96)*Inputs!B19,0) -> 142176.17 | H96: =G96*Inputs!B17 -> 35544.042 | I96: =MIN(B96,E96+F96+G96) -> 1255702.5 | J96: =MAX(B96-I96,0) -> 1.1281466e+08 | K96: =B96*Inputs!B8/12 -> 47529.316 | L96: =MAX(D96-K96,0) -> 499057.81 | M96: =MAX(I96-H96,0) -> 1220158.5
A97: 96 | B97: =J96 -> 1.1281466e+08 | C97: =IF(A97<=Inputs!B7,IF(B97>0,-PMT(Inputs!B6/12,Inputs!B7-A97+1,B97),0),0) -> 865371.29 | D97: =B97*Inputs!B6/12 -> 540570.22 | E97: =MAX(C97-D97,0) -> 324801.07 | F97: =MAX((B97-E97)*Inputs!B18,0) -> 778922.79 | G97: =MAX((B97-E97-F97)*Inputs!B19,0) -> 140607.98 | H97: =G97*Inputs!B17 -> 35151.995 | I97: =MIN(B97,E97+F97+G97) -> 1244331.8 | J97: =MAX(B97-I97,0) -> 1.1157032e+08 | K97: =B97*Inputs!B8/12 -> 47006.106 | L97: =MAX(D97-K97,0) -> 493564.12 | M97: =MAX(I97-H97,0) -> 1209179.8
A98: 97 | B98: =J97 -> 1.1157032e+08 | C98: =IF(A98<=Inputs!B7,IF(B98>0,-PMT(Inputs!B6/12,Inputs!B7-A98+1,B98),0),0) -> 858297.45 | D98: =B98*Inputs!B6/12 -> 534607.8 | E98: =MAX(C98-D98,0) -> 323689.65 | F98: =MAX((B98-E98)*Inputs!B18,0) -> 770314.26 | G98: =MAX((B98-E98-F98)*Inputs!B19,0) -> 139054 | H98: =G98*Inputs!B17 -> 34763.501 | I98: =MIN(B98,E98+F98+G98) -> 1233057.9 | J98: =MAX(B98-I98,0) -> 1.1033727e+08 | K98: =B98*Inputs!B8/12 -> 46487.635 | L98: =MAX(D98-K98,0) -> 488120.16 | M98: =MAX(I98-H98,0) -> 1198294.4
A99: 98 | B99: =J98 -> 1.1033727e+08 | C99: =IF(A99<=Inputs!B7,IF(B99>0,-PMT(Inputs!B6/12,Inputs!B7-A99+1,B99),0),0) -> 851281.43 | D99: =B99*Inputs!B6/12 -> 528699.4 | E99: =MAX(C99-D99,0) -> 322582.04 | F99: =MAX((B99-E99)*Inputs!B18,0) -> 761783.76 | G99: =MAX((B99-E99-F99)*Inputs!B19,0) -> 137514.11 | H99: =G99*Inputs!B17 -> 34378.528 | I99: =MIN(B99,E99+F99+G99) -> 1221879.9 | J99: =MAX(B99-I99,0) -> 1.0911539e+08 | K99: =B99*Inputs!B8/12 -> 45973.861 | L99: =MAX(D99-K99,0) -> 482725.54 | M99: =MAX(I99-H99,0) -> 1187501.4
A100: 99 | B100: =J99 -> 1.0911539e+08 | C100: =IF(A100<=Inputs!B7,IF(B100>0,-PMT(Inputs!B6/12,Inputs!B7-A100+1,B100),0),0) -> 844322.76 | D100: =B100*Inputs!B6/12 -> 522844.56 | E100: =MAX(C100-D100,0) -> 321478.21 | F100: =MAX((B100-E100)*Inputs!B18,0) -> 753330.64 | G100: =MAX((B100-E100-F100)*Inputs!B19,0) -> 135988.19 | H100: =G100*Inputs!B17 -> 33997.048 | I100: =MIN(B100,E100+F100+G100) -> 1210797 | J100: =MAX(B100-I100,0) -> 1.0790459e+08 | K100: =B100*Inputs!B8/12 -> 45464.744 | L100: =MAX(D100-K100,0) -> 477379.81 | M100: =MAX(I100-H100,0) -> 1176800
...

Sheet Waterfall
A1: Month | B1: Pool_Interest_Available | C1: Pool_Principal_Available | D1: Pool_Loss | E1: A_Begin | F1: B_Begin | G1: E_Begin | H1: Loss_to_E | I1: Loss_to_B | J1: Loss_to_A | K1: A_After_Loss | L1: B_After_Loss | M1: E_After_Loss | N1: A_Int_Due | O1: A_Int_Paid | P1: A_Int_Shortfall | Q1: B_Int_Due | R1: B_Int_Paid | S1: B_Int_Shortfall | T1: E_Residual_Int | U1: A_Principal_Paid | V1: B_Principal_Paid | W1: E_Principal_Paid | X1: A_End | Y1: B_End | Z1: E_End | AA1: Principal_Diff | AB1: Interest_Diff | AC1: Loss_Diff
A2: 1 | B2: =LoanPool!L2 -> 1312500 | C2: =LoanPool!M2 -> 2804838.9 | D2: =LoanPool!H2 -> 93606.545 | E2: =Inputs!B3*Inputs!B9 -> 240000000 | F2: =Inputs!B3*Inputs!B10 -> 45000000 | G2: =Inputs!B3*Inputs!B11 -> 15000000 | H2: =MIN(D2,G2) -> 93606.545 | I2: =MIN(MAX(D2-H2,0),F2) -> 0 | J2: =MIN(MAX(D2-H2-I2,0),E2) -> 0 | K2: =MAX(E2-J2,0) -> 240000000 | L2: =MAX(F2-I2,0) -> 45000000 | M2: =MAX(G2-H2,0) -> 14906393 | N2: =K2*Inputs!B6/12 -> 1150000 | O2: =MIN(B2,N2) -> 1150000 | P2: =N2-O2 -> 0 | Q2: =L2*Inputs!B6/12 -> 215625 | R2: =MIN(MAX(B2-O2,0),Q2) -> 162500 | S2: =Q2-R2 -> 53125 | T2: =MAX(B2-O2-R2,0) -> 0 | U2: =MIN(C2,K2) -> 2804838.9 | V2: =MIN(MAX(C2-U2,0),L2) -> 0 | W2: =MIN(MAX(C2-U2-V2,0),M2) -> 0 | X2: =MAX(K2-U2,0) -> 2.3719516e+08 | Y2: =MAX(L2-V2,0) -> 45000000 | Z2: =MAX(M2-W2,0) -> 14906393 | AA2: =C2-(U2+V2+W2) -> 0 | AB2: =B2-(O2+R2+T2) -> 0 | AC2: =D2-(H2+I2+J2) -> 0
A3: 2 | B3: =LoanPool!L3 -> 1299819.3 | C3: =LoanPool!M3 -> 2780524.6 | D3: =LoanPool!H3 -> 92701.29 | E3: =X2 -> 2.3719516e+08 | F3: =Y2 -> 45000000 | G3: =Z2 -> 14906393 | H3: =MIN(D3,G3) -> 92701.29 | I3: =MIN(MAX(D3-H3,0),F3) -> 0 | J3: =MIN(MAX(D3-H3-I3,0),E3) -> 0 | K3: =MAX(E3-J3,0) -> 2.3719516e+08 | L3: =MAX(F3-I3,0) -> 45000000 | M3: =MAX(G3-H3,0) -> 14813692 | N3: =K3*Inputs!B6/12 -> 1136560.1 | O3: =MIN(B3,N3) -> 1136560.1 | P3: =N3-O3 -> 0 | Q3: =L3*Inputs!B6/12 -> 215625 | R3: =MIN(MAX(B3-O3,0),Q3) -> 163259.15 | S3: =Q3-R3 -> 52365.846 | T3: =MAX(B3-O3-R3,0) -> 0 | U3: =MIN(C3,K3) -> 2780524.6 | V3: =MIN(MAX(C3-U3,0),L3) -> 0 | W3: =MIN(MAX(C3-U3-V3,0),M3) -> 0 | X3: =MAX(K3-U3,0) -> 2.3441464e+08 | Y3: =MAX(L3-V3,0) -> 45000000 | Z3: =MAX(M3-W3,0) -> 14813692 | AA3: =C3-(U3+V3+W3) -> 0 | AB3: =B3-(O3+R3+T3) -> 0 | AC3: =D3-(H3+I3+J3) -> 0
A4: 3 | B4: =LoanPool!L4 -> 1287248.9 | C4: =LoanPool!M4 -> 2756413.9 | D4: =LoanPool!H4 -> 91803.914 | E4: =X3 -> 2.3441464e+08 | F4: =Y3 -> 45000000 | G4: =Z3 -> 14813692 | H4: =MIN(D4,G4) -> 91803.914 | I4: =MIN(MAX(D4-H4,0),F4) -> 0 | J4: =MIN(MAX(D4-H4-I4,0),E4) -> 0 | K4: =MAX(E4-J4,0) -> 2.3441464e+08 | L4: =MAX(F4-I4,0) -> 45000000 | M4: =MAX(G4-H4,0) -> 14721888 | N4: =K4*Inputs!B6/12 -> 1123236.8 | O4: =MIN(B4,N4) -> 1123236.8 | P4: =N4-O4 -> 0 | Q4: =L4*Inputs!B6/12 -> 215625 | R4: =MIN(MAX(B4-O4,0),Q4) -> 164012.14 | S4: =Q4-R4 -> 51612.862 | T4: =MAX(B4-O4-R4,0) -> 0 | U4: =MIN(C4,K4) -> 2756413.9 | V4: =MIN(MAX(C4-U4,0),L4) -> 0 | W4: =MIN(MAX(C4-U4-V4,0),M4) -> 0 | X4: =MAX(K4-U4,0) -> 2.3165822e+08 | Y4: =MAX(L4-V4,0) -> 45000000 | Z4: =MAX(M4-W4,0) -> 14721888 | AA4: =C4-(U4+V4+W4) -> 0 | AB4: =B4-(O4+R4+T4) -> 0 | AC4: =D4-(H4+I4+J4) -> 0
A5: 4 | B5: =LoanPool!L5 -> 1274788 | C5: =LoanPool!M5 -> 2732504.9 | D5: =LoanPool!H5 -> 90914.351 | E5: =X4 -> 2.3165822e+08 | F5: =Y4 -> 45000000 | G5: =Z4 -> 14721888 | H5: =MIN(D5,G5) -> 90914.351 | I5: =MIN(MAX(D5-H5,0),F5) -> 0 | J5: =MIN(MAX(D5-H5-I5,0),E5) -> 0 | K5: =MAX(E5-J5,0) -> 2.3165822e+08 | L5: =MAX(F5-I5,0) -> 45000000 | M5: =MAX(G5-H5,0) -> 14630974 | N5: =K5*Inputs!B6/12 -> 1110029 | O5: =MIN(B5,N5) -> 1110029 | P5: =N5-O5 -> 0 | Q5: =L5*Inputs!B6/12 -> 215625 | R5: =MIN(MAX(B5-O5,0),Q5) -> 164759 | S5: =Q5-R5 -> 50865.998 | T5: =MAX(B5-O5-R5,0) -> 0 | U5: =MIN(C5,K5) -> 2732504.9 | V5: =MIN(MAX(C5-U5,0),L5) -> 0 | W5: =MIN(MAX(C5-U5-V5,0),M5) -> 0 | X5: =MAX(K5-U5,0) -> 2.2892572e+08 | Y5: =MAX(L5-V5,0) -> 45000000 | Z5: =MAX(M5-W5,0) -> 14630974 | AA5: =C5-(U5+V5+W5) -> 0 | AB5: =B5-(O5+R5+T5) -> 0 | AC5: =D5-(H5+I5+J5) -> 0
A6: 5 | B6: =LoanPool!L6 -> 1262435.5 | C6: =LoanPool!M6 -> 2708796.1 | D6: =LoanPool!H6 -> 90032.536 | E6: =X5 -> 2.2892572e+08 | F6: =Y5 -> 45000000 | G6: =Z5 -> 14630974 | H6: =MIN(D6,G6) -> 90032.536 | I6: =MIN(MAX(D6-H6,0),F6) -> 0 | J6: =MIN(MAX(D6-H6-I6,0),E6) -> 0 | K6: =MAX(E6-J6,0) -> 2.2892572e+08 | L6: =MAX(F6-I6,0) -> 45000000 | M6: =MAX(G6-H6,0) -> 14540941 | N6: =K6*Inputs!B6/12 -> 1096935.7 | O6: =MIN(B6,N6) -> 1096935.7 | P6: =N6-O6 -> 0 | Q6: =L6*Inputs!B6/12 -> 215625 | R6: =MIN(MAX(B6-O6,0),Q6) -> 165499.8 | S6: =Q6-R6 -> 50125.205 | T6: =MAX(B6-O6-R6,0) -> 0 | U6: =MIN(C6,K6) -> 2708796.1 | V6: =MIN(MAX(C6-U6,0),L6) -> 0 | W6: =MIN(MAX(C6-U6-V6,0),M6) -> 0 | X6: =MAX(K6-U6,0) -> 2.2621692e+08 | Y6: =MAX(L6-V6,0) -> 45000000 | Z6: =MAX(M6-W6,0) -> 14540941 | AA6: =C6-(U6+V6+W6) -> 0 | AB6: =B6-(O6+R6+T6) -> 0 | AC6: =D6-(H6+I6+J6) -> 0
A7: 6 | B7: =LoanPool!L7 -> 1250190.7 | C7: =LoanPool!M7 -> 2685285.8 | D7: =LoanPool!H7 -> 89158.403 | E7: =X6 -> 2.2621692e+08 | F7: =Y6 -> 45000000 | G7: =Z6 -> 14540941 | H7: =MIN(D7,G7) -> 89158.403 | I7: =MIN(MAX(D7-H7,0),F7) -> 0 | J7: =MIN(MAX(D7-H7-I7,0),E7) -> 0 | K7: =MAX(E7-J7,0) -> 2.2621692e+08 | L7: =MAX(F7-I7,0) -> 45000000 | M7: =MAX(G7-H7,0) -> 14451783 | N7: =K7*Inputs!B6/12 -> 1083956.1 | O7: =MIN(B7,N7) -> 1083956.1 | P7: =N7-O7 -> 0 | Q7: =L7*Inputs!B6/12 -> 215625 | R7: =MIN(MAX(B7-O7,0),Q7) -> 166234.57 | S7: =Q7-R7 -> 49390.432 | T7: =MAX(B7-O7-R7,0) -> 0 | U7: =MIN(C7,K7) -> 2685285.8 | V7: =MIN(MAX(C7-U7,0),L7) -> 0 | W7: =MIN(MAX(C7-U7-V7,0),M7) -> 0 | X7: =MAX(K7-U7,0) -> 2.2353164e+08 | Y7: =MAX(L7-V7,0) -> 45000000 | Z7: =MAX(M7-W7,0) -> 14451783 | AA7: =C7-(U7+V7+W7) -> 0 | AB7: =B7-(O7+R7+T7) -> 0 | AC7: =D7-(H7+I7+J7) -> 0
A8: 7 | B8: =LoanPool!L8 -> 1238052.5 | C8: =LoanPool!M8 -> 2661972.4 | D8: =LoanPool!H8 -> 88291.889 | E8: =X7 -> 2.2353164e+08 | F8: =Y7 -> 45000000 | G8: =Z7 -> 14451783 | H8: =MIN(D8,G8) -> 88291.889 | I8: =MIN(MAX(D8-H8,0),F8) -> 0 | J8: =MIN(MAX(D8-H8-I8,0),E8) -> 0 | K8: =MAX(E8-J8,0) -> 2.2353164e+08 | L8: =MAX(F8-I8,0) -> 45000000 | M8: =MAX(G8-H8,0) -> 14363491 | N8: =K8*Inputs!B6/12 -> 1071089.1 | O8: =MIN(B8,N8) -> 1071089.1 | P8: =N8-O8 -> 0 | Q8: =L8*Inputs!B6/12 -> 215625 | R8: =MIN(MAX(B8-O8,0),Q8) -> 166963.37 | S8: =Q8-R8 -> 48661.631 | T8: =MAX(B8-O8-R8,0) -> 0 | U8: =MIN(C8,K8) -> 2661972.4 | V8: =MIN(MAX(C8-U8,0),L8) -> 0 | W8: =MIN(MAX(C8-U8-V8,0),M8) -> 0 | X8: =MAX(K8-U8,0) -> 2.2086966e+08 | Y8: =MAX(L8-V8,0) -> 45000000 | Z8: =MAX(M8-W8,0) -> 14363491 | AA8: =C8-(U8+V8+W8) -> 0 | AB8: =B8-(O8+R8+T8) -> 0 | AC8: =D8-(H8+I8+J8) -> 0
A9: 8 | B9: =LoanPool!L9 -> 1226020.1 | C9: =LoanPool!M9 -> 2638854.2 | D9: =LoanPool!H9 -> 87432.929 | E9: =X8 -> 2.2086966e+08 | F9: =Y8 -> 45000000 | G9: =Z8 -> 14363491 | H9: =MIN(D9,G9) -> 87432.929 | I9: =MIN(MAX(D9-H9,0),F9) -> 0 | J9: =MIN(MAX(D9-H9-I9,0),E9) -> 0 | K9: =MAX(E9-J9,0) -> 2.2086966e+08 | L9: =MAX(F9-I9,0) -> 45000000 | M9: =MAX(G9-H9,0) -> 14276058 | N9: =K9*Inputs!B6/12 -> 1058333.8 | O9: =MIN(B9,N9) -> 1058333.8 | P9: =N9-O9 -> 0 | Q9: =L9*Inputs!B6/12 -> 215625 | R9: =MIN(MAX(B9-O9,0),Q9) -> 167686.25 | S9: =Q9-R9 -> 47938.753 | T9: =MAX(B9-O9-R9,0) -> 0 | U9: =MIN(C9,K9) -> 2638854.2 | V9: =MIN(MAX(C9-U9,0),L9) -> 0 | W9: =MIN(MAX(C9-U9-V9,0),M9) -> 0 | X9: =MAX(K9-U9,0) -> 2.1823081e+08 | Y9: =MAX(L9-V9,0) -> 45000000 | Z9: =MAX(M9-W9,0) -> 14276058 | AA9: =C9-(U9+V9+W9) -> 0 | AB9: =B9-(O9+R9+T9) -> 0 | AC9: =D9-(H9+I9+J9) -> 0
A10: 9 | B10: =LoanPool!L10 -> 1214092.5 | C10: =LoanPool!M10 -> 2615929.6 | D10: =LoanPool!H10 -> 86581.46 | E10: =X9 -> 2.1823081e+08 | F10: =Y9 -> 45000000 | G10: =Z9 -> 14276058 | H10: =MIN(D10,G10) -> 86581.46 | I10: =MIN(MAX(D10-H10,0),F10) -> 0 | J10: =MIN(MAX(D10-H10-I10,0),E10) -> 0 | K10: =MAX(E10-J10,0) -> 2.1823081e+08 | L10: =MAX(F10-I10,0) -> 45000000 | M10: =MAX(G10-H10,0) -> 14189477 | N10: =K10*Inputs!B6/12 -> 1045689.3 | O10: =MIN(B10,N10) -> 1045689.3 | P10: =N10-O10 -> 0 | Q10: =L10*Inputs!B6/12 -> 215625 | R10: =MIN(MAX(B10-O10,0),Q10) -> 168403.25 | S10: =Q10-R10 -> 47221.749 | T10: =MAX(B10-O10-R10,0) -> 0 | U10: =MIN(C10,K10) -> 2615929.6 | V10: =MIN(MAX(C10-U10,0),L10) -> 0 | W10: =MIN(MAX(C10-U10-V10,0),M10) -> 0 | X10: =MAX(K10-U10,0) -> 2.1561488e+08 | Y10: =MAX(L10-V10,0) -> 45000000 | Z10: =MAX(M10-W10,0) -> 14189477 | AA10: =C10-(U10+V10+W10) -> 0 | AB10: =B10-(O10+R10+T10) -> 0 | AC10: =D10-(H10+I10+J10) -> 0
A11: 10 | B11: =LoanPool!L11 -> 1202269.1 | C11: =LoanPool!M11 -> 2593197.1 | D11: =LoanPool!H11 -> 85737.419 | E11: =X10 -> 2.1561488e+08 | F11: =Y10 -> 45000000 | G11: =Z10 -> 14189477 | H11: =MIN(D11,G11) -> 85737.419 | I11: =MIN(MAX(D11-H11,0),F11) -> 0 | J11: =MIN(MAX(D11-H11-I11,0),E11) -> 0 | K11: =MAX(E11-J11,0) -> 2.1561488e+08 | L11: =MAX(F11-I11,0) -> 45000000 | M11: =MAX(G11-H11,0) -> 14103739 | N11: =K11*Inputs!B6/12 -> 1033154.6 | O11: =MIN(B11,N11) -> 1033154.6 | P11: =N11-O11 -> 0 | Q11: =L11*Inputs!B6/12 -> 215625 | R11: =MIN(MAX(B11-O11,0),Q11) -> 169114.43 | S11: =Q11-R11 -> 46510.573 | T11: =MAX(B11-O11-R11,0) -> 0 | U11: =MIN(C11,K11) -> 2593197.1 | V11: =MIN(MAX(C11-U11,0),L11) -> 0 | W11: =MIN(MAX(C11-U11-V11,0),M11) -> 0 | X11: =MAX(K11-U11,0) -> 2.1302168e+08 | Y11: =MAX(L11-V11,0) -> 45000000 | Z11: =MAX(M11-W11,0) -> 14103739 | AA11: =C11-(U11+V11+W11) -> 0 | AB11: =B11-(O11+R11+T11) -> 0 | AC11: =D11-(H11+I11+J11) -> 0
A12: 11 | B12: =LoanPool!L12 -> 1190548.7 | C12: =LoanPool!M12 -> 2570655 | D12: =LoanPool!H12 -> 84900.744 | E12: =X11 -> 2.1302168e+08 | F12: =Y11 -> 45000000 | G12: =Z11 -> 14103739 | H12: =MIN(D12,G12) -> 84900.744 | I12: =MIN(MAX(D12-H12,0),F12) -> 0 | J12: =MIN(MAX(D12-H12-I12,0),E12) -> 0 | K12: =MAX(E12-J12,0) -> 2.1302168e+08 | L12: =MAX(F12-I12,0) -> 45000000 | M12: =MAX(G12-H12,0) -> 14018839 | N12: =K12*Inputs!B6/12 -> 1020728.9 | O12: =MIN(B12,N12) -> 1020728.9 | P12: =N12-O12 -> 0 | Q12: =L12*Inputs!B6/12 -> 215625 | R12: =MIN(MAX(B12-O12,0),Q12) -> 169819.82 | S12: =Q12-R12 -> 45805.175 | T12: =MAX(B12-O12-R12,0) -> 0 | U12: =MIN(C12,K12) -> 2570655 | V12: =MIN(MAX(C12-U12,0),L12) -> 0 | W12: =MIN(MAX(C12-U12-V12,0),M12) -> 0 | X12: =MAX(K12-U12,0) -> 2.1045103e+08 | Y12: =MAX(L12-V12,0) -> 45000000 | Z12: =MAX(M12-W12,0) -> 14018839 | AA12: =C12-(U12+V12+W12) -> 0 | AB12: =B12-(O12+R12+T12) -> 0 | AC12: =D12-(H12+I12+J12) -> 0
A13: 12 | B13: =LoanPool!L13 -> 1178930.7 | C13: =LoanPool!M13 -> 2548301.7 | D13: =LoanPool!H13 -> 84071.374 | E13: =X12 -> 2.1045103e+08 | F13: =Y12 -> 45000000 | G13: =Z12 -> 14018839 | H13: =MIN(D13,G13) -> 84071.374 | I13: =MIN(MAX(D13-H13,0),F13) -> 0 | J13: =MIN(MAX(D13-H13-I13,0),E13) -> 0 | K13: =MAX(E13-J13,0) -> 2.1045103e+08 | L13: =MAX(F13-I13,0) -> 45000000 | M13: =MAX(G13-H13,0) -> 13934767 | N13: =K13*Inputs!B6/12 -> 1008411.2 | O13: =MIN(B13,N13) -> 1008411.2 | P13: =N13-O13 -> 0 | Q13: =L13*Inputs!B6/12 -> 215625 | R13: =MIN(MAX(B13-O13,0),Q13) -> 170519.49 | S13: =Q13-R13 -> 45105.51 | T13: =MAX(B13-O13-R13,0) -> 0 | U13: =MIN(C13,K13) -> 2548301.7 | V13: =MIN(MAX(C13-U13,0),L13) -> 0 | W13: =MIN(MAX(C13-U13-V13,0),M13) -> 0 | X13: =MAX(K13-U13,0) -> 2.0790273e+08 | Y13: =MAX(L13-V13,0) -> 45000000 | Z13: =MAX(M13-W13,0) -> 13934767 | AA13: =C13-(U13+V13+W13) -> 0 | AB13: =B13-(O13+R13+T13) -> 0 | AC13: =D13-(H13+I13+J13) -> 0
A14: 13 | B14: =LoanPool!L14 -> 1167414 | C14: =LoanPool!M14 -> 2526135.8 | D14: =LoanPool!H14 -> 83249.246 | E14: =X13 -> 2.0790273e+08 | F14: =Y13 -> 45000000 | G14: =Z13 -> 13934767 | H14: =MIN(D14,G14) -> 83249.246 | I14: =MIN(MAX(D14-H14,0),F14) -> 0 | J14: =MIN(MAX(D14-H14-I14,0),E14) -> 0 | K14: =MAX(E14-J14,0) -> 2.0790273e+08 | L14: =MAX(F14-I14,0) -> 45000000 | M14: =MAX(G14-H14,0) -> 13851518 | N14: =K14*Inputs!B6/12 -> 996200.56 | O14: =MIN(B14,N14) -> 996200.56 | P14: =N14-O14 -> 0 | Q14: =L14*Inputs!B6/12 -> 215625 | R14: =MIN(MAX(B14-O14,0),Q14) -> 171213.47 | S14: =Q14-R14 -> 44411.529 | T14: =MAX(B14-O14-R14,0) -> 0 | U14: =MIN(C14,K14) -> 2526135.8 | V14: =MIN(MAX(C14-U14,0),L14) -> 0 | W14: =MIN(MAX(C14-U14-V14,0),M14) -> 0 | X14: =MAX(K14-U14,0) -> 2.0537659e+08 | Y14: =MAX(L14-V14,0) -> 45000000 | Z14: =MAX(M14-W14,0) -> 13851518 | AA14: =C14-(U14+V14+W14) -> 0 | AB14: =B14-(O14+R14+T14) -> 0 | AC14: =D14-(H14+I14+J14) -> 0
A15: 14 | B15: =LoanPool!L15 -> 1155998 | C15: =LoanPool!M15 -> 2504155.6 | D15: =LoanPool!H15 -> 82434.3 | E15: =X14 -> 2.0537659e+08 | F15: =Y14 -> 45000000 | G15: =Z14 -> 13851518 | H15: =MIN(D15,G15) -> 82434.3 | I15: =MIN(MAX(D15-H15,0),F15) -> 0 | J15: =MIN(MAX(D15-H15-I15,0),E15) -> 0 | K15: =MAX(E15-J15,0) -> 2.0537659e+08 | L15: =MAX(F15-I15,0) -> 45000000 | M15: =MAX(G15-H15,0) -> 13769084 | N15: =K15*Inputs!B6/12 -> 984096.16 | O15: =MIN(B15,N15) -> 984096.16 | P15: =N15-O15 -> 0 | Q15: =L15*Inputs!B6/12 -> 215625 | R15: =MIN(MAX(B15-O15,0),Q15) -> 171901.81 | S15: =Q15-R15 -> 43723.188 | T15: =MAX(B15-O15-R15,0) -> 0 | U15: =MIN(C15,K15) -> 2504155.6 | V15: =MIN(MAX(C15-U15,0),L15) -> 0 | W15: =MIN(MAX(C15-U15-V15,0),M15) -> 0 | X15: =MAX(K15-U15,0) -> 2.0287243e+08 | Y15: =MAX(L15-V15,0) -> 45000000 | Z15: =MAX(M15-W15,0) -> 13769084 | AA15: =C15-(U15+V15+W15) -> 0 | AB15: =B15-(O15+R15+T15) -> 0 | AC15: =D15-(H15+I15+J15) -> 0
A16: 15 | B16: =LoanPool!L16 -> 1144681.6 | C16: =LoanPool!M16 -> 2482359.7 | D16: =LoanPool!H16 -> 81626.475 | E16: =X15 -> 2.0287243e+08 | F16: =Y15 -> 45000000 | G16: =Z15 -> 13769084 | H16: =MIN(D16,G16) -> 81626.475 | I16: =MIN(MAX(D16-H16,0),F16) -> 0 | J16: =MIN(MAX(D16-H16-I16,0),E16) -> 0 | K16: =MAX(E16-J16,0) -> 2.0287243e+08 | L16: =MAX(F16-I16,0) -> 45000000 | M16: =MAX(G16-H16,0) -> 13687457 | N16: =K16*Inputs!B6/12 -> 972097.08 | O16: =MIN(B16,N16) -> 972097.08 | P16: =N16-O16 -> 0 | Q16: =L16*Inputs!B6/12 -> 215625 | R16: =MIN(MAX(B16-O16,0),Q16) -> 172584.56 | S16: =Q16-R16 -> 43040.44 | T16: =MAX(B16-O16-R16,0) -> 0 | U16: =MIN(C16,K16) -> 2482359.7 | V16: =MIN(MAX(C16-U16,0),L16) -> 0 | W16: =MIN(MAX(C16-U16-V16,0),M16) -> 0 | X16: =MAX(K16-U16,0) -> 2.0039007e+08 | Y16: =MAX(L16-V16,0) -> 45000000 | Z16: =MAX(M16-W16,0) -> 13687457 | AA16: =C16-(U16+V16+W16) -> 0 | AB16: =B16-(O16+R16+T16) -> 0 | AC16: =D16-(H16+I16+J16) -> 0
A17: 16 | B17: =LoanPool!L17 -> 1133464.2 | C17: =LoanPool!M17 -> 2460746.4 | D17: =LoanPool!H17 -> 80825.713 | E17: =X16 -> 2.0039007e+08 | F17: =Y16 -> 45000000 | G17: =Z16 -> 13687457 | H17: =MIN(D17,G17) -> 80825.713 | I17: =MIN(MAX(D17-H17,0),F17) -> 0 | J17: =MIN(MAX(D17-H17-I17,0),E17) -> 0 | K17: =MAX(E17-J17,0) -> 2.0039007e+08 | L17: =MAX(F17-I17,0) -> 45000000 | M17: =MAX(G17-H17,0) -> 13606631 | N17: =K17*Inputs!B6/12 -> 960202.44 | O17: =MIN(B17,N17) -> 960202.44 | P17: =N17-O17 -> 0 | Q17: =L17*Inputs!B6/12 -> 215625 | R17: =MIN(MAX(B17-O17,0),Q17) -> 173261.76 | S17: =Q17-R17 -> 42363.24 | T17: =MAX(B17-O17-R17,0) -> 0 | U17: =MIN(C17,K17) -> 2460746.4 | V17: =MIN(MAX(C17-U17,0),L17) -> 0 | W17: =MIN(MAX(C17-U17-V17,0),M17) -> 0 | X17: =MAX(K17-U17,0) -> 1.9792933e+08 | Y17: =MAX(L17-V17,0) -> 45000000 | Z17: =MAX(M17-W17,0) -> 13606631 | AA17: =C17-(U17+V17+W17) -> 0 | AB17: =B17-(O17+R17+T17) -> 0 | AC17: =D17-(H17+I17+J17) -> 0
A18: 17 | B18: =LoanPool!L18 -> 1122344.8 | C18: =LoanPool!M18 -> 2439314.4 | D18: =LoanPool!H18 -> 80031.953 | E18: =X17 -> 1.9792933e+08 | F18: =Y17 -> 45000000 | G18: =Z17 -> 13606631 | H18: =MIN(D18,G18) -> 80031.953 | I18: =MIN(MAX(D18-H18,0),F18) -> 0 | J18: =MIN(MAX(D18-H18-I18,0),E18) -> 0 | K18: =MAX(E18-J18,0) -> 1.9792933e+08 | L18: =MAX(F18-I18,0) -> 45000000 | M18: =MAX(G18-H18,0) -> 13526599 | N18: =K18*Inputs!B6/12 -> 948411.36 | O18: =MIN(B18,N18) -> 948411.36 | P18: =N18-O18 -> 0 | Q18: =L18*Inputs!B6/12 -> 215625 | R18: =MIN(MAX(B18-O18,0),Q18) -> 173933.46 | S18: =Q18-R18 -> 41691.541 | T18: =MAX(B18-O18-R18,0) -> 0 | U18: =MIN(C18,K18) -> 2439314.4 | V18: =MIN(MAX(C18-U18,0),L18) -> 0 | W18: =MIN(MAX(C18-U18-V18,0),M18) -> 0 | X18: =MAX(K18-U18,0) -> 1.9549001e+08 | Y18: =MAX(L18-V18,0) -> 45000000 | Z18: =MAX(M18-W18,0) -> 13526599 | AA18: =C18-(U18+V18+W18) -> 0 | AB18: =B18-(O18+R18+T18) -> 0 | AC18: =D18-(H18+I18+J18) -> 0
A19: 18 | B19: =LoanPool!L19 -> 1111322.7 | C19: =LoanPool!M19 -> 2418062 | D19: =LoanPool!H19 -> 79245.137 | E19: =X18 -> 1.9549001e+08 | F19: =Y18 -> 45000000 | G19: =Z18 -> 13526599 | H19: =MIN(D19,G19) -> 79245.137 | I19: =MIN(MAX(D19-H19,0),F19) -> 0 | J19: =MIN(MAX(D19-H19-I19,0),E19) -> 0 | K19: =MAX(E19-J19,0) -> 1.9549001e+08 | L19: =MAX(F19-I19,0) -> 45000000 | M19: =MAX(G19-H19,0) -> 13447354 | N19: =K19*Inputs!B6/12 -> 936722.98 | O19: =MIN(B19,N19) -> 936722.98 | P19: =N19-O19 -> 0 | Q19: =L19*Inputs!B6/12 -> 215625 | R19: =MIN(MAX(B19-O19,0),Q19) -> 174599.7 | S19: =Q19-R19 -> 41025.3 | T19: =MAX(B19-O19-R19,0) -> 0 | U19: =MIN(C19,K19) -> 2418062 | V19: =MIN(MAX(C19-U19,0),L19) -> 0 | W19: =MIN(MAX(C19-U19-V19,0),M19) -> 0 | X19: =MAX(K19-U19,0) -> 1.9307195e+08 | Y19: =MAX(L19-V19,0) -> 45000000 | Z19: =MAX(M19-W19,0) -> 13447354 | AA19: =C19-(U19+V19+W19) -> 0 | AB19: =B19-(O19+R19+T19) -> 0 | AC19: =D19-(H19+I19+J19) -> 0
A20: 19 | B20: =LoanPool!L20 -> 1100397 | C20: =LoanPool!M20 -> 2396987.9 | D20: =LoanPool!H20 -> 78465.206 | E20: =X19 -> 1.9307195e+08 | F20: =Y19 -> 45000000 | G20: =Z19 -> 13447354 | H20: =MIN(D20,G20) -> 78465.206 | I20: =MIN(MAX(D20-H20,0),F20) -> 0 | J20: =MIN(MAX(D20-H20-I20,0),E20) -> 0 | K20: =MAX(E20-J20,0) -> 1.9307195e+08 | L20: =MAX(F20-I20,0) -> 45000000 | M20: =MAX(G20-H20,0) -> 13368889 | N20: =K20*Inputs!B6/12 -> 925136.44 | O20: =MIN(B20,N20) -> 925136.44 | P20: =N20-O20 -> 0 | Q20: =L20*Inputs!B6/12 -> 215625 | R20: =MIN(MAX(B20-O20,0),Q20) -> 175260.53 | S20: =Q20-R20 -> 40364.471 | T20: =MAX(B20-O20-R20,0) -> 0 | U20: =MIN(C20,K20) -> 2396987.9 | V20: =MIN(MAX(C20-U20,0),L20) -> 0 | W20: =MIN(MAX(C20-U20-V20,0),M20) -> 0 | X20: =MAX(K20-U20,0) -> 1.9067496e+08 | Y20: =MAX(L20-V20,0) -> 45000000 | Z20: =MAX(M20-W20,0) -> 13368889 | AA20: =C20-(U20+V20+W20) -> 0 | AB20: =B20-(O20+R20+T20) -> 0 | AC20: =D20-(H20+I20+J20) -> 0
A21: 20 | B21: =LoanPool!L21 -> 1089566.9 | C21: =LoanPool!M21 -> 2376090.5 | D21: =LoanPool!H21 -> 77692.103 | E21: =X20 -> 1.9067496e+08 | F21: =Y20 -> 45000000 | G21: =Z20 -> 13368889 | H21: =MIN(D21,G21) -> 77692.103 | I21: =MIN(MAX(D21-H21,0),F21) -> 0 | J21: =MIN(MAX(D21-H21-I21,0),E21) -> 0 | K21: =MAX(E21-J21,0) -> 1.9067496e+08 | L21: =MAX(F21-I21,0) -> 45000000 | M21: =MAX(G21-H21,0) -> 13291197 | N21: =K21*Inputs!B6/12 -> 913650.87 | O21: =MIN(B21,N21) -> 913650.87 | P21: =N21-O21 -> 0 | Q21: =L21*Inputs!B6/12 -> 215625 | R21: =MIN(MAX(B21-O21,0),Q21) -> 175915.99 | S21: =Q21-R21 -> 39709.012 | T21: =MAX(B21-O21-R21,0) -> 0 | U21: =MIN(C21,K21) -> 2376090.5 | V21: =MIN(MAX(C21-U21,0),L21) -> 0 | W21: =MIN(MAX(C21-U21-V21,0),M21) -> 0 | X21: =MAX(K21-U21,0) -> 1.8829887e+08 | Y21: =MAX(L21-V21,0) -> 45000000 | Z21: =MAX(M21-W21,0) -> 13291197 | AA21: =C21-(U21+V21+W21) -> 0 | AB21: =B21-(O21+R21+T21) -> 0 | AC21: =D21-(H21+I21+J21) -> 0
A22: 21 | B22: =LoanPool!L22 -> 1078831.6 | C22: =LoanPool!M22 -> 2355368.4 | D22: =LoanPool!H22 -> 76925.77 | E22: =X21 -> 1.8829887e+08 | F22: =Y21 -> 45000000 | G22: =Z21 -> 13291197 | H22: =MIN(D22,G22) -> 76925.77 | I22: =MIN(MAX(D22-H22,0),F22) -> 0 | J22: =MIN(MAX(D22-H22-I22,0),E22) -> 0 | K22: =MAX(E22-J22,0) -> 1.8829887e+08 | L22: =MAX(F22-I22,0) -> 45000000 | M22: =MAX(G22-H22,0) -> 13214271 | N22: =K22*Inputs!B6/12 -> 902265.44 | O22: =MIN(B22,N22) -> 902265.44 | P22: =N22-O22 -> 0 | Q22: =L22*Inputs!B6/12 -> 215625 | R22: =MIN(MAX(B22-O22,0),Q22) -> 176566.12 | S22: =Q22-R22 -> 39058.877 | T22: =MAX(B22-O22-R22,0) -> 0 | U22: =MIN(C22,K22) -> 2355368.4 | V22: =MIN(MAX(C22-U22,0),L22) -> 0 | W22: =MIN(MAX(C22-U22-V22,0),M22) -> 0 | X22: =MAX(K22-U22,0) -> 1.8594351e+08 | Y22: =MAX(L22-V22,0) -> 45000000 | Z22: =MAX(M22-W22,0) -> 13214271 | AA22: =C22-(U22+V22+W22) -> 0 | AB22: =B22-(O22+R22+T22) -> 0 | AC22: =D22-(H22+I22+J22) -> 0
A23: 22 | B23: =LoanPool!L23 -> 1068190.3 | C23: =LoanPool!M23 -> 2334820.1 | D23: =LoanPool!H23 -> 76166.151 | E23: =X22 -> 1.8594351e+08 | F23: =Y22 -> 45000000 | G23: =Z22 -> 13214271 | H23: =MIN(D23,G23) -> 76166.151 | I23: =MIN(MAX(D23-H23,0),F23) -> 0 | J23: =MIN(MAX(D23-H23-I23,0),E23) -> 0 | K23: =MAX(E23-J23,0) -> 1.8594351e+08 | L23: =MAX(F23-I23,0) -> 45000000 | M23: =MAX(G23-H23,0) -> 13138105 | N23: =K23*Inputs!B6/12 -> 890979.3 | O23: =MIN(B23,N23) -> 890979.3 | P23: =N23-O23 -> 0 | Q23: =L23*Inputs!B6/12 -> 215625 | R23: =MIN(MAX(B23-O23,0),Q23) -> 177210.98 | S23: =Q23-R23 -> 38414.024 | T23: =MAX(B23-O23-R23,0) -> 0 | U23: =MIN(C23,K23) -> 2334820.1 | V23: =MIN(MAX(C23-U23,0),L23) -> 0 | W23: =MIN(MAX(C23-U23-V23,0),M23) -> 0 | X23: =MAX(K23-U23,0) -> 1.8360868e+08 | Y23: =MAX(L23-V23,0) -> 45000000 | Z23: =MAX(M23-W23,0) -> 13138105 | AA23: =C23-(U23+V23+W23) -> 0 | AB23: =B23-(O23+R23+T23) -> 0 | AC23: =D23-(H23+I23+J23) -> 0
A24: 23 | B24: =LoanPool!L24 -> 1057642.2 | C24: =LoanPool!M24 -> 2314444.3 | D24: =LoanPool!H24 -> 75413.188 | E24: =X23 -> 1.8360868e+08 | F24: =Y23 -> 45000000 | G24: =Z23 -> 13138105 | H24: =MIN(D24,G24) -> 75413.188 | I24: =MIN(MAX(D24-H24,0),F24) -> 0 | J24: =MIN(MAX(D24-H24-I24,0),E24) -> 0 | K24: =MAX(E24-J24,0) -> 1.8360868e+08 | L24: =MAX(F24-I24,0) -> 45000000 | M24: =MAX(G24-H24,0) -> 13062692 | N24: =K24*Inputs!B6/12 -> 879791.62 | O24: =MIN(B24,N24) -> 879791.62 | P24: =N24-O24 -> 0 | Q24: =L24*Inputs!B6/12 -> 215625 | R24: =MIN(MAX(B24-O24,0),Q24) -> 177850.59 | S24: =Q24-R24 -> 37774.409 | T24: =MAX(B24-O24-R24,0) -> 0 | U24: =MIN(C24,K24) -> 2314444.3 | V24: =MIN(MAX(C24-U24,0),L24) -> 0 | W24: =MIN(MAX(C24-U24-V24,0),M24) -> 0 | X24: =MAX(K24-U24,0) -> 1.8129424e+08 | Y24: =MAX(L24-V24,0) -> 45000000 | Z24: =MAX(M24-W24,0) -> 13062692 | AA24: =C24-(U24+V24+W24) -> 0 | AB24: =B24-(O24+R24+T24) -> 0 | AC24: =D24-(H24+I24+J24) -> 0
A25: 24 | B25: =LoanPool!L25 -> 1047186.6 | C25: =LoanPool!M25 -> 2294239.4 | D25: =LoanPool!H25 -> 74666.827 | E25: =X24 -> 1.8129424e+08 | F25: =Y24 -> 45000000 | G25: =Z24 -> 13062692 | H25: =MIN(D25,G25) -> 74666.827 | I25: =MIN(MAX(D25-H25,0),F25) -> 0 | J25: =MIN(MAX(D25-H25-I25,0),E25) -> 0 | K25: =MAX(E25-J25,0) -> 1.8129424e+08 | L25: =MAX(F25-I25,0) -> 45000000 | M25: =MAX(G25-H25,0) -> 12988025 | N25: =K25*Inputs!B6/12 -> 868701.57 | O25: =MIN(B25,N25) -> 868701.57 | P25: =N25-O25 -> 0 | Q25: =L25*Inputs!B6/12 -> 215625 | R25: =MIN(MAX(B25-O25,0),Q25) -> 178485.01 | S25: =Q25-R25 -> 37139.99 | T25: =MAX(B25-O25-R25,0) -> 0 | U25: =MIN(C25,K25) -> 2294239.4 | V25: =MIN(MAX(C25-U25,0),L25) -> 0 | W25: =MIN(MAX(C25-U25-V25,0),M25) -> 0 | X25: =MAX(K25-U25,0) -> 1.79e+08 | Y25: =MAX(L25-V25,0) -> 45000000 | Z25: =MAX(M25-W25,0) -> 12988025 | AA25: =C25-(U25+V25+W25) -> 0 | AB25: =B25-(O25+R25+T25) -> 0 | AC25: =D25-(H25+I25+J25) -> 0
A26: 25 | B26: =LoanPool!L26 -> 1036822.6 | C26: =LoanPool!M26 -> 2274204 | D26: =LoanPool!H26 -> 73927.011 | E26: =X25 -> 1.79e+08 | F26: =Y25 -> 45000000 | G26: =Z25 -> 12988025 | H26: =MIN(D26,G26) -> 73927.011 | I26: =MIN(MAX(D26-H26,0),F26) -> 0 | J26: =MIN(MAX(D26-H26-I26,0),E26) -> 0 | K26: =MAX(E26-J26,0) -> 1.79e+08 | L26: =MAX(F26-I26,0) -> 45000000 | M26: =MAX(G26-H26,0) -> 12914098 | N26: =K26*Inputs!B6/12 -> 857708.34 | O26: =MIN(B26,N26) -> 857708.34 | P26: =N26-O26 -> 0 | Q26: =L26*Inputs!B6/12 -> 215625 | R26: =MIN(MAX(B26-O26,0),Q26) -> 179114.28 | S26: =Q26-R26 -> 36510.724 | T26: =MAX(B26-O26-R26,0) -> 0 | U26: =MIN(C26,K26) -> 2274204 | V26: =MIN(MAX(C26-U26,0),L26) -> 0 | W26: =MIN(MAX(C26-U26-V26,0),M26) -> 0 | X26: =MAX(K26-U26,0) -> 1.767258e+08 | Y26: =MAX(L26-V26,0) -> 45000000 | Z26: =MAX(M26-W26,0) -> 12914098 | AA26: =C26-(U26+V26+W26) -> 0 | AB26: =B26-(O26+R26+T26) -> 0 | AC26: =D26-(H26+I26+J26) -> 0
A27: 26 | B27: =LoanPool!L27 -> 1026549.5 | C27: =LoanPool!M27 -> 2254336.9 | D27: =LoanPool!H27 -> 73193.686 | E27: =X26 -> 1.767258e+08 | F27: =Y26 -> 45000000 | G27: =Z26 -> 12914098 | H27: =MIN(D27,G27) -> 73193.686 | I27: =MIN(MAX(D27-H27,0),F27) -> 0 | J27: =MIN(MAX(D27-H27-I27,0),E27) -> 0 | K27: =MAX(E27-J27,0) -> 1.767258e+08 | L27: =MAX(F27-I27,0) -> 45000000 | M27: =MAX(G27-H27,0) -> 12840904 | N27: =K27*Inputs!B6/12 -> 846811.11 | O27: =MIN(B27,N27) -> 846811.11 | P27: =N27-O27 -> 0 | Q27: =L27*Inputs!B6/12 -> 215625 | R27: =MIN(MAX(B27-O27,0),Q27) -> 179738.43 | S27: =Q27-R27 -> 35886.57 | T27: =MAX(B27-O27-R27,0) -> 0 | U27: =MIN(C27,K27) -> 2254336.9 | V27: =MIN(MAX(C27-U27,0),L27) -> 0 | W27: =MIN(MAX(C27-U27-V27,0),M27) -> 0 | X27: =MAX(K27-U27,0) -> 1.7447146e+08 | Y27: =MAX(L27-V27,0) -> 45000000 | Z27: =MAX(M27-W27,0) -> 12840904 | AA27: =C27-(U27+V27+W27) -> 0 | AB27: =B27-(O27+R27+T27) -> 0 | AC27: =D27-(H27+I27+J27) -> 0
A28: 27 | B28: =LoanPool!L28 -> 1016366.6 | C28: =LoanPool!M28 -> 2234636.4 | D28: =LoanPool!H28 -> 72466.797 | E28: =X27 -> 1.7447146e+08 | F28: =Y27 -> 45000000 | G28: =Z27 -> 12840904 | H28: =MIN(D28,G28) -> 72466.797 | I28: =MIN(MAX(D28-H28,0),F28) -> 0 | J28: =MIN(MAX(D28-H28-I28,0),E28) -> 0 | K28: =MAX(E28-J28,0) -> 1.7447146e+08 | L28: =MAX(F28-I28,0) -> 45000000 | M28: =MAX(G28-H28,0) -> 12768438 | N28: =K28*Inputs!B6/12 -> 836009.08 | O28: =MIN(B28,N28) -> 836009.08 | P28: =N28-O28 -> 0 | Q28: =L28*Inputs!B6/12 -> 215625 | R28: =MIN(MAX(B28-O28,0),Q28) -> 180357.51 | S28: =Q28-R28 -> 35267.485 | T28: =MAX(B28-O28-R28,0) -> 0 | U28: =MIN(C28,K28) -> 2234636.4 | V28: =MIN(MAX(C28-U28,0),L28) -> 0 | W28: =MIN(MAX(C28-U28-V28,0),M28) -> 0 | X28: =MAX(K28-U28,0) -> 1.7223682e+08 | Y28: =MAX(L28-V28,0) -> 45000000 | Z28: =MAX(M28-W28,0) -> 12768438 | AA28: =C28-(U28+V28+W28) -> 0 | AB28: =B28-(O28+R28+T28) -> 0 | AC28: =D28-(H28+I28+J28) -> 0
A29: 28 | B29: =LoanPool!L29 -> 1006273 | C29: =LoanPool!M29 -> 2215101.4 | D29: =LoanPool!H29 -> 71746.289 | E29: =X28 -> 1.7223682e+08 | F29: =Y28 -> 45000000 | G29: =Z28 -> 12768438 | H29: =MIN(D29,G29) -> 71746.289 | I29: =MIN(MAX(D29-H29,0),F29) -> 0 | J29: =MIN(MAX(D29-H29-I29,0),E29) -> 0 | K29: =MAX(E29-J29,0) -> 1.7223682e+08 | L29: =MAX(F29-I29,0) -> 45000000 | M29: =MAX(G29-H29,0) -> 12696691 | N29: =K29*Inputs!B6/12 -> 825301.45 | O29: =MIN(B29,N29) -> 825301.45 | P29: =N29-O29 -> 0 | Q29: =L29*Inputs!B6/12 -> 215625 | R29: =MIN(MAX(B29-O29,0),Q29) -> 180971.57 | S29: =Q29-R29 -> 34653.429 | T29: =MAX(B29-O29-R29,0) -> 0 | U29: =MIN(C29,K29) -> 2215101.4 | V29: =MIN(MAX(C29-U29,0),L29) -> 0 | W29: =MIN(MAX(C29-U29-V29,0),M29) -> 0 | X29: =MAX(K29-U29,0) -> 1.7002172e+08 | Y29: =MAX(L29-V29,0) -> 45000000 | Z29: =MAX(M29-W29,0) -> 12696691 | AA29: =C29-(U29+V29+W29) -> 0 | AB29: =B29-(O29+R29+T29) -> 0 | AC29: =D29-(H29+I29+J29) -> 0
A30: 29 | B30: =LoanPool!L30 -> 996268.06 | C30: =LoanPool!M30 -> 2195730.5 | D30: =LoanPool!H30 -> 71032.11 | E30: =X29 -> 1.7002172e+08 | F30: =Y29 -> 45000000 | G30: =Z29 -> 12696691 | H30: =MIN(D30,G30) -> 71032.11 | I30: =MIN(MAX(D30-H30,0),F30) -> 0 | J30: =MIN(MAX(D30-H30-I30,0),E30) -> 0 | K30: =MAX(E30-J30,0) -> 1.7002172e+08 | L30: =MAX(F30-I30,0) -> 45000000 | M30: =MAX(G30-H30,0) -> 12625659 | N30: =K30*Inputs!B6/12 -> 814687.42 | O30: =MIN(B30,N30) -> 814687.42 | P30: =N30-O30 -> 0 | Q30: =L30*Inputs!B6/12 -> 215625 | R30: =MIN(MAX(B30-O30,0),Q30) -> 181580.64 | S30: =Q30-R30 -> 34044.36 | T30: =MAX(B30-O30-R30,0) -> 0 | U30: =MIN(C30,K30) -> 2195730.5 | V30: =MIN(MAX(C30-U30,0),L30) -> 0 | W30: =MIN(MAX(C30-U30-V30,0),M30) -> 0 | X30: =MAX(K30-U30,0) -> 1.6782599e+08 | Y30: =MAX(L30-V30,0) -> 45000000 | Z30: =MAX(M30-W30,0) -> 12625659 | AA30: =C30-(U30+V30+W30) -> 0 | AB30: =B30-(O30+R30+T30) -> 0 | AC30: =D30-(H30+I30+J30) -> 0
A31: 30 | B31: =LoanPool!L31 -> 986350.97 | C31: =LoanPool!M31 -> 2176522.1 | D31: =LoanPool!H31 -> 70324.205 | E31: =X30 -> 1.6782599e+08 | F31: =Y30 -> 45000000 | G31: =Z30 -> 12625659 | H31: =MIN(D31,G31) -> 70324.205 | I31: =MIN(MAX(D31-H31,0),F31) -> 0 | J31: =MIN(MAX(D31-H31-I31,0),E31) -> 0 | K31: =MAX(E31-J31,0) -> 1.6782599e+08 | L31: =MAX(F31-I31,0) -> 45000000 | M31: =MAX(G31-H31,0) -> 12555335 | N31: =K31*Inputs!B6/12 -> 804166.21 | O31: =MIN(B31,N31) -> 804166.21 | P31: =N31-O31 -> 0 | Q31: =L31*Inputs!B6/12 -> 215625 | R31: =MIN(MAX(B31-O31,0),Q31) -> 182184.76 | S31: =Q31-R31 -> 33440.238 | T31: =MAX(B31-O31-R31,0) -> 0 | U31: =MIN(C31,K31) -> 2176522.1 | V31: =MIN(MAX(C31-U31,0),L31) -> 0 | W31: =MIN(MAX(C31-U31-V31,0),M31) -> 0 | X31: =MAX(K31-U31,0) -> 1.6564947e+08 | Y31: =MAX(L31-V31,0) -> 45000000 | Z31: =MAX(M31-W31,0) -> 12555335 | AA31: =C31-(U31+V31+W31) -> 0 | AB31: =B31-(O31+R31+T31) -> 0 | AC31: =D31-(H31+I31+J31) -> 0
A32: 31 | B32: =LoanPool!L32 -> 976521.02 | C32: =LoanPool!M32 -> 2157475.1 | D32: =LoanPool!H32 -> 69622.523 | E32: =X31 -> 1.6564947e+08 | F32: =Y31 -> 45000000 | G32: =Z31 -> 12555335 | H32: =MIN(D32,G32) -> 69622.523 | I32: =MIN(MAX(D32-H32,0),F32) -> 0 | J32: =MIN(MAX(D32-H32-I32,0),E32) -> 0 | K32: =MAX(E32-J32,0) -> 1.6564947e+08 | L32: =MAX(F32-I32,0) -> 45000000 | M32: =MAX(G32-H32,0) -> 12485712 | N32: =K32*Inputs!B6/12 -> 793737.04 | O32: =MIN(B32,N32) -> 793737.04 | P32: =N32-O32 -> 0 | Q32: =L32*Inputs!B6/12 -> 215625 | R32: =MIN(MAX(B32-O32,0),Q32) -> 182783.98 | S32: =Q32-R32 -> 32841.022 | T32: =MAX(B32-O32-R32,0) -> 0 | U32: =MIN(C32,K32) -> 2157475.1 | V32: =MIN(MAX(C32-U32,0),L32) -> 0 | W32: =MIN(MAX(C32-U32-V32,0),M32) -> 0 | X32: =MAX(K32-U32,0) -> 1.6349199e+08 | Y32: =MAX(L32-V32,0) -> 45000000 | Z32: =MAX(M32-W32,0) -> 12485712 | AA32: =C32-(U32+V32+W32) -> 0 | AB32: =B32-(O32+R32+T32) -> 0 | AC32: =D32-(H32+I32+J32) -> 0
A33: 32 | B33: =LoanPool!L33 -> 966777.47 | C33: =LoanPool!M33 -> 2138588.2 | D33: =LoanPool!H33 -> 68927.01 | E33: =X32 -> 1.6349199e+08 | F33: =Y32 -> 45000000 | G33: =Z32 -> 12485712 | H33: =MIN(D33,G33) -> 68927.01 | I33: =MIN(MAX(D33-H33,0),F33) -> 0 | J33: =MIN(MAX(D33-H33-I33,0),E33) -> 0 | K33: =MAX(E33-J33,0) -> 1.6349199e+08 | L33: =MAX(F33-I33,0) -> 45000000 | M33: =MAX(G33-H33,0) -> 12416785 | N33: =K33*Inputs!B6/12 -> 783399.14 | O33: =MIN(B33,N33) -> 783399.14 | P33: =N33-O33 -> 0 | Q33: =L33*Inputs!B6/12 -> 215625 | R33: =MIN(MAX(B33-O33,0),Q33) -> 183378.33 | S33: =Q33-R33 -> 32246.673 | T33: =MAX(B33-O33-R33,0) -> 0 | U33: =MIN(C33,K33) -> 2138588.2 | V33: =MIN(MAX(C33-U33,0),L33) -> 0 | W33: =MIN(MAX(C33-U33-V33,0),M33) -> 0 | X33: =MAX(K33-U33,0) -> 1.6135341e+08 | Y33: =MAX(L33-V33,0) -> 45000000 | Z33: =MAX(M33-W33,0) -> 12416785 | AA33: =C33-(U33+V33+W33) -> 0 | AB33: =B33-(O33+R33+T33) -> 0 | AC33: =D33-(H33+I33+J33) -> 0
A34: 33 | B34: =LoanPool!L34 -> 957119.59 | C34: =LoanPool!M34 -> 2119859.8 | D34: =LoanPool!H34 -> 68237.615 | E34: =X33 -> 1.6135341e+08 | F34: =Y33 -> 45000000 | G34: =Z33 -> 12416785 | H34: =MIN(D34,G34) -> 68237.615 | I34: =MIN(MAX(D34-H34,0),F34) -> 0 | J34: =MIN(MAX(D34-H34-I34,0),E34) -> 0 | K34: =MAX(E34-J34,0) -> 1.6135341e+08 | L34: =MAX(F34-I34,0) -> 45000000 | M34: =MAX(G34-H34,0) -> 12348548 | N34: =K34*Inputs!B6/12 -> 773151.74 | O34: =MIN(B34,N34) -> 773151.74 | P34: =N34-O34 -> 0 | Q34: =L34*Inputs!B6/12 -> 215625 | R34: =MIN(MAX(B34-O34,0),Q34) -> 183967.85 | S34: =Q34-R34 -> 31657.15 | T34: =MAX(B34-O34-R34,0) -> 0 | U34: =MIN(C34,K34) -> 2119859.8 | V34: =MIN(MAX(C34-U34,0),L34) -> 0 | W34: =MIN(MAX(C34-U34-V34,0),M34) -> 0 | X34: =MAX(K34-U34,0) -> 1.5923355e+08 | Y34: =MAX(L34-V34,0) -> 45000000 | Z34: =MAX(M34-W34,0) -> 12348548 | AA34: =C34-(U34+V34+W34) -> 0 | AB34: =B34-(O34+R34+T34) -> 0 | AC34: =D34-(H34+I34+J34) -> 0
A35: 34 | B35: =LoanPool!L35 -> 947546.66 | C35: =LoanPool!M35 -> 2101288.9 | D35: =LoanPool!H35 -> 67554.287 | E35: =X34 -> 1.5923355e+08 | F35: =Y34 -> 45000000 | G35: =Z34 -> 12348548 | H35: =MIN(D35,G35) -> 67554.287 | I35: =MIN(MAX(D35-H35,0),F35) -> 0 | J35: =MIN(MAX(D35-H35-I35,0),E35) -> 0 | K35: =MAX(E35-J35,0) -> 1.5923355e+08 | L35: =MAX(F35-I35,0) -> 45000000 | M35: =MAX(G35-H35,0) -> 12280994 | N35: =K35*Inputs!B6/12 -> 762994.08 | O35: =MIN(B35,N35) -> 762994.08 | P35: =N35-O35 -> 0 | Q35: =L35*Inputs!B6/12 -> 215625 | R35: =MIN(MAX(B35-O35,0),Q35) -> 184552.59 | S35: =Q35-R35 -> 31072.414 | T35: =MAX(B35-O35-R35,0) -> 0 | U35: =MIN(C35,K35) -> 2101288.9 | V35: =MIN(MAX(C35-U35,0),L35) -> 0 | W35: =MIN(MAX(C35-U35-V35,0),M35) -> 0 | X35: =MAX(K35-U35,0) -> 1.5713226e+08 | Y35: =MAX(L35-V35,0) -> 45000000 | Z35: =MAX(M35-W35,0) -> 12280994 | AA35: =C35-(U35+V35+W35) -> 0 | AB35: =B35-(O35+R35+T35) -> 0 | AC35: =D35-(H35+I35+J35) -> 0
A36: 35 | B36: =LoanPool!L36 -> 938057.98 | C36: =LoanPool!M36 -> 2082873.9 | D36: =LoanPool!H36 -> 66876.974 | E36: =X35 -> 1.5713226e+08 | F36: =Y35 -> 45000000 | G36: =Z35 -> 12280994 | H36: =MIN(D36,G36) -> 66876.974 | I36: =MIN(MAX(D36-H36,0),F36) -> 0 | J36: =MIN(MAX(D36-H36-I36,0),E36) -> 0 | K36: =MAX(E36-J36,0) -> 1.5713226e+08 | L36: =MAX(F36-I36,0) -> 45000000 | M36: =MAX(G36-H36,0) -> 12214117 | N36: =K36*Inputs!B6/12 -> 752925.4 | O36: =MIN(B36,N36) -> 752925.4 | P36: =N36-O36 -> 0 | Q36: =L36*Inputs!B6/12 -> 215625 | R36: =MIN(MAX(B36-O36,0),Q36) -> 185132.57 | S36: =Q36-R36 -> 30492.427 | T36: =MAX(B36-O36-R36,0) -> 0 | U36: =MIN(C36,K36) -> 2082873.9 | V36: =MIN(MAX(C36-U36,0),L36) -> 0 | W36: =MIN(MAX(C36-U36-V36,0),M36) -> 0 | X36: =MAX(K36-U36,0) -> 1.5504938e+08 | Y36: =MAX(L36-V36,0) -> 45000000 | Z36: =MAX(M36-W36,0) -> 12214117 | AA36: =C36-(U36+V36+W36) -> 0 | AB36: =B36-(O36+R36+T36) -> 0 | AC36: =D36-(H36+I36+J36) -> 0
A37: 36 | B37: =LoanPool!L37 -> 928652.82 | C37: =LoanPool!M37 -> 2064613.8 | D37: =LoanPool!H37 -> 66205.626 | E37: =X36 -> 1.5504938e+08 | F37: =Y36 -> 45000000 | G37: =Z36 -> 12214117 | H37: =MIN(D37,G37) -> 66205.626 | I37: =MIN(MAX(D37-H37,0),F37) -> 0 | J37: =MIN(MAX(D37-H37-I37,0),E37) -> 0 | K37: =MAX(E37-J37,0) -> 1.5504938e+08 | L37: =MAX(F37-I37,0) -> 45000000 | M37: =MAX(G37-H37,0) -> 12147911 | N37: =K37*Inputs!B6/12 -> 742944.97 | O37: =MIN(B37,N37) -> 742944.97 | P37: =N37-O37 -> 0 | Q37: =L37*Inputs!B6/12 -> 215625 | R37: =MIN(MAX(B37-O37,0),Q37) -> 185707.85 | S37: =Q37-R37 -> 29917.15 | T37: =MAX(B37-O37-R37,0) -> 0 | U37: =MIN(C37,K37) -> 2064613.8 | V37: =MIN(MAX(C37-U37,0),L37) -> 0 | W37: =MIN(MAX(C37-U37-V37,0),M37) -> 0 | X37: =MAX(K37-U37,0) -> 1.5298477e+08 | Y37: =MAX(L37-V37,0) -> 45000000 | Z37: =MAX(M37-W37,0) -> 12147911 | AA37: =C37-(U37+V37+W37) -> 0 | AB37: =B37-(O37+R37+T37) -> 0 | AC37: =D37-(H37+I37+J37) -> 0
A38: 37 | B38: =LoanPool!L38 -> 919330.48 | C38: =LoanPool!M38 -> 2046507.1 | D38: =LoanPool!H38 -> 65540.192 | E38: =X37 -> 1.5298477e+08 | F38: =Y37 -> 45000000 | G38: =Z37 -> 12147911 | H38: =MIN(D38,G38) -> 65540.192 | I38: =MIN(MAX(D38-H38,0),F38) -> 0 | J38: =MIN(MAX(D38-H38-I38,0),E38) -> 0 | K38: =MAX(E38-J38,0) -> 1.5298477e+08 | L38: =MAX(F38-I38,0) -> 45000000 | M38: =MAX(G38-H38,0) -> 12082371 | N38: =K38*Inputs!B6/12 -> 733052.02 | O38: =MIN(B38,N38) -> 733052.02 | P38: =N38-O38 -> 0 | Q38: =L38*Inputs!B6/12 -> 215625 | R38: =MIN(MAX(B38-O38,0),Q38) -> 186278.46 | S38: =Q38-R38 -> 29346.544 | T38: =MAX(B38-O38-R38,0) -> 0 | U38: =MIN(C38,K38) -> 2046507.1 | V38: =MIN(MAX(C38-U38,0),L38) -> 0 | W38: =MIN(MAX(C38-U38-V38,0),M38) -> 0 | X38: =MAX(K38-U38,0) -> 1.5093826e+08 | Y38: =MAX(L38-V38,0) -> 45000000 | Z38: =MAX(M38-W38,0) -> 12082371 | AA38: =C38-(U38+V38+W38) -> 0 | AB38: =B38-(O38+R38+T38) -> 0 | AC38: =D38-(H38+I38+J38) -> 0
A39: 38 | B39: =LoanPool!L39 -> 910090.27 | C39: =LoanPool!M39 -> 2028552.7 | D39: =LoanPool!H39 -> 64880.622 | E39: =X38 -> 1.5093826e+08 | F39: =Y38 -> 45000000 | G39: =Z38 -> 12082371 | H39: =MIN(D39,G39) -> 64880.622 | I39: =MIN(MAX(D39-H39,0),F39) -> 0 | J39: =MIN(MAX(D39-H39-I39,0),E39) -> 0 | K39: =MAX(E39-J39,0) -> 1.5093826e+08 | L39: =MAX(F39-I39,0) -> 45000000 | M39: =MAX(G39-H39,0) -> 12017490 | N39: =K39*Inputs!B6/12 -> 723245.84 | O39: =MIN(B39,N39) -> 723245.84 | P39: =N39-O39 -> 0 | Q39: =L39*Inputs!B6/12 -> 215625 | R39: =MIN(MAX(B39-O39,0),Q39) -> 186844.43 | S39: =Q39-R39 -> 28780.571 | T39: =MAX(B39-O39-R39,0) -> 0 | U39: =MIN(C39,K39) -> 2028552.7 | V39: =MIN(MAX(C39-U39,0),L39) -> 0 | W39: =MIN(MAX(C39-U39-V39,0),M39) -> 0 | X39: =MAX(K39-U39,0) -> 1.4890971e+08 | Y39: =MAX(L39-V39,0) -> 45000000 | Z39: =MAX(M39-W39,0) -> 12017490 | AA39: =C39-(U39+V39+W39) -> 0 | AB39: =B39-(O39+R39+T39) -> 0 | AC39: =D39-(H39+I39+J39) -> 0
A40: 39 | B40: =LoanPool!L40 -> 900931.5 | C40: =LoanPool!M40 -> 2010749.2 | D40: =LoanPool!H40 -> 64226.868 | E40: =X39 -> 1.4890971e+08 | F40: =Y39 -> 45000000 | G40: =Z39 -> 12017490 | H40: =MIN(D40,G40) -> 64226.868 | I40: =MIN(MAX(D40-H40,0),F40) -> 0 | J40: =MIN(MAX(D40-H40-I40,0),E40) -> 0 | K40: =MAX(E40-J40,0) -> 1.4890971e+08 | L40: =MAX(F40-I40,0) -> 45000000 | M40: =MAX(G40-H40,0) -> 11953263 | N40: =K40*Inputs!B6/12 -> 713525.7 | O40: =MIN(B40,N40) -> 713525.7 | P40: =N40-O40 -> 0 | Q40: =L40*Inputs!B6/12 -> 215625 | R40: =MIN(MAX(B40-O40,0),Q40) -> 187405.81 | S40: =Q40-R40 -> 28219.193 | T40: =MAX(B40-O40-R40,0) -> 0 | U40: =MIN(C40,K40) -> 2010749.2 | V40: =MIN(MAX(C40-U40,0),L40) -> 0 | W40: =MIN(MAX(C40-U40-V40,0),M40) -> 0 | X40: =MAX(K40-U40,0) -> 1.4689896e+08 | Y40: =MAX(L40-V40,0) -> 45000000 | Z40: =MAX(M40-W40,0) -> 11953263 | AA40: =C40-(U40+V40+W40) -> 0 | AB40: =B40-(O40+R40+T40) -> 0 | AC40: =D40-(H40+I40+J40) -> 0
A41: 40 | B41: =LoanPool!L41 -> 891853.48 | C41: =LoanPool!M41 -> 1993095.5 | D41: =LoanPool!H41 -> 63578.881 | E41: =X40 -> 1.4689896e+08 | F41: =Y40 -> 45000000 | G41: =Z40 -> 11953263 | H41: =MIN(D41,G41) -> 63578.881 | I41: =MIN(MAX(D41-H41,0),F41) -> 0 | J41: =MIN(MAX(D41-H41-I41,0),E41) -> 0 | K41: =MAX(E41-J41,0) -> 1.4689896e+08 | L41: =MAX(F41-I41,0) -> 45000000 | M41: =MAX(G41-H41,0) -> 11889684 | N41: =K41*Inputs!B6/12 -> 703890.86 | O41: =MIN(B41,N41) -> 703890.86 | P41: =N41-O41 -> 0 | Q41: =L41*Inputs!B6/12 -> 215625 | R41: =MIN(MAX(B41-O41,0),Q41) -> 187962.63 | S41: =Q41-R41 -> 27662.374 | T41: =MAX(B41-O41-R41,0) -> 0 | U41: =MIN(C41,K41) -> 1993095.5 | V41: =MIN(MAX(C41-U41,0),L41) -> 0 | W41: =MIN(MAX(C41-U41-V41,0),M41) -> 0 | X41: =MAX(K41-U41,0) -> 1.4490587e+08 | Y41: =MAX(L41-V41,0) -> 45000000 | Z41: =MAX(M41-W41,0) -> 11889684 | AA41: =C41-(U41+V41+W41) -> 0 | AB41: =B41-(O41+R41+T41) -> 0 | AC41: =D41-(H41+I41+J41) -> 0
A42: 41 | B42: =LoanPool!L42 -> 882855.53 | C42: =LoanPool!M42 -> 1975590.2 | D42: =LoanPool!H42 -> 62936.61 | E42: =X41 -> 1.4490587e+08 | F42: =Y41 -> 45000000 | G42: =Z41 -> 11889684 | H42: =MIN(D42,G42) -> 62936.61 | I42: =MIN(MAX(D42-H42,0),F42) -> 0 | J42: =MIN(MAX(D42-H42-I42,0),E42) -> 0 | K42: =MAX(E42-J42,0) -> 1.4490587e+08 | L42: =MAX(F42-I42,0) -> 45000000 | M42: =MAX(G42-H42,0) -> 11826748 | N42: =K42*Inputs!B6/12 -> 694340.61 | O42: =MIN(B42,N42) -> 694340.61 | P42: =N42-O42 -> 0 | Q42: =L42*Inputs!B6/12 -> 215625 | R42: =MIN(MAX(B42-O42,0),Q42) -> 188514.93 | S42: =Q42-R42 -> 27110.075 | T42: =MAX(B42-O42-R42,0) -> 0 | U42: =MIN(C42,K42) -> 1975590.2 | V42: =MIN(MAX(C42-U42,0),L42) -> 0 | W42: =MIN(MAX(C42-U42-V42,0),M42) -> 0 | X42: =MAX(K42-U42,0) -> 1.4293028e+08 | Y42: =MAX(L42-V42,0) -> 45000000 | Z42: =MAX(M42-W42,0) -> 11826748 | AA42: =C42-(U42+V42+W42) -> 0 | AB42: =B42-(O42+R42+T42) -> 0 | AC42: =D42-(H42+I42+J42) -> 0
A43: 42 | B43: =LoanPool!L43 -> 873936.98 | C43: =LoanPool!M43 -> 1958232.1 | D43: =LoanPool!H43 -> 62300.01 | E43: =X42 -> 1.4293028e+08 | F43: =Y42 -> 45000000 | G43: =Z42 -> 11826748 | H43: =MIN(D43,G43) -> 62300.01 | I43: =MIN(MAX(D43-H43,0),F43) -> 0 | J43: =MIN(MAX(D43-H43-I43,0),E43) -> 0 | K43: =MAX(E43-J43,0) -> 1.4293028e+08 | L43: =MAX(F43-I43,0) -> 45000000 | M43: =MAX(G43-H43,0) -> 11764448 | N43: =K43*Inputs!B6/12 -> 684874.24 | O43: =MIN(B43,N43) -> 684874.24 | P43: =N43-O43 -> 0 | Q43: =L43*Inputs!B6/12 -> 215625 | R43: =MIN(MAX(B43-O43,0),Q43) -> 189062.74 | S43: =Q43-R43 -> 26562.26 | T43: =MAX(B43-O43-R43,0) -> 0 | U43: =MIN(C43,K43) -> 1958232.1 | V43: =MIN(MAX(C43-U43,0),L43) -> 0 | W43: =MIN(MAX(C43-U43-V43,0),M43) -> 0 | X43: =MAX(K43-U43,0) -> 1.4097204e+08 | Y43: =MAX(L43-V43,0) -> 45000000 | Z43: =MAX(M43-W43,0) -> 11764448 | AA43: =C43-(U43+V43+W43) -> 0 | AB43: =B43-(O43+R43+T43) -> 0 | AC43: =D43-(H43+I43+J43) -> 0
A44: 43 | B44: =LoanPool!L44 -> 865097.15 | C44: =LoanPool!M44 -> 1941020.1 | D44: =LoanPool!H44 -> 61669.031 | E44: =X43 -> 1.4097204e+08 | F44: =Y43 -> 45000000 | G44: =Z43 -> 11764448 | H44: =MIN(D44,G44) -> 61669.031 | I44: =MIN(MAX(D44-H44,0),F44) -> 0 | J44: =MIN(MAX(D44-H44-I44,0),E44) -> 0 | K44: =MAX(E44-J44,0) -> 1.4097204e+08 | L44: =MAX(F44-I44,0) -> 45000000 | M44: =MAX(G44-H44,0) -> 11702779 | N44: =K44*Inputs!B6/12 -> 675491.04 | O44: =MIN(B44,N44) -> 675491.04 | P44: =N44-O44 -> 0 | Q44: =L44*Inputs!B6/12 -> 215625 | R44: =MIN(MAX(B44-O44,0),Q44) -> 189606.11 | S44: =Q44-R44 -> 26018.892 | T44: =MAX(B44-O44-R44,0) -> 0 | U44: =MIN(C44,K44) -> 1941020.1 | V44: =MIN(MAX(C44-U44,0),L44) -> 0 | W44: =MIN(MAX(C44-U44-V44,0),M44) -> 0 | X44: =MAX(K44-U44,0) -> 1.3903102e+08 | Y44: =MAX(L44-V44,0) -> 45000000 | Z44: =MAX(M44-W44,0) -> 11702779 | AA44: =C44-(U44+V44+W44) -> 0 | AB44: =B44-(O44+R44+T44) -> 0 | AC44: =D44-(H44+I44+J44) -> 0
A45: 44 | B45: =LoanPool!L45 -> 856335.38 | C45: =LoanPool!M45 -> 1923952.9 | D45: =LoanPool!H45 -> 61043.626 | E45: =X44 -> 1.3903102e+08 | F45: =Y44 -> 45000000 | G45: =Z44 -> 11702779 | H45: =MIN(D45,G45) -> 61043.626 | I45: =MIN(MAX(D45-H45,0),F45) -> 0 | J45: =MIN(MAX(D45-H45-I45,0),E45) -> 0 | K45: =MAX(E45-J45,0) -> 1.3903102e+08 | L45: =MAX(F45-I45,0) -> 45000000 | M45: =MAX(G45-H45,0) -> 11641735 | N45: =K45*Inputs!B6/12 -> 666190.32 | O45: =MIN(B45,N45) -> 666190.32 | P45: =N45-O45 -> 0 | Q45: =L45*Inputs!B6/12 -> 215625 | R45: =MIN(MAX(B45-O45,0),Q45) -> 190145.06 | S45: =Q45-R45 -> 25479.936 | T45: =MAX(B45-O45-R45,0) -> 0 | U45: =MIN(C45,K45) -> 1923952.9 | V45: =MIN(MAX(C45-U45,0),L45) -> 0 | W45: =MIN(MAX(C45-U45-V45,0),M45) -> 0 | X45: =MAX(K45-U45,0) -> 1.3710707e+08 | Y45: =MAX(L45-V45,0) -> 45000000 | Z45: =MAX(M45-W45,0) -> 11641735 | AA45: =C45-(U45+V45+W45) -> 0 | AB45: =B45-(O45+R45+T45) -> 0 | AC45: =D45-(H45+I45+J45) -> 0
A46: 45 | B46: =LoanPool!L46 -> 847651.02 | C46: =LoanPool!M46 -> 1907029.3 | D46: =LoanPool!H46 -> 60423.749 | E46: =X45 -> 1.3710707e+08 | F46: =Y45 -> 45000000 | G46: =Z45 -> 11641735 | H46: =MIN(D46,G46) -> 60423.749 | I46: =MIN(MAX(D46-H46,0),F46) -> 0 | J46: =MIN(MAX(D46-H46-I46,0),E46) -> 0 | K46: =MAX(E46-J46,0) -> 1.3710707e+08 | L46: =MAX(F46-I46,0) -> 45000000 | M46: =MAX(G46-H46,0) -> 11581311 | N46: =K46*Inputs!B6/12 -> 656971.38 | O46: =MIN(B46,N46) -> 656971.38 | P46: =N46-O46 -> 0 | Q46: =L46*Inputs!B6/12 -> 215625 | R46: =MIN(MAX(B46-O46,0),Q46) -> 190679.65 | S46: =Q46-R46 -> 24945.355 | T46: =MAX(B46-O46-R46,0) -> 0 | U46: =MIN(C46,K46) -> 1907029.3 | V46: =MIN(MAX(C46-U46,0),L46) -> 0 | W46: =MIN(MAX(C46-U46-V46,0),M46) -> 0 | X46: =MAX(K46-U46,0) -> 1.3520004e+08 | Y46: =MAX(L46-V46,0) -> 45000000 | Z46: =MAX(M46-W46,0) -> 11581311 | AA46: =C46-(U46+V46+W46) -> 0 | AB46: =B46-(O46+R46+T46) -> 0 | AC46: =D46-(H46+I46+J46) -> 0
A47: 46 | B47: =LoanPool!L47 -> 839043.42 | C47: =LoanPool!M47 -> 1890248.2 | D47: =LoanPool!H47 -> 59809.353 | E47: =X46 -> 1.3520004e+08 | F47: =Y46 -> 45000000 | G47: =Z46 -> 11581311 | H47: =MIN(D47,G47) -> 59809.353 | I47: =MIN(MAX(D47-H47,0),F47) -> 0 | J47: =MIN(MAX(D47-H47-I47,0),E47) -> 0 | K47: =MAX(E47-J47,0) -> 1.3520004e+08 | L47: =MAX(F47-I47,0) -> 45000000 | M47: =MAX(G47-H47,0) -> 11521502 | N47: =K47*Inputs!B6/12 -> 647833.53 | O47: =MIN(B47,N47) -> 647833.53 | P47: =N47-O47 -> 0 | Q47: =L47*Inputs!B6/12 -> 215625 | R47: =MIN(MAX(B47-O47,0),Q47) -> 191209.89 | S47: =Q47-R47 -> 24415.113 | T47: =MAX(B47-O47-R47,0) -> 0 | U47: =MIN(C47,K47) -> 1890248.2 | V47: =MIN(MAX(C47-U47,0),L47) -> 0 | W47: =MIN(MAX(C47-U47-V47,0),M47) -> 0 | X47: =MAX(K47-U47,0) -> 1.3330979e+08 | Y47: =MAX(L47-V47,0) -> 45000000 | Z47: =MAX(M47-W47,0) -> 11521502 | AA47: =C47-(U47+V47+W47) -> 0 | AB47: =B47-(O47+R47+T47) -> 0 | AC47: =D47-(H47+I47+J47) -> 0
A48: 47 | B48: =LoanPool!L48 -> 830511.92 | C48: =LoanPool!M48 -> 1873608.3 | D48: =LoanPool!H48 -> 59200.391 | E48: =X47 -> 1.3330979e+08 | F48: =Y47 -> 45000000 | G48: =Z47 -> 11521502 | H48: =MIN(D48,G48) -> 59200.391 | I48: =MIN(MAX(D48-H48,0),F48) -> 0 | J48: =MIN(MAX(D48-H48-I48,0),E48) -> 0 | K48: =MAX(E48-J48,0) -> 1.3330979e+08 | L48: =MAX(F48-I48,0) -> 45000000 | M48: =MAX(G48-H48,0) -> 11462302 | N48: =K48*Inputs!B6/12 -> 638776.09 | O48: =MIN(B48,N48) -> 638776.09 | P48: =N48-O48 -> 0 | Q48: =L48*Inputs!B6/12 -> 215625 | R48: =MIN(MAX(B48-O48,0),Q48) -> 191735.82 | S48: =Q48-R48 -> 23889.176 | T48: =MAX(B48-O48-R48,0) -> 0 | U48: =MIN(C48,K48) -> 1873608.3 | V48: =MIN(MAX(C48-U48,0),L48) -> 0 | W48: =MIN(MAX(C48-U48-V48,0),M48) -> 0 | X48: =MAX(K48-U48,0) -> 1.3143618e+08 | Y48: =MAX(L48-V48,0) -> 45000000 | Z48: =MAX(M48-W48,0) -> 11462302 | AA48: =C48-(U48+V48+W48) -> 0 | AB48: =B48-(O48+R48+T48) -> 0 | AC48: =D48-(H48+I48+J48) -> 0
A49: 48 | B49: =LoanPool!L49 -> 822055.88 | C49: =LoanPool!M49 -> 1857108.5 | D49: =LoanPool!H49 -> 58596.818 | E49: =X48 -> 1.3143618e+08 | F49: =Y48 -> 45000000 | G49: =Z48 -> 11462302 | H49: =MIN(D49,G49) -> 58596.818 | I49: =MIN(MAX(D49-H49,0),F49) -> 0 | J49: =MIN(MAX(D49-H49-I49,0),E49) -> 0 | K49: =MAX(E49-J49,0) -> 1.3143618e+08 | L49: =MAX(F49-I49,0) -> 45000000 | M49: =MAX(G49-H49,0) -> 11403705 | N49: =K49*Inputs!B6/12 -> 629798.39 | O49: =MIN(B49,N49) -> 629798.39 | P49: =N49-O49 -> 0 | Q49: =L49*Inputs!B6/12 -> 215625 | R49: =MIN(MAX(B49-O49,0),Q49) -> 192257.49 | S49: =Q49-R49 -> 23367.507 | T49: =MAX(B49-O49-R49,0) -> 0 | U49: =MIN(C49,K49) -> 1857108.5 | V49: =MIN(MAX(C49-U49,0),L49) -> 0 | W49: =MIN(MAX(C49-U49-V49,0),M49) -> 0 | X49: =MAX(K49-U49,0) -> 1.2957908e+08 | Y49: =MAX(L49-V49,0) -> 45000000 | Z49: =MAX(M49-W49,0) -> 11403705 | AA49: =C49-(U49+V49+W49) -> 0 | AB49: =B49-(O49+R49+T49) -> 0 | AC49: =D49-(H49+I49+J49) -> 0
A50: 49 | B50: =LoanPool!L50 -> 813674.67 | C50: =LoanPool!M50 -> 1840747.6 | D50: =LoanPool!H50 -> 57998.588 | E50: =X49 -> 1.2957908e+08 | F50: =Y49 -> 45000000 | G50: =Z49 -> 11403705 | H50: =MIN(D50,G50) -> 57998.588 | I50: =MIN(MAX(D50-H50,0),F50) -> 0 | J50: =MIN(MAX(D50-H50-I50,0),E50) -> 0 | K50: =MAX(E50-J50,0) -> 1.2957908e+08 | L50: =MAX(F50-I50,0) -> 45000000 | M50: =MAX(G50-H50,0) -> 11345706 | N50: =K50*Inputs!B6/12 -> 620899.74 | O50: =MIN(B50,N50) -> 620899.74 | P50: =N50-O50 -> 0 | Q50: =L50*Inputs!B6/12 -> 215625 | R50: =MIN(MAX(B50-O50,0),Q50) -> 192774.93 | S50: =Q50-R50 -> 22850.073 | T50: =MAX(B50-O50-R50,0) -> 0 | U50: =MIN(C50,K50) -> 1840747.6 | V50: =MIN(MAX(C50-U50,0),L50) -> 0 | W50: =MIN(MAX(C50-U50-V50,0),M50) -> 0 | X50: =MAX(K50-U50,0) -> 1.2773833e+08 | Y50: =MAX(L50-V50,0) -> 45000000 | Z50: =MAX(M50-W50,0) -> 11345706 | AA50: =C50-(U50+V50+W50) -> 0 | AB50: =B50-(O50+R50+T50) -> 0 | AC50: =D50-(H50+I50+J50) -> 0
A51: 50 | B51: =LoanPool!L51 -> 805367.65 | C51: =LoanPool!M51 -> 1824524.5 | D51: =LoanPool!H51 -> 57405.656 | E51: =X50 -> 1.2773833e+08 | F51: =Y50 -> 45000000 | G51: =Z50 -> 11345706 | H51: =MIN(D51,G51) -> 57405.656 | I51: =MIN(MAX(D51-H51,0),F51) -> 0 | J51: =MIN(MAX(D51-H51-I51,0),E51) -> 0 | K51: =MAX(E51-J51,0) -> 1.2773833e+08 | L51: =MAX(F51-I51,0) -> 45000000 | M51: =MAX(G51-H51,0) -> 11288301 | N51: =K51*Inputs!B6/12 -> 612079.49 | O51: =MIN(B51,N51) -> 612079.49 | P51: =N51-O51 -> 0 | Q51: =L51*Inputs!B6/12 -> 215625 | R51: =MIN(MAX(B51-O51,0),Q51) -> 193288.16 | S51: =Q51-R51 -> 22336.839 | T51: =MAX(B51-O51-R51,0) -> 0 | U51: =MIN(C51,K51) -> 1824524.5 | V51: =MIN(MAX(C51-U51,0),L51) -> 0 | W51: =MIN(MAX(C51-U51-V51,0),M51) -> 0 | X51: =MAX(K51-U51,0) -> 1.259138e+08 | Y51: =MAX(L51-V51,0) -> 45000000 | Z51: =MAX(M51-W51,0) -> 11288301 | AA51: =C51-(U51+V51+W51) -> 0 | AB51: =B51-(O51+R51+T51) -> 0 | AC51: =D51-(H51+I51+J51) -> 0
A52: 51 | B52: =LoanPool!L52 -> 797134.21 | C52: =LoanPool!M52 -> 1808438 | D52: =LoanPool!H52 -> 56817.977 | E52: =X51 -> 1.259138e+08 | F52: =Y51 -> 45000000 | G52: =Z51 -> 11288301 | H52: =MIN(D52,G52) -> 56817.977 | I52: =MIN(MAX(D52-H52,0),F52) -> 0 | J52: =MIN(MAX(D52-H52-I52,0),E52) -> 0 | K52: =MAX(E52-J52,0) -> 1.259138e+08 | L52: =MAX(F52-I52,0) -> 45000000 | M52: =MAX(G52-H52,0) -> 11231483 | N52: =K52*Inputs!B6/12 -> 603336.98 | O52: =MIN(B52,N52) -> 603336.98 | P52: =N52-O52 -> 0 | Q52: =L52*Inputs!B6/12 -> 215625 | R52: =MIN(MAX(B52-O52,0),Q52) -> 193797.23 | S52: =Q52-R52 -> 21827.77 | T52: =MAX(B52-O52-R52,0) -> 0 | U52: =MIN(C52,K52) -> 1808438 | V52: =MIN(MAX(C52-U52,0),L52) -> 0 | W52: =MIN(MAX(C52-U52-V52,0),M52) -> 0 | X52: =MAX(K52-U52,0) -> 1.2410537e+08 | Y52: =MAX(L52-V52,0) -> 45000000 | Z52: =MAX(M52-W52,0) -> 11231483 | AA52: =C52-(U52+V52+W52) -> 0 | AB52: =B52-(O52+R52+T52) -> 0 | AC52: =D52-(H52+I52+J52) -> 0
A53: 52 | B53: =LoanPool!L53 -> 788973.71 | C53: =LoanPool!M53 -> 1792487.1 | D53: =LoanPool!H53 -> 56235.508 | E53: =X52 -> 1.2410537e+08 | F53: =Y52 -> 45000000 | G53: =Z52 -> 11231483 | H53: =MIN(D53,G53) -> 56235.508 | I53: =MIN(MAX(D53-H53,0),F53) -> 0 | J53: =MIN(MAX(D53-H53-I53,0),E53) -> 0 | K53: =MAX(E53-J53,0) -> 1.2410537e+08 | L53: =MAX(F53-I53,0) -> 45000000 | M53: =MAX(G53-H53,0) -> 11175247 | N53: =K53*Inputs!B6/12 -> 594671.55 | O53: =MIN(B53,N53) -> 594671.55 | P53: =N53-O53 -> 0 | Q53: =L53*Inputs!B6/12 -> 215625 | R53: =MIN(MAX(B53-O53,0),Q53) -> 194302.17 | S53: =Q53-R53 -> 21322.833 | T53: =MAX(B53-O53-R53,0) -> 0 | U53: =MIN(C53,K53) -> 1792487.1 | V53: =MIN(MAX(C53-U53,0),L53) -> 0 | W53: =MIN(MAX(C53-U53-V53,0),M53) -> 0 | X53: =MAX(K53-U53,0) -> 1.2231288e+08 | Y53: =MAX(L53-V53,0) -> 45000000 | Z53: =MAX(M53-W53,0) -> 11175247 | AA53: =C53-(U53+V53+W53) -> 0 | AB53: =B53-(O53+R53+T53) -> 0 | AC53: =D53-(H53+I53+J53) -> 0
A54: 53 | B54: =LoanPool!L54 -> 780885.55 | C54: =LoanPool!M54 -> 1776670.5 | D54: =LoanPool!H54 -> 55658.204 | E54: =X53 -> 1.2231288e+08 | F54: =Y53 -> 45000000 | G54: =Z53 -> 11175247 | H54: =MIN(D54,G54) -> 55658.204 | I54: =MIN(MAX(D54-H54,0),F54) -> 0 | J54: =MIN(MAX(D54-H54-I54,0),E54) -> 0 | K54: =MAX(E54-J54,0) -> 1.2231288e+08 | L54: =MAX(F54-I54,0) -> 45000000 | M54: =MAX(G54-H54,0) -> 11119589 | N54: =K54*Inputs!B6/12 -> 586082.55 | O54: =MIN(B54,N54) -> 586082.55 | P54: =N54-O54 -> 0 | Q54: =L54*Inputs!B6/12 -> 215625 | R54: =MIN(MAX(B54-O54,0),Q54) -> 194803.01 | S54: =Q54-R54 -> 20821.994 | T54: =MAX(B54-O54-R54,0) -> 0 | U54: =MIN(C54,K54) -> 1776670.5 | V54: =MIN(MAX(C54-U54,0),L54) -> 0 | W54: =MIN(MAX(C54-U54-V54,0),M54) -> 0 | X54: =MAX(K54-U54,0) -> 1.2053621e+08 | Y54: =MAX(L54-V54,0) -> 45000000 | Z54: =MAX(M54-W54,0) -> 11119589 | AA54: =C54-(U54+V54+W54) -> 0 | AB54: =B54-(O54+R54+T54) -> 0 | AC54: =D54-(H54+I54+J54) -> 0
A55: 54 | B55: =LoanPool!L55 -> 772869.11 | C55: =LoanPool!M55 -> 1760987.2 | D55: =LoanPool!H55 -> 55086.021 | E55: =X54 -> 1.2053621e+08 | F55: =Y54 -> 45000000 | G55: =Z54 -> 11119589 | H55: =MIN(D55,G55) -> 55086.021 | I55: =MIN(MAX(D55-H55,0),F55) -> 0 | J55: =MIN(MAX(D55-H55-I55,0),E55) -> 0 | K55: =MAX(E55-J55,0) -> 1.2053621e+08 | L55: =MAX(F55-I55,0) -> 45000000 | M55: =MAX(G55-H55,0) -> 11064503 | N55: =K55*Inputs!B6/12 -> 577569.33 | O55: =MIN(B55,N55) -> 577569.33 | P55: =N55-O55 -> 0 | Q55: =L55*Inputs!B6/12 -> 215625 | R55: =MIN(MAX(B55-O55,0),Q55) -> 195299.78 | S55: =Q55-R55 -> 20325.219 | T55: =MAX(B55-O55-R55,0) -> 0 | U55: =MIN(C55,K55) -> 1760987.2 | V55: =MIN(MAX(C55-U55,0),L55) -> 0 | W55: =MIN(MAX(C55-U55-V55,0),M55) -> 0 | X55: =MAX(K55-U55,0) -> 1.1877522e+08 | Y55: =MAX(L55-V55,0) -> 45000000 | Z55: =MAX(M55-W55,0) -> 11064503 | AA55: =C55-(U55+V55+W55) -> 0 | AB55: =B55-(O55+R55+T55) -> 0 | AC55: =D55-(H55+I55+J55) -> 0
A56: 55 | B56: =LoanPool!L56 -> 764923.79 | C56: =LoanPool!M56 -> 1745436.1 | D56: =LoanPool!H56 -> 54518.917 | E56: =X55 -> 1.1877522e+08 | F56: =Y55 -> 45000000 | G56: =Z55 -> 11064503 | H56: =MIN(D56,G56) -> 54518.917 | I56: =MIN(MAX(D56-H56,0),F56) -> 0 | J56: =MIN(MAX(D56-H56-I56,0),E56) -> 0 | K56: =MAX(E56-J56,0) -> 1.1877522e+08 | L56: =MAX(F56-I56,0) -> 45000000 | M56: =MAX(G56-H56,0) -> 11009984 | N56: =K56*Inputs!B6/12 -> 569131.27 | O56: =MIN(B56,N56) -> 569131.27 | P56: =N56-O56 -> 0 | Q56: =L56*Inputs!B6/12 -> 215625 | R56: =MIN(MAX(B56-O56,0),Q56) -> 195792.52 | S56: =Q56-R56 -> 19832.476 | T56: =MAX(B56-O56-R56,0) -> 0 | U56: =MIN(C56,K56) -> 1745436.1 | V56: =MIN(MAX(C56-U56,0),L56) -> 0 | W56: =MIN(MAX(C56-U56-V56,0),M56) -> 0 | X56: =MAX(K56-U56,0) -> 1.1702979e+08 | Y56: =MAX(L56-V56,0) -> 45000000 | Z56: =MAX(M56-W56,0) -> 11009984 | AA56: =C56-(U56+V56+W56) -> 0 | AB56: =B56-(O56+R56+T56) -> 0 | AC56: =D56-(H56+I56+J56) -> 0
A57: 56 | B57: =LoanPool!L57 -> 757048.99 | C57: =LoanPool!M57 -> 1730016 | D57: =LoanPool!H57 -> 53956.848 | E57: =X56 -> 1.1702979e+08 | F57: =Y56 -> 45000000 | G57: =Z56 -> 11009984 | H57: =MIN(D57,G57) -> 53956.848 | I57: =MIN(MAX(D57-H57,0),F57) -> 0 | J57: =MIN(MAX(D57-H57-I57,0),E57) -> 0 | K57: =MAX(E57-J57,0) -> 1.1702979e+08 | L57: =MAX(F57-I57,0) -> 45000000 | M57: =MAX(G57-H57,0) -> 10956027 | N57: =K57*Inputs!B6/12 -> 560767.72 | O57: =MIN(B57,N57) -> 560767.72 | P57: =N57-O57 -> 0 | Q57: =L57*Inputs!B6/12 -> 215625 | R57: =MIN(MAX(B57-O57,0),Q57) -> 196281.27 | S57: =Q57-R57 -> 19343.731 | T57: =MAX(B57-O57-R57,0) -> 0 | U57: =MIN(C57,K57) -> 1730016 | V57: =MIN(MAX(C57-U57,0),L57) -> 0 | W57: =MIN(MAX(C57-U57-V57,0),M57) -> 0 | X57: =MAX(K57-U57,0) -> 1.1529977e+08 | Y57: =MAX(L57-V57,0) -> 45000000 | Z57: =MAX(M57-W57,0) -> 10956027 | AA57: =C57-(U57+V57+W57) -> 0 | AB57: =B57-(O57+R57+T57) -> 0 | AC57: =D57-(H57+I57+J57) -> 0
A58: 57 | B58: =LoanPool!L58 -> 749244.11 | C58: =LoanPool!M58 -> 1714726 | D58: =LoanPool!H58 -> 53399.772 | E58: =X57 -> 1.1529977e+08 | F58: =Y57 -> 45000000 | G58: =Z57 -> 10956027 | H58: =MIN(D58,G58) -> 53399.772 | I58: =MIN(MAX(D58-H58,0),F58) -> 0 | J58: =MIN(MAX(D58-H58-I58,0),E58) -> 0 | K58: =MAX(E58-J58,0) -> 1.1529977e+08 | L58: =MAX(F58-I58,0) -> 45000000 | M58: =MAX(G58-H58,0) -> 10902627 | N58: =K58*Inputs!B6/12 -> 552478.06 | O58: =MIN(B58,N58) -> 552478.06 | P58: =N58-O58 -> 0 | Q58: =L58*Inputs!B6/12 -> 215625 | R58: =MIN(MAX(B58-O58,0),Q58) -> 196766.05 | S58: =Q58-R58 -> 18858.952 | T58: =MAX(B58-O58-R58,0) -> 0 | U58: =MIN(C58,K58) -> 1714726 | V58: =MIN(MAX(C58-U58,0),L58) -> 0 | W58: =MIN(MAX(C58-U58-V58,0),M58) -> 0 | X58: =MAX(K58-U58,0) -> 1.1358504e+08 | Y58: =MAX(L58-V58,0) -> 45000000 | Z58: =MAX(M58-W58,0) -> 10902627 | AA58: =C58-(U58+V58+W58) -> 0 | AB58: =B58-(O58+R58+T58) -> 0 | AC58: =D58-(H58+I58+J58) -> 0
A59: 58 | B59: =LoanPool!L59 -> 741508.56 | C59: =LoanPool!M59 -> 1699564.8 | D59: =LoanPool!H59 -> 52847.647 | E59: =X58 -> 1.1358504e+08 | F59: =Y58 -> 45000000 | G59: =Z58 -> 10902627 | H59: =MIN(D59,G59) -> 52847.647 | I59: =MIN(MAX(D59-H59,0),F59) -> 0 | J59: =MIN(MAX(D59-H59-I59,0),E59) -> 0 | K59: =MAX(E59-J59,0) -> 1.1358504e+08 | L59: =MAX(F59-I59,0) -> 45000000 | M59: =MAX(G59-H59,0) -> 10849780 | N59: =K59*Inputs!B6/12 -> 544261.67 | O59: =MIN(B59,N59) -> 544261.67 | P59: =N59-O59 -> 0 | Q59: =L59*Inputs!B6/12 -> 215625 | R59: =MIN(MAX(B59-O59,0),Q59) -> 197246.89 | S59: =Q59-R59 -> 18378.107 | T59: =MAX(B59-O59-R59,0) -> 0 | U59: =MIN(C59,K59) -> 1699564.8 | V59: =MIN(MAX(C59-U59,0),L59) -> 0 | W59: =MIN(MAX(C59-U59-V59,0),M59) -> 0 | X59: =MAX(K59-U59,0) -> 1.1188548e+08 | Y59: =MAX(L59-V59,0) -> 45000000 | Z59: =MAX(M59-W59,0) -> 10849780 | AA59: =C59-(U59+V59+W59) -> 0 | AB59: =B59-(O59+R59+T59) -> 0 | AC59: =D59-(H59+I59+J59) -> 0
A60: 59 | B60: =LoanPool!L60 -> 733841.75 | C60: =LoanPool!M60 -> 1684531.5 | D60: =LoanPool!H60 -> 52300.43 | E60: =X59 -> 1.1188548e+08 | F60: =Y59 -> 45000000 | G60: =Z59 -> 10849780 | H60: =MIN(D60,G60) -> 52300.43 | I60: =MIN(MAX(D60-H60,0),F60) -> 0 | J60: =MIN(MAX(D60-H60-I60,0),E60) -> 0 | K60: =MAX(E60-J60,0) -> 1.1188548e+08 | L60: =MAX(F60-I60,0) -> 45000000 | M60: =MAX(G60-H60,0) -> 10797479 | N60: =K60*Inputs!B6/12 -> 536117.92 | O60: =MIN(B60,N60) -> 536117.92 | P60: =N60-O60 -> 0 | Q60: =L60*Inputs!B6/12 -> 215625 | R60: =MIN(MAX(B60-O60,0),Q60) -> 197723.84 | S60: =Q60-R60 -> 17901.163 | T60: =MAX(B60-O60-R60,0) -> 0 | U60: =MIN(C60,K60) -> 1684531.5 | V60: =MIN(MAX(C60-U60,0),L60) -> 0 | W60: =MIN(MAX(C60-U60-V60,0),M60) -> 0 | X60: =MAX(K60-U60,0) -> 1.1020095e+08 | Y60: =MAX(L60-V60,0) -> 45000000 | Z60: =MAX(M60-W60,0) -> 10797479 | AA60: =C60-(U60+V60+W60) -> 0 | AB60: =B60-(O60+R60+T60) -> 0 | AC60: =D60-(H60+I60+J60) -> 0
A61: 60 | B61: =LoanPool!L61 -> 726243.12 | C61: =LoanPool!M61 -> 1669625 | D61: =LoanPool!H61 -> 51758.081 | E61: =X60 -> 1.1020095e+08 | F61: =Y60 -> 45000000 | G61: =Z60 -> 10797479 | H61: =MIN(D61,G61) -> 51758.081 | I61: =MIN(MAX(D61-H61,0),F61) -> 0 | J61: =MIN(MAX(D61-H61-I61,0),E61) -> 0 | K61: =MAX(E61-J61,0) -> 1.1020095e+08 | L61: =MAX(F61-I61,0) -> 45000000 | M61: =MAX(G61-H61,0) -> 10745721 | N61: =K61*Inputs!B6/12 -> 528046.2 | O61: =MIN(B61,N61) -> 528046.2 | P61: =N61-O61 -> 0 | Q61: =L61*Inputs!B6/12 -> 215625 | R61: =MIN(MAX(B61-O61,0),Q61) -> 198196.91 | S61: =Q61-R61 -> 17428.09 | T61: =MAX(B61-O61-R61,0) -> 0 | U61: =MIN(C61,K61) -> 1669625 | V61: =MIN(MAX(C61-U61,0),L61) -> 0 | W61: =MIN(MAX(C61-U61-V61,0),M61) -> 0 | X61: =MAX(K61-U61,0) -> 1.0853132e+08 | Y61: =MAX(L61-V61,0) -> 45000000 | Z61: =MAX(M61-W61,0) -> 10745721 | AA61: =C61-(U61+V61+W61) -> 0 | AB61: =B61-(O61+R61+T61) -> 0 | AC61: =D61-(H61+I61+J61) -> 0
A62: 61 | B62: =LoanPool!L62 -> 718712.06 | C62: =LoanPool!M62 -> 1654844.3 | D62: =LoanPool!H62 -> 51220.559 | E62: =X61 -> 1.0853132e+08 | F62: =Y61 -> 45000000 | G62: =Z61 -> 10745721 | H62: =MIN(D62,G62) -> 51220.559 | I62: =MIN(MAX(D62-H62,0),F62) -> 0 | J62: =MIN(MAX(D62-H62-I62,0),E62) -> 0 | K62: =MAX(E62-J62,0) -> 1.0853132e+08 | L62: =MAX(F62-I62,0) -> 45000000 | M62: =MAX(G62-H62,0) -> 10694501 | N62: =K62*Inputs!B6/12 -> 520045.92 | O62: =MIN(B62,N62) -> 520045.92 | P62: =N62-O62 -> 0 | Q62: =L62*Inputs!B6/12 -> 215625 | R62: =MIN(MAX(B62-O62,0),Q62) -> 198666.15 | S62: =Q62-R62 -> 16958.854 | T62: =MAX(B62-O62-R62,0) -> 0 | U62: =MIN(C62,K62) -> 1654844.3 | V62: =MIN(MAX(C62-U62,0),L62) -> 0 | W62: =MIN(MAX(C62-U62-V62,0),M62) -> 0 | X62: =MAX(K62-U62,0) -> 1.0687648e+08 | Y62: =MAX(L62-V62,0) -> 45000000 | Z62: =MAX(M62-W62,0) -> 10694501 | AA62: =C62-(U62+V62+W62) -> 0 | AB62: =B62-(O62+R62+T62) -> 0 | AC62: =D62-(H62+I62+J62) -> 0
A63: 62 | B63: =LoanPool!L63 -> 711248.03 | C63: =LoanPool!M63 -> 1640188.2 | D63: =LoanPool!H63 -> 50687.821 | E63: =X62 -> 1.0687648e+08 | F63: =Y62 -> 45000000 | G63: =Z62 -> 10694501 | H63: =MIN(D63,G63) -> 50687.821 | I63: =MIN(MAX(D63-H63,0),F63) -> 0 | J63: =MIN(MAX(D63-H63-I63,0),E63) -> 0 | K63: =MAX(E63-J63,0) -> 1.0687648e+08 | L63: =MAX(F63-I63,0) -> 45000000 | M63: =MAX(G63-H63,0) -> 10643813 | N63: =K63*Inputs!B6/12 -> 512116.46 | O63: =MIN(B63,N63) -> 512116.46 | P63: =N63-O63 -> 0 | Q63: =L63*Inputs!B6/12 -> 215625 | R63: =MIN(MAX(B63-O63,0),Q63) -> 199131.57 | S63: =Q63-R63 -> 16493.426 | T63: =MAX(B63-O63-R63,0) -> 0 | U63: =MIN(C63,K63) -> 1640188.2 | V63: =MIN(MAX(C63-U63,0),L63) -> 0 | W63: =MIN(MAX(C63-U63-V63,0),M63) -> 0 | X63: =MAX(K63-U63,0) -> 1.0523629e+08 | Y63: =MAX(L63-V63,0) -> 45000000 | Z63: =MAX(M63-W63,0) -> 10643813 | AA63: =C63-(U63+V63+W63) -> 0 | AB63: =B63-(O63+R63+T63) -> 0 | AC63: =D63-(H63+I63+J63) -> 0
A64: 63 | B64: =LoanPool!L64 -> 703850.45 | C64: =LoanPool!M64 -> 1625655.8 | D64: =LoanPool!H64 -> 50159.829 | E64: =X63 -> 1.0523629e+08 | F64: =Y63 -> 45000000 | G64: =Z63 -> 10643813 | H64: =MIN(D64,G64) -> 50159.829 | I64: =MIN(MAX(D64-H64,0),F64) -> 0 | J64: =MIN(MAX(D64-H64-I64,0),E64) -> 0 | K64: =MAX(E64-J64,0) -> 1.0523629e+08 | L64: =MAX(F64-I64,0) -> 45000000 | M64: =MAX(G64-H64,0) -> 10593653 | N64: =K64*Inputs!B6/12 -> 504257.22 | O64: =MIN(B64,N64) -> 504257.22 | P64: =N64-O64 -> 0 | Q64: =L64*Inputs!B6/12 -> 215625 | R64: =MIN(MAX(B64-O64,0),Q64) -> 199593.23 | S64: =Q64-R64 -> 16031.773 | T64: =MAX(B64-O64-R64,0) -> 0 | U64: =MIN(C64,K64) -> 1625655.8 | V64: =MIN(MAX(C64-U64,0),L64) -> 0 | W64: =MIN(MAX(C64-U64-V64,0),M64) -> 0 | X64: =MAX(K64-U64,0) -> 1.0361063e+08 | Y64: =MAX(L64-V64,0) -> 45000000 | Z64: =MAX(M64-W64,0) -> 10593653 | AA64: =C64-(U64+V64+W64) -> 0 | AB64: =B64-(O64+R64+T64) -> 0 | AC64: =D64-(H64+I64+J64) -> 0
A65: 64 | B65: =LoanPool!L65 -> 696518.75 | C65: =LoanPool!M65 -> 1611246 | D65: =LoanPool!H65 -> 49636.542 | E65: =X64 -> 1.0361063e+08 | F65: =Y64 -> 45000000 | G65: =Z64 -> 10593653 | H65: =MIN(D65,G65) -> 49636.542 | I65: =MIN(MAX(D65-H65,0),F65) -> 0 | J65: =MIN(MAX(D65-H65-I65,0),E65) -> 0 | K65: =MAX(E65-J65,0) -> 1.0361063e+08 | L65: =MAX(F65-I65,0) -> 45000000 | M65: =MAX(G65-H65,0) -> 10544016 | N65: =K65*Inputs!B6/12 -> 496467.62 | O65: =MIN(B65,N65) -> 496467.62 | P65: =N65-O65 -> 0 | Q65: =L65*Inputs!B6/12 -> 215625 | R65: =MIN(MAX(B65-O65,0),Q65) -> 200051.13 | S65: =Q65-R65 -> 15573.866 | T65: =MAX(B65-O65-R65,0) -> 0 | U65: =MIN(C65,K65) -> 1611246 | V65: =MIN(MAX(C65-U65,0),L65) -> 0 | W65: =MIN(MAX(C65-U65-V65,0),M65) -> 0 | X65: =MAX(K65-U65,0) -> 1.0199939e+08 | Y65: =MAX(L65-V65,0) -> 45000000 | Z65: =MAX(M65-W65,0) -> 10544016 | AA65: =C65-(U65+V65+W65) -> 0 | AB65: =B65-(O65+R65+T65) -> 0 | AC65: =D65-(H65+I65+J65) -> 0
A66: 65 | B66: =LoanPool!L66 -> 689252.39 | C66: =LoanPool!M66 -> 1596957.9 | D66: =LoanPool!H66 -> 49117.92 | E66: =X65 -> 1.0199939e+08 | F66: =Y65 -> 45000000 | G66: =Z65 -> 10544016 | H66: =MIN(D66,G66) -> 49117.92 | I66: =MIN(MAX(D66-H66,0),F66) -> 0 | J66: =MIN(MAX(D66-H66-I66,0),E66) -> 0 | K66: =MAX(E66-J66,0) -> 1.0199939e+08 | L66: =MAX(F66-I66,0) -> 45000000 | M66: =MAX(G66-H66,0) -> 10494898 | N66: =K66*Inputs!B6/12 -> 488747.07 | O66: =MIN(B66,N66) -> 488747.07 | P66: =N66-O66 -> 0 | Q66: =L66*Inputs!B6/12 -> 215625 | R66: =MIN(MAX(B66-O66,0),Q66) -> 200505.33 | S66: =Q66-R66 -> 15119.673 | T66: =MAX(B66-O66-R66,0) -> 0 | U66: =MIN(C66,K66) -> 1596957.9 | V66: =MIN(MAX(C66-U66,0),L66) -> 0 | W66: =MIN(MAX(C66-U66-V66,0),M66) -> 0 | X66: =MAX(K66-U66,0) -> 1.0040243e+08 | Y66: =MAX(L66-V66,0) -> 45000000 | Z66: =MAX(M66-W66,0) -> 10494898 | AA66: =C66-(U66+V66+W66) -> 0 | AB66: =B66-(O66+R66+T66) -> 0 | AC66: =D66-(H66+I66+J66) -> 0
A67: 66 | B67: =LoanPool!L67 -> 682050.81 | C67: =LoanPool!M67 -> 1582790.4 | D67: =LoanPool!H67 -> 48603.923 | E67: =X66 -> 1.0040243e+08 | F67: =Y66 -> 45000000 | G67: =Z66 -> 10494898 | H67: =MIN(D67,G67) -> 48603.923 | I67: =MIN(MAX(D67-H67,0),F67) -> 0 | J67: =MIN(MAX(D67-H67-I67,0),E67) -> 0 | K67: =MAX(E67-J67,0) -> 1.0040243e+08 | L67: =MAX(F67-I67,0) -> 45000000 | M67: =MAX(G67-H67,0) -> 10446295 | N67: =K67*Inputs!B6/12 -> 481094.98 | O67: =MIN(B67,N67) -> 481094.98 | P67: =N67-O67 -> 0 | Q67: =L67*Inputs!B6/12 -> 215625 | R67: =MIN(MAX(B67-O67,0),Q67) -> 200955.84 | S67: =Q67-R67 -> 14669.165 | T67: =MAX(B67-O67-R67,0) -> 0 | U67: =MIN(C67,K67) -> 1582790.4 | V67: =MIN(MAX(C67-U67,0),L67) -> 0 | W67: =MIN(MAX(C67-U67-V67,0),M67) -> 0 | X67: =MAX(K67-U67,0) -> 98819639 | Y67: =MAX(L67-V67,0) -> 45000000 | Z67: =MAX(M67-W67,0) -> 10446295 | AA67: =C67-(U67+V67+W67) -> 0 | AB67: =B67-(O67+R67+T67) -> 0 | AC67: =D67-(H67+I67+J67) -> 0
A68: 67 | B68: =LoanPool!L68 -> 674913.46 | C68: =LoanPool!M68 -> 1568742.5 | D68: =LoanPool!H68 -> 48094.513 | E68: =X67 -> 98819639 | F68: =Y67 -> 45000000 | G68: =Z67 -> 10446295 | H68: =MIN(D68,G68) -> 48094.513 | I68: =MIN(MAX(D68-H68,0),F68) -> 0 | J68: =MIN(MAX(D68-H68-I68,0),E68) -> 0 | K68: =MAX(E68-J68,0) -> 98819639 | L68: =MAX(F68-I68,0) -> 45000000 | M68: =MAX(G68-H68,0) -> 10398200 | N68: =K68*Inputs!B6/12 -> 473510.77 | O68: =MIN(B68,N68) -> 473510.77 | P68: =N68-O68 -> 0 | Q68: =L68*Inputs!B6/12 -> 215625 | R68: =MIN(MAX(B68-O68,0),Q68) -> 201402.69 | S68: =Q68-R68 -> 14222.311 | T68: =MAX(B68-O68-R68,0) -> 0 | U68: =MIN(C68,K68) -> 1568742.5 | V68: =MIN(MAX(C68-U68,0),L68) -> 0 | W68: =MIN(MAX(C68-U68-V68,0),M68) -> 0 | X68: =MAX(K68-U68,0) -> 97250897 | Y68: =MAX(L68-V68,0) -> 45000000 | Z68: =MAX(M68-W68,0) -> 10398200 | AA68: =C68-(U68+V68+W68) -> 0 | AB68: =B68-(O68+R68+T68) -> 0 | AC68: =D68-(H68+I68+J68) -> 0
A69: 68 | B69: =LoanPool!L69 -> 667839.8 | C69: =LoanPool!M69 -> 1554813.2 | D69: =LoanPool!H69 -> 47589.651 | E69: =X68 -> 97250897 | F69: =Y68 -> 45000000 | G69: =Z68 -> 10398200 | H69: =MIN(D69,G69) -> 47589.651 | I69: =MIN(MAX(D69-H69,0),F69) -> 0 | J69: =MIN(MAX(D69-H69-I69,0),E69) -> 0 | K69: =MAX(E69-J69,0) -> 97250897 | L69: =MAX(F69-I69,0) -> 45000000 | M69: =MAX(G69-H69,0) -> 10350610 | N69: =K69*Inputs!B6/12 -> 465993.88 | O69: =MIN(B69,N69) -> 465993.88 | P69: =N69-O69 -> 0 | Q69: =L69*Inputs!B6/12 -> 215625 | R69: =MIN(MAX(B69-O69,0),Q69) -> 201845.92 | S69: =Q69-R69 -> 13779.082 | T69: =MAX(B69-O69-R69,0) -> 0 | U69: =MIN(C69,K69) -> 1554813.2 | V69: =MIN(MAX(C69-U69,0),L69) -> 0 | W69: =MIN(MAX(C69-U69-V69,0),M69) -> 0 | X69: =MAX(K69-U69,0) -> 95696084 | Y69: =MAX(L69-V69,0) -> 45000000 | Z69: =MAX(M69-W69,0) -> 10350610 | AA69: =C69-(U69+V69+W69) -> 0 | AB69: =B69-(O69+R69+T69) -> 0 | AC69: =D69-(H69+I69+J69) -> 0
A70: 69 | B70: =LoanPool!L70 -> 660829.29 | C70: =LoanPool!M70 -> 1541001.6 | D70: =LoanPool!H70 -> 47089.297 | E70: =X69 -> 95696084 | F70: =Y69 -> 45000000 | G70: =Z69 -> 10350610 | H70: =MIN(D70,G70) -> 47089.297 | I70: =MIN(MAX(D70-H70,0),F70) -> 0 | J70: =MIN(MAX(D70-H70-I70,0),E70) -> 0 | K70: =MAX(E70-J70,0) -> 95696084 | L70: =MAX(F70-I70,0) -> 45000000 | M70: =MAX(G70-H70,0) -> 10303521 | N70: =K70*Inputs!B6/12 -> 458543.73 | O70: =MIN(B70,N70) -> 458543.73 | P70: =N70-O70 -> 0 | Q70: =L70*Inputs!B6/12 -> 215625 | R70: =MIN(MAX(B70-O70,0),Q70) -> 202285.55 | S70: =Q70-R70 -> 13339.448 | T70: =MAX(B70-O70-R70,0) -> 0 | U70: =MIN(C70,K70) -> 1541001.6 | V70: =MIN(MAX(C70-U70,0),L70) -> 0 | W70: =MIN(MAX(C70-U70-V70,0),M70) -> 0 | X70: =MAX(K70-U70,0) -> 94155082 | Y70: =MAX(L70-V70,0) -> 45000000 | Z70: =MAX(M70-W70,0) -> 10303521 | AA70: =C70-(U70+V70+W70) -> 0 | AB70: =B70-(O70+R70+T70) -> 0 | AC70: =D70-(H70+I70+J70) -> 0
A71: 70 | B71: =LoanPool!L71 -> 653881.39 | C71: =LoanPool!M71 -> 1527306.7 | D71: =LoanPool!H71 -> 46593.415 | E71: =X70 -> 94155082 | F71: =Y70 -> 45000000 | G71: =Z70 -> 10303521 | H71: =MIN(D71,G71) -> 46593.415 | I71: =MIN(MAX(D71-H71,0),F71) -> 0 | J71: =MIN(MAX(D71-H71-I71,0),E71) -> 0 | K71: =MAX(E71-J71,0) -> 94155082 | L71: =MAX(F71-I71,0) -> 45000000 | M71: =MAX(G71-H71,0) -> 10256928 | N71: =K71*Inputs!B6/12 -> 451159.77 | O71: =MIN(B71,N71) -> 451159.77 | P71: =N71-O71 -> 0 | Q71: =L71*Inputs!B6/12 -> 215625 | R71: =MIN(MAX(B71-O71,0),Q71) -> 202721.62 | S71: =Q71-R71 -> 12903.379 | T71: =MAX(B71-O71-R71,0) -> 0 | U71: =MIN(C71,K71) -> 1527306.7 | V71: =MIN(MAX(C71-U71,0),L71) -> 0 | W71: =MIN(MAX(C71-U71-V71,0),M71) -> 0 | X71: =MAX(K71-U71,0) -> 92627775 | Y71: =MAX(L71-V71,0) -> 45000000 | Z71: =MAX(M71-W71,0) -> 10256928 | AA71: =C71-(U71+V71+W71) -> 0 | AB71: =B71-(O71+R71+T71) -> 0 | AC71: =D71-(H71+I71+J71) -> 0
A72: 71 | B72: =LoanPool!L72 -> 646995.58 | C72: =LoanPool!M72 -> 1513727.5 | D72: =LoanPool!H72 -> 46101.966 | E72: =X71 -> 92627775 | F72: =Y71 -> 45000000 | G72: =Z71 -> 10256928 | H72: =MIN(D72,G72) -> 46101.966 | I72: =MIN(MAX(D72-H72,0),F72) -> 0 | J72: =MIN(MAX(D72-H72-I72,0),E72) -> 0 | K72: =MAX(E72-J72,0) -> 92627775 | L72: =MAX(F72-I72,0) -> 45000000 | M72: =MAX(G72-H72,0) -> 10210826 | N72: =K72*Inputs!B6/12 -> 443841.42 | O72: =MIN(B72,N72) -> 443841.42 | P72: =N72-O72 -> 0 | Q72: =L72*Inputs!B6/12 -> 215625 | R72: =MIN(MAX(B72-O72,0),Q72) -> 203154.15 | S72: =Q72-R72 -> 12470.848 | T72: =MAX(B72-O72-R72,0) -> 0 | U72: =MIN(C72,K72) -> 1513727.5 | V72: =MIN(MAX(C72-U72,0),L72) -> 0 | W72: =MIN(MAX(C72-U72-V72,0),M72) -> 0 | X72: =MAX(K72-U72,0) -> 91114048 | Y72: =MAX(L72-V72,0) -> 45000000 | Z72: =MAX(M72-W72,0) -> 10210826 | AA72: =C72-(U72+V72+W72) -> 0 | AB72: =B72-(O72+R72+T72) -> 0 | AC72: =D72-(H72+I72+J72) -> 0
A73: 72 | B73: =LoanPool!L73 -> 640171.32 | C73: =LoanPool!M73 -> 1500263 | D73: =LoanPool!H73 -> 45614.913 | E73: =X72 -> 91114048 | F73: =Y72 -> 45000000 | G73: =Z72 -> 10210826 | H73: =MIN(D73,G73) -> 45614.913 | I73: =MIN(MAX(D73-H73,0),F73) -> 0 | J73: =MIN(MAX(D73-H73-I73,0),E73) -> 0 | K73: =MAX(E73-J73,0) -> 91114048 | L73: =MAX(F73-I73,0) -> 45000000 | M73: =MAX(G73-H73,0) -> 10165211 | N73: =K73*Inputs!B6/12 -> 436588.15 | O73: =MIN(B73,N73) -> 436588.15 | P73: =N73-O73 -> 0 | Q73: =L73*Inputs!B6/12 -> 215625 | R73: =MIN(MAX(B73-O73,0),Q73) -> 203583.18 | S73: =Q73-R73 -> 12041.824 | T73: =MAX(B73-O73-R73,0) -> 0 | U73: =MIN(C73,K73) -> 1500263 | V73: =MIN(MAX(C73-U73,0),L73) -> 0 | W73: =MIN(MAX(C73-U73-V73,0),M73) -> 0 | X73: =MAX(K73-U73,0) -> 89613785 | Y73: =MAX(L73-V73,0) -> 45000000 | Z73: =MAX(M73-W73,0) -> 10165211 | AA73: =C73-(U73+V73+W73) -> 0 | AB73: =B73-(O73+R73+T73) -> 0 | AC73: =D73-(H73+I73+J73) -> 0
A74: 73 | B74: =LoanPool!L74 -> 633408.11 | C74: =LoanPool!M74 -> 1486912.3 | D74: =LoanPool!H74 -> 45132.218 | E74: =X73 -> 89613785 | F74: =Y73 -> 45000000 | G74: =Z73 -> 10165211 | H74: =MIN(D74,G74) -> 45132.218 | I74: =MIN(MAX(D74-H74,0),F74) -> 0 | J74: =MIN(MAX(D74-H74-I74,0),E74) -> 0 | K74: =MAX(E74-J74,0) -> 89613785 | L74: =MAX(F74-I74,0) -> 45000000 | M74: =MAX(G74-H74,0) -> 10120079 | N74: =K74*Inputs!B6/12 -> 429399.39 | O74: =MIN(B74,N74) -> 429399.39 | P74: =N74-O74 -> 0 | Q74: =L74*Inputs!B6/12 -> 215625 | R74: =MIN(MAX(B74-O74,0),Q74) -> 204008.72 | S74: =Q74-R74 -> 11616.28 | T74: =MAX(B74-O74-R74,0) -> 0 | U74: =MIN(C74,K74) -> 1486912.3 | V74: =MIN(MAX(C74-U74,0),L74) -> 0 | W74: =MIN(MAX(C74-U74-V74,0),M74) -> 0 | X74: =MAX(K74-U74,0) -> 88126873 | Y74: =MAX(L74-V74,0) -> 45000000 | Z74: =MAX(M74-W74,0) -> 10120079 | AA74: =C74-(U74+V74+W74) -> 0 | AB74: =B74-(O74+R74+T74) -> 0 | AC74: =D74-(H74+I74+J74) -> 0
A75: 74 | B75: =LoanPool!L75 -> 626705.41 | C75: =LoanPool!M75 -> 1473674.4 | D75: =LoanPool!H75 -> 44653.845 | E75: =X74 -> 88126873 | F75: =Y74 -> 45000000 | G75: =Z74 -> 10120079 | H75: =MIN(D75,G75) -> 44653.845 | I75: =MIN(MAX(D75-H75,0),F75) -> 0 | J75: =MIN(MAX(D75-H75-I75,0),E75) -> 0 | K75: =MAX(E75-J75,0) -> 88126873 | L75: =MAX(F75-I75,0) -> 45000000 | M75: =MAX(G75-H75,0) -> 10075425 | N75: =K75*Inputs!B6/12 -> 422274.6 | O75: =MIN(B75,N75) -> 422274.6 | P75: =N75-O75 -> 0 | Q75: =L75*Inputs!B6/12 -> 215625 | R75: =MIN(MAX(B75-O75,0),Q75) -> 204430.81 | S75: =Q75-R75 -> 11194.187 | T75: =MAX(B75-O75-R75,0) -> 0 | U75: =MIN(C75,K75) -> 1473674.4 | V75: =MIN(MAX(C75-U75,0),L75) -> 0 | W75: =MIN(MAX(C75-U75-V75,0),M75) -> 0 | X75: =MAX(K75-U75,0) -> 86653198 | Y75: =MAX(L75-V75,0) -> 45000000 | Z75: =MAX(M75-W75,0) -> 10075425 | AA75: =C75-(U75+V75+W75) -> 0 | AB75: =B75-(O75+R75+T75) -> 0 | AC75: =D75-(H75+I75+J75) -> 0
A76: 75 | B76: =LoanPool!L76 -> 620062.73 | C76: =LoanPool!M76 -> 1460548.5 | D76: =LoanPool!H76 -> 44179.756 | E76: =X75 -> 86653198 | F76: =Y75 -> 45000000 | G76: =Z75 -> 10075425 | H76: =MIN(D76,G76) -> 44179.756 | I76: =MIN(MAX(D76-H76,0),F76) -> 0 | J76: =MIN(MAX(D76-H76-I76,0),E76) -> 0 | K76: =MAX(E76-J76,0) -> 86653198 | L76: =MAX(F76-I76,0) -> 45000000 | M76: =MAX(G76-H76,0) -> 10031245 | N76: =K76*Inputs!B6/12 -> 415213.24 | O76: =MIN(B76,N76) -> 415213.24 | P76: =N76-O76 -> 0 | Q76: =L76*Inputs!B6/12 -> 215625 | R76: =MIN(MAX(B76-O76,0),Q76) -> 204849.48 | S76: =Q76-R76 -> 10775.516 | T76: =MAX(B76-O76-R76,0) -> 0 | U76: =MIN(C76,K76) -> 1460548.5 | V76: =MIN(MAX(C76-U76,0),L76) -> 0 | W76: =MIN(MAX(C76-U76-V76,0),M76) -> 0 | X76: =MAX(K76-U76,0) -> 85192650 | Y76: =MAX(L76-V76,0) -> 45000000 | Z76: =MAX(M76-W76,0) -> 10031245 | AA76: =C76-(U76+V76+W76) -> 0 | AB76: =B76-(O76+R76+T76) -> 0 | AC76: =D76-(H76+I76+J76) -> 0
A77: 76 | B77: =LoanPool!L77 -> 613479.54 | C77: =LoanPool!M77 -> 1447533.6 | D77: =LoanPool!H77 -> 43709.917 | E77: =X76 -> 85192650 | F77: =Y76 -> 45000000 | G77: =Z76 -> 10031245 | H77: =MIN(D77,G77) -> 43709.917 | I77: =MIN(MAX(D77-H77,0),F77) -> 0 | J77: =MIN(MAX(D77-H77-I77,0),E77) -> 0 | K77: =MAX(E77-J77,0) -> 85192650 | L77: =MAX(F77-I77,0) -> 45000000 | M77: =MAX(G77-H77,0) -> 9987535.1 | N77: =K77*Inputs!B6/12 -> 408214.78 | O77: =MIN(B77,N77) -> 408214.78 | P77: =N77-O77 -> 0 | Q77: =L77*Inputs!B6/12 -> 215625 | R77: =MIN(MAX(B77-O77,0),Q77) -> 205264.76 | S77: =Q77-R77 -> 10360.241 | T77: =MAX(B77-O77-R77,0) -> 0 | U77: =MIN(C77,K77) -> 1447533.6 | V77: =MIN(MAX(C77-U77,0),L77) -> 0 | W77: =MIN(MAX(C77-U77-V77,0),M77) -> 0 | X77: =MAX(K77-U77,0) -> 83745116 | Y77: =MAX(L77-V77,0) -> 45000000 | Z77: =MAX(M77-W77,0) -> 9987535.1 | AA77: =C77-(U77+V77+W77) -> 0 | AB77: =B77-(O77+R77+T77) -> 0 | AC77: =D77-(H77+I77+J77) -> 0
A78: 77 | B78: =LoanPool!L78 -> 606955.35 | C78: =LoanPool!M78 -> 1434628.7 | D78: =LoanPool!H78 -> 43244.289 | E78: =X77 -> 83745116 | F78: =Y77 -> 45000000 | G78: =Z77 -> 9987535.1 | H78: =MIN(D78,G78) -> 43244.289 | I78: =MIN(MAX(D78-H78,0),F78) -> 0 | J78: =MIN(MAX(D78-H78-I78,0),E78) -> 0 | K78: =MAX(E78-J78,0) -> 83745116 | L78: =MAX(F78-I78,0) -> 45000000 | M78: =MAX(G78-H78,0) -> 9944290.8 | N78: =K78*Inputs!B6/12 -> 401278.68 | O78: =MIN(B78,N78) -> 401278.68 | P78: =N78-O78 -> 0 | Q78: =L78*Inputs!B6/12 -> 215625 | R78: =MIN(MAX(B78-O78,0),Q78) -> 205676.67 | S78: =Q78-R78 -> 9948.3325 | T78: =MAX(B78-O78-R78,0) -> 0 | U78: =MIN(C78,K78) -> 1434628.7 | V78: =MIN(MAX(C78-U78,0),L78) -> 0 | W78: =MIN(MAX(C78-U78-V78,0),M78) -> 0 | X78: =MAX(K78-U78,0) -> 82310488 | Y78: =MAX(L78-V78,0) -> 45000000 | Z78: =MAX(M78-W78,0) -> 9944290.8 | AA78: =C78-(U78+V78+W78) -> 0 | AB78: =B78-(O78+R78+T78) -> 0 | AC78: =D78-(H78+I78+J78) -> 0
A79: 78 | B79: =LoanPool!L79 -> 600489.66 | C79: =LoanPool!M79 -> 1421833 | D79: =LoanPool!H79 -> 42782.839 | E79: =X78 -> 82310488 | F79: =Y78 -> 45000000 | G79: =Z78 -> 9944290.8 | H79: =MIN(D79,G79) -> 42782.839 | I79: =MIN(MAX(D79-H79,0),F79) -> 0 | J79: =MIN(MAX(D79-H79-I79,0),E79) -> 0 | K79: =MAX(E79-J79,0) -> 82310488 | L79: =MAX(F79-I79,0) -> 45000000 | M79: =MAX(G79-H79,0) -> 9901507.9 | N79: =K79*Inputs!B6/12 -> 394404.42 | O79: =MIN(B79,N79) -> 394404.42 | P79: =N79-O79 -> 0 | Q79: =L79*Inputs!B6/12 -> 215625 | R79: =MIN(MAX(B79-O79,0),Q79) -> 206085.24 | S79: =Q79-R79 -> 9539.7643 | T79: =MAX(B79-O79-R79,0) -> 0 | U79: =MIN(C79,K79) -> 1421833 | V79: =MIN(MAX(C79-U79,0),L79) -> 0 | W79: =MIN(MAX(C79-U79-V79,0),M79) -> 0 | X79: =MAX(K79-U79,0) -> 80888655 | Y79: =MAX(L79-V79,0) -> 45000000 | Z79: =MAX(M79-W79,0) -> 9901507.9 | AA79: =C79-(U79+V79+W79) -> 0 | AB79: =B79-(O79+R79+T79) -> 0 | AC79: =D79-(H79+I79+J79) -> 0
A80: 79 | B80: =LoanPool!L80 -> 594081.96 | C80: =LoanPool!M80 -> 1409145.5 | D80: =LoanPool!H80 -> 42325.53 | E80: =X79 -> 80888655 | F80: =Y79 -> 45000000 | G80: =Z79 -> 9901507.9 | H80: =MIN(D80,G80) -> 42325.53 | I80: =MIN(MAX(D80-H80,0),F80) -> 0 | J80: =MIN(MAX(D80-H80-I80,0),E80) -> 0 | K80: =MAX(E80-J80,0) -> 80888655 | L80: =MAX(F80-I80,0) -> 45000000 | M80: =MAX(G80-H80,0) -> 9859182.4 | N80: =K80*Inputs!B6/12 -> 387591.47 | O80: =MIN(B80,N80) -> 387591.47 | P80: =N80-O80 -> 0 | Q80: =L80*Inputs!B6/12 -> 215625 | R80: =MIN(MAX(B80-O80,0),Q80) -> 206490.49 | S80: =Q80-R80 -> 9134.5089 | T80: =MAX(B80-O80-R80,0) -> 0 | U80: =MIN(C80,K80) -> 1409145.5 | V80: =MIN(MAX(C80-U80,0),L80) -> 0 | W80: =MIN(MAX(C80-U80-V80,0),M80) -> 0 | X80: =MAX(K80-U80,0) -> 79479509 | Y80: =MAX(L80-V80,0) -> 45000000 | Z80: =MAX(M80-W80,0) -> 9859182.4 | AA80: =C80-(U80+V80+W80) -> 0 | AB80: =B80-(O80+R80+T80) -> 0 | AC80: =D80-(H80+I80+J80) -> 0
A81: 80 | B81: =LoanPool!L81 -> 587731.77 | C81: =LoanPool!M81 -> 1396565.4 | D81: =LoanPool!H81 -> 41872.327 | E81: =X80 -> 79479509 | F81: =Y80 -> 45000000 | G81: =Z80 -> 9859182.4 | H81: =MIN(D81,G81) -> 41872.327 | I81: =MIN(MAX(D81-H81,0),F81) -> 0 | J81: =MIN(MAX(D81-H81-I81,0),E81) -> 0 | K81: =MAX(E81-J81,0) -> 79479509 | L81: =MAX(F81-I81,0) -> 45000000 | M81: =MAX(G81-H81,0) -> 9817310.1 | N81: =K81*Inputs!B6/12 -> 380839.31 | O81: =MIN(B81,N81) -> 380839.31 | P81: =N81-O81 -> 0 | Q81: =L81*Inputs!B6/12 -> 215625 | R81: =MIN(MAX(B81-O81,0),Q81) -> 206892.46 | S81: =Q81-R81 -> 8732.5391 | T81: =MAX(B81-O81-R81,0) -> 0 | U81: =MIN(C81,K81) -> 1396565.4 | V81: =MIN(MAX(C81-U81,0),L81) -> 0 | W81: =MIN(MAX(C81-U81-V81,0),M81) -> 0 | X81: =MAX(K81-U81,0) -> 78082944 | Y81: =MAX(L81-V81,0) -> 45000000 | Z81: =MAX(M81-W81,0) -> 9817310.1 | AA81: =C81-(U81+V81+W81) -> 0 | AB81: =B81-(O81+R81+T81) -> 0 | AC81: =D81-(H81+I81+J81) -> 0
A82: 81 | B82: =LoanPool!L82 -> 581438.61 | C82: =LoanPool!M82 -> 1384091.8 | D82: =LoanPool!H82 -> 41423.196 | E82: =X81 -> 78082944 | F82: =Y81 -> 45000000 | G82: =Z81 -> 9817310.1 | H82: =MIN(D82,G82) -> 41423.196 | I82: =MIN(MAX(D82-H82,0),F82) -> 0 | J82: =MIN(MAX(D82-H82-I82,0),E82) -> 0 | K82: =MAX(E82-J82,0) -> 78082944 | L82: =MAX(F82-I82,0) -> 45000000 | M82: =MAX(G82-H82,0) -> 9775886.9 | N82: =K82*Inputs!B6/12 -> 374147.44 | O82: =MIN(B82,N82) -> 374147.44 | P82: =N82-O82 -> 0 | Q82: =L82*Inputs!B6/12 -> 215625 | R82: =MIN(MAX(B82-O82,0),Q82) -> 207291.17 | S82: =Q82-R82 -> 8333.8282 | T82: =MAX(B82-O82-R82,0) -> 0 | U82: =MIN(C82,K82) -> 1384091.8 | V82: =MIN(MAX(C82-U82,0),L82) -> 0 | W82: =MIN(MAX(C82-U82-V82,0),M82) -> 0 | X82: =MAX(K82-U82,0) -> 76698852 | Y82: =MAX(L82-V82,0) -> 45000000 | Z82: =MAX(M82-W82,0) -> 9775886.9 | AA82: =C82-(U82+V82+W82) -> 0 | AB82: =B82-(O82+R82+T82) -> 0 | AC82: =D82-(H82+I82+J82) -> 0
A83: 82 | B83: =LoanPool!L83 -> 575201.98 | C83: =LoanPool!M83 -> 1371723.8 | D83: =LoanPool!H83 -> 40978.102 | E83: =X82 -> 76698852 | F83: =Y82 -> 45000000 | G83: =Z82 -> 9775886.9 | H83: =MIN(D83,G83) -> 40978.102 | I83: =MIN(MAX(D83-H83,0),F83) -> 0 | J83: =MIN(MAX(D83-H83-I83,0),E83) -> 0 | K83: =MAX(E83-J83,0) -> 76698852 | L83: =MAX(F83-I83,0) -> 45000000 | M83: =MAX(G83-H83,0) -> 9734908.8 | N83: =K83*Inputs!B6/12 -> 367515.33 | O83: =MIN(B83,N83) -> 367515.33 | P83: =N83-O83 -> 0 | Q83: =L83*Inputs!B6/12 -> 215625 | R83: =MIN(MAX(B83-O83,0),Q83) -> 207686.65 | S83: =Q83-R83 -> 7938.3498 | T83: =MAX(B83-O83-R83,0) -> 0 | U83: =MIN(C83,K83) -> 1371723.8 | V83: =MIN(MAX(C83-U83,0),L83) -> 0 | W83: =MIN(MAX(C83-U83-V83,0),M83) -> 0 | X83: =MAX(K83-U83,0) -> 75327128 | Y83: =MAX(L83-V83,0) -> 45000000 | Z83: =MAX(M83-W83,0) -> 9734908.8 | AA83: =C83-(U83+V83+W83) -> 0 | AB83: =B83-(O83+R83+T83) -> 0 | AC83: =D83-(H83+I83+J83) -> 0
A84: 83 | B84: =LoanPool!L84 -> 569021.41 | C84: =LoanPool!M84 -> 1359460.4 | D84: =LoanPool!H84 -> 40537.011 | E84: =X83 -> 75327128 | F84: =Y83 -> 45000000 | G84: =Z83 -> 9734908.8 | H84: =MIN(D84,G84) -> 40537.011 | I84: =MIN(MAX(D84-H84,0),F84) -> 0 | J84: =MIN(MAX(D84-H84-I84,0),E84) -> 0 | K84: =MAX(E84-J84,0) -> 75327128 | L84: =MAX(F84-I84,0) -> 45000000 | M84: =MAX(G84-H84,0) -> 9694371.8 | N84: =K84*Inputs!B6/12 -> 360942.49 | O84: =MIN(B84,N84) -> 360942.49 | P84: =N84-O84 -> 0 | Q84: =L84*Inputs!B6/12 -> 215625 | R84: =MIN(MAX(B84-O84,0),Q84) -> 208078.92 | S84: =Q84-R84 -> 7546.0774 | T84: =MAX(B84-O84-R84,0) -> 0 | U84: =MIN(C84,K84) -> 1359460.4 | V84: =MIN(MAX(C84-U84,0),L84) -> 0 | W84: =MIN(MAX(C84-U84-V84,0),M84) -> 0 | X84: =MAX(K84-U84,0) -> 73967668 | Y84: =MAX(L84-V84,0) -> 45000000 | Z84: =MAX(M84-W84,0) -> 9694371.8 | AA84: =C84-(U84+V84+W84) -> 0 | AB84: =B84-(O84+R84+T84) -> 0 | AC84: =D84-(H84+I84+J84) -> 0
A85: 84 | B85: =LoanPool!L85 -> 562896.42 | C85: =LoanPool!M85 -> 1347300.9 | D85: =LoanPool!H85 -> 40099.888 | E85: =X84 -> 73967668 | F85: =Y84 -> 45000000 | G85: =Z84 -> 9694371.8 | H85: =MIN(D85,G85) -> 40099.888 | I85: =MIN(MAX(D85-H85,0),F85) -> 0 | J85: =MIN(MAX(D85-H85-I85,0),E85) -> 0 | K85: =MAX(E85-J85,0) -> 73967668 | L85: =MAX(F85-I85,0) -> 45000000 | M85: =MAX(G85-H85,0) -> 9654271.9 | N85: =K85*Inputs!B6/12 -> 354428.41 | O85: =MIN(B85,N85) -> 354428.41 | P85: =N85-O85 -> 0 | Q85: =L85*Inputs!B6/12 -> 215625 | R85: =MIN(MAX(B85-O85,0),Q85) -> 208468.01 | S85: =Q85-R85 -> 7156.985 | T85: =MAX(B85-O85-R85,0) -> 0 | U85: =MIN(C85,K85) -> 1347300.9 | V85: =MIN(MAX(C85-U85,0),L85) -> 0 | W85: =MIN(MAX(C85-U85-V85,0),M85) -> 0 | X85: =MAX(K85-U85,0) -> 72620367 | Y85: =MAX(L85-V85,0) -> 45000000 | Z85: =MAX(M85-W85,0) -> 9654271.9 | AA85: =C85-(U85+V85+W85) -> 0 | AB85: =B85-(O85+R85+T85) -> 0 | AC85: =D85-(H85+I85+J85) -> 0
A86: 85 | B86: =LoanPool!L86 -> 556826.54 | C86: =LoanPool!M86 -> 1335244.4 | D86: =LoanPool!H86 -> 39666.701 | E86: =X85 -> 72620367 | F86: =Y85 -> 45000000 | G86: =Z85 -> 9654271.9 | H86: =MIN(D86,G86) -> 39666.701 | I86: =MIN(MAX(D86-H86,0),F86) -> 0 | J86: =MIN(MAX(D86-H86-I86,0),E86) -> 0 | K86: =MAX(E86-J86,0) -> 72620367 | L86: =MAX(F86-I86,0) -> 45000000 | M86: =MAX(G86-H86,0) -> 9614605.2 | N86: =K86*Inputs!B6/12 -> 347972.59 | O86: =MIN(B86,N86) -> 347972.59 | P86: =N86-O86 -> 0 | Q86: =L86*Inputs!B6/12 -> 215625 | R86: =MIN(MAX(B86-O86,0),Q86) -> 208853.95 | S86: =Q86-R86 -> 6771.0466 | T86: =MAX(B86-O86-R86,0) -> 0 | U86: =MIN(C86,K86) -> 1335244.4 | V86: =MIN(MAX(C86-U86,0),L86) -> 0 | W86: =MIN(MAX(C86-U86-V86,0),M86) -> 0 | X86: =MAX(K86-U86,0) -> 71285122 | Y86: =MAX(L86-V86,0) -> 45000000 | Z86: =MAX(M86-W86,0) -> 9614605.2 | AA86: =C86-(U86+V86+W86) -> 0 | AB86: =B86-(O86+R86+T86) -> 0 | AC86: =D86-(H86+I86+J86) -> 0
A87: 86 | B87: =LoanPool!L87 -> 550811.31 | C87: =LoanPool!M87 -> 1323290 | D87: =LoanPool!H87 -> 39237.415 | E87: =X86 -> 71285122 | F87: =Y86 -> 45000000 | G87: =Z86 -> 9614605.2 | H87: =MIN(D87,G87) -> 39237.415 | I87: =MIN(MAX(D87-H87,0),F87) -> 0 | J87: =MIN(MAX(D87-H87-I87,0),E87) -> 0 | K87: =MAX(E87-J87,0) -> 71285122 | L87: =MAX(F87-I87,0) -> 45000000 | M87: =MAX(G87-H87,0) -> 9575367.8 | N87: =K87*Inputs!B6/12 -> 341574.54 | O87: =MIN(B87,N87) -> 341574.54 | P87: =N87-O87 -> 0 | Q87: =L87*Inputs!B6/12 -> 215625 | R87: =MIN(MAX(B87-O87,0),Q87) -> 209236.76 | S87: =Q87-R87 -> 6388.2366 | T87: =MAX(B87-O87-R87,0) -> 0 | U87: =MIN(C87,K87) -> 1323290 | V87: =MIN(MAX(C87-U87,0),L87) -> 0 | W87: =MIN(MAX(C87-U87-V87,0),M87) -> 0 | X87: =MAX(K87-U87,0) -> 69961832 | Y87: =MAX(L87-V87,0) -> 45000000 | Z87: =MAX(M87-W87,0) -> 9575367.8 | AA87: =C87-(U87+V87+W87) -> 0 | AB87: =B87-(O87+R87+T87) -> 0 | AC87: =D87-(H87+I87+J87) -> 0
A88: 87 | B88: =LoanPool!L88 -> 544850.25 | C88: =LoanPool!M88 -> 1311436.9 | D88: =LoanPool!H88 -> 38811.998 | E88: =X87 -> 69961832 | F88: =Y87 -> 45000000 | G88: =Z87 -> 9575367.8 | H88: =MIN(D88,G88) -> 38811.998 | I88: =MIN(MAX(D88-H88,0),F88) -> 0 | J88: =MIN(MAX(D88-H88-I88,0),E88) -> 0 | K88: =MAX(E88-J88,0) -> 69961832 | L88: =MAX(F88-I88,0) -> 45000000 | M88: =MAX(G88-H88,0) -> 9536555.8 | N88: =K88*Inputs!B6/12 -> 335233.78 | O88: =MIN(B88,N88) -> 335233.78 | P88: =N88-O88 -> 0 | Q88: =L88*Inputs!B6/12 -> 215625 | R88: =MIN(MAX(B88-O88,0),Q88) -> 209616.47 | S88: =Q88-R88 -> 6008.5295 | T88: =MAX(B88-O88-R88,0) -> 0 | U88: =MIN(C88,K88) -> 1311436.9 | V88: =MIN(MAX(C88-U88,0),L88) -> 0 | W88: =MIN(MAX(C88-U88-V88,0),M88) -> 0 | X88: =MAX(K88-U88,0) -> 68650395 | Y88: =MAX(L88-V88,0) -> 45000000 | Z88: =MAX(M88-W88,0) -> 9536555.8 | AA88: =C88-(U88+V88+W88) -> 0 | AB88: =B88-(O88+R88+T88) -> 0 | AC88: =D88-(H88+I88+J88) -> 0
A89: 88 | B89: =LoanPool!L89 -> 538942.91 | C89: =LoanPool!M89 -> 1299684.2 | D89: =LoanPool!H89 -> 38390.416 | E89: =X88 -> 68650395 | F89: =Y88 -> 45000000 | G89: =Z88 -> 9536555.8 | H89: =MIN(D89,G89) -> 38390.416 | I89: =MIN(MAX(D89-H89,0),F89) -> 0 | J89: =MIN(MAX(D89-H89-I89,0),E89) -> 0 | K89: =MAX(E89-J89,0) -> 68650395 | L89: =MAX(F89-I89,0) -> 45000000 | M89: =MAX(G89-H89,0) -> 9498165.3 | N89: =K89*Inputs!B6/12 -> 328949.81 | O89: =MIN(B89,N89) -> 328949.81 | P89: =N89-O89 -> 0 | Q89: =L89*Inputs!B6/12 -> 215625 | R89: =MIN(MAX(B89-O89,0),Q89) -> 209993.1 | S89: =Q89-R89 -> 5631.9 | T89: =MAX(B89-O89-R89,0) -> 0 | U89: =MIN(C89,K89) -> 1299684.2 | V89: =MIN(MAX(C89-U89,0),L89) -> 0 | W89: =MIN(MAX(C89-U89-V89,0),M89) -> 0 | X89: =MAX(K89-U89,0) -> 67350711 | Y89: =MAX(L89-V89,0) -> 45000000 | Z89: =MAX(M89-W89,0) -> 9498165.3 | AA89: =C89-(U89+V89+W89) -> 0 | AB89: =B89-(O89+R89+T89) -> 0 | AC89: =D89-(H89+I89+J89) -> 0
A90: 89 | B90: =LoanPool!L90 -> 533088.84 | C90: =LoanPool!M90 -> 1288031.1 | D90: =LoanPool!H90 -> 37972.638 | E90: =X89 -> 67350711 | F90: =Y89 -> 45000000 | G90: =Z89 -> 9498165.3 | H90: =MIN(D90,G90) -> 37972.638 | I90: =MIN(MAX(D90-H90,0),F90) -> 0 | J90: =MIN(MAX(D90-H90-I90,0),E90) -> 0 | K90: =MAX(E90-J90,0) -> 67350711 | L90: =MAX(F90-I90,0) -> 45000000 | M90: =MAX(G90-H90,0) -> 9460192.7 | N90: =K90*Inputs!B6/12 -> 322722.16 | O90: =MIN(B90,N90) -> 322722.16 | P90: =N90-O90 -> 0 | Q90: =L90*Inputs!B6/12 -> 215625 | R90: =MIN(MAX(B90-O90,0),Q90) -> 210366.68 | S90: =Q90-R90 -> 5258.323 | T90: =MAX(B90-O90-R90,0) -> 0 | U90: =MIN(C90,K90) -> 1288031.1 | V90: =MIN(MAX(C90-U90,0),L90) -> 0 | W90: =MIN(MAX(C90-U90-V90,0),M90) -> 0 | X90: =MAX(K90-U90,0) -> 66062680 | Y90: =MAX(L90-V90,0) -> 45000000 | Z90: =MAX(M90-W90,0) -> 9460192.7 | AA90: =C90-(U90+V90+W90) -> 0 | AB90: =B90-(O90+R90+T90) -> 0 | AC90: =D90-(H90+I90+J90) -> 0
A91: 90 | B91: =LoanPool!L91 -> 527287.57 | C91: =LoanPool!M91 -> 1276476.8 | D91: =LoanPool!H91 -> 37558.63 | E91: =X90 -> 66062680 | F91: =Y90 -> 45000000 | G91: =Z90 -> 9460192.7 | H91: =MIN(D91,G91) -> 37558.63 | I91: =MIN(MAX(D91-H91,0),F91) -> 0 | J91: =MIN(MAX(D91-H91-I91,0),E91) -> 0 | K91: =MAX(E91-J91,0) -> 66062680 | L91: =MAX(F91-I91,0) -> 45000000 | M91: =MAX(G91-H91,0) -> 9422634.1 | N91: =K91*Inputs!B6/12 -> 316550.34 | O91: =MIN(B91,N91) -> 316550.34 | P91: =N91-O91 -> 0 | Q91: =L91*Inputs!B6/12 -> 215625 | R91: =MIN(MAX(B91-O91,0),Q91) -> 210737.23 | S91: =Q91-R91 -> 4887.7736 | T91: =MAX(B91-O91-R91,0) -> 0 | U91: =MIN(C91,K91) -> 1276476.8 | V91: =MIN(MAX(C91-U91,0),L91) -> 0 | W91: =MIN(MAX(C91-U91-V91,0),M91) -> 0 | X91: =MAX(K91-U91,0) -> 64786203 | Y91: =MAX(L91-V91,0) -> 45000000 | Z91: =MAX(M91-W91,0) -> 9422634.1 | AA91: =C91-(U91+V91+W91) -> 0 | AB91: =B91-(O91+R91+T91) -> 0 | AC91: =D91-(H91+I91+J91) -> 0
A92: 91 | B92: =LoanPool!L92 -> 521538.66 | C92: =LoanPool!M92 -> 1265020.4 | D92: =LoanPool!H92 -> 37148.361 | E92: =X91 -> 64786203 | F92: =Y91 -> 45000000 | G92: =Z91 -> 9422634.1 | H92: =MIN(D92,G92) -> 37148.361 | I92: =MIN(MAX(D92-H92,0),F92) -> 0 | J92: =MIN(MAX(D92-H92-I92,0),E92) -> 0 | K92: =MAX(E92-J92,0) -> 64786203 | L92: =MAX(F92-I92,0) -> 45000000 | M92: =MAX(G92-H92,0) -> 9385485.7 | N92: =K92*Inputs!B6/12 -> 310433.89 | O92: =MIN(B92,N92) -> 310433.89 | P92: =N92-O92 -> 0 | Q92: =L92*Inputs!B6/12 -> 215625 | R92: =MIN(MAX(B92-O92,0),Q92) -> 211104.77 | S92: =Q92-R92 -> 4520.2273 | T92: =MAX(B92-O92-R92,0) -> 0 | U92: =MIN(C92,K92) -> 1265020.4 | V92: =MIN(MAX(C92-U92,0),L92) -> 0 | W92: =MIN(MAX(C92-U92-V92,0),M92) -> 0 | X92: =MAX(K92-U92,0) -> 63521183 | Y92: =MAX(L92-V92,0) -> 45000000 | Z92: =MAX(M92-W92,0) -> 9385485.7 | AA92: =C92-(U92+V92+W92) -> 0 | AB92: =B92-(O92+R92+T92) -> 0 | AC92: =D92-(H92+I92+J92) -> 0
A93: 92 | B93: =LoanPool!L93 -> 515841.68 | C93: =LoanPool!M93 -> 1253661.2 | D93: =LoanPool!H93 -> 36741.799 | E93: =X92 -> 63521183 | F93: =Y92 -> 45000000 | G93: =Z92 -> 9385485.7 | H93: =MIN(D93,G93) -> 36741.799 | I93: =MIN(MAX(D93-H93,0),F93) -> 0 | J93: =MIN(MAX(D93-H93-I93,0),E93) -> 0 | K93: =MAX(E93-J93,0) -> 63521183 | L93: =MAX(F93-I93,0) -> 45000000 | M93: =MAX(G93-H93,0) -> 9348743.9 | N93: =K93*Inputs!B6/12 -> 304372.33 | O93: =MIN(B93,N93) -> 304372.33 | P93: =N93-O93 -> 0 | Q93: =L93*Inputs!B6/12 -> 215625 | R93: =MIN(MAX(B93-O93,0),Q93) -> 211469.34 | S93: =Q93-R93 -> 4155.6595 | T93: =MAX(B93-O93-R93,0) -> 0 | U93: =MIN(C93,K93) -> 1253661.2 | V93: =MIN(MAX(C93-U93,0),L93) -> 0 | W93: =MIN(MAX(C93-U93-V93,0),M93) -> 0 | X93: =MAX(K93-U93,0) -> 62267522 | Y93: =MAX(L93-V93,0) -> 45000000 | Z93: =MAX(M93-W93,0) -> 9348743.9 | AA93: =C93-(U93+V93+W93) -> 0 | AB93: =B93-(O93+R93+T93) -> 0 | AC93: =D93-(H93+I93+J93) -> 0
A94: 93 | B94: =LoanPool!L94 -> 510196.16 | C94: =LoanPool!M94 -> 1242398.4 | D94: =LoanPool!H94 -> 36338.913 | E94: =X93 -> 62267522 | F94: =Y93 -> 45000000 | G94: =Z93 -> 9348743.9 | H94: =MIN(D94,G94) -> 36338.913 | I94: =MIN(MAX(D94-H94,0),F94) -> 0 | J94: =MIN(MAX(D94-H94-I94,0),E94) -> 0 | K94: =MAX(E94-J94,0) -> 62267522 | L94: =MAX(F94-I94,0) -> 45000000 | M94: =MAX(G94-H94,0) -> 9312405 | N94: =K94*Inputs!B6/12 -> 298365.21 | O94: =MIN(B94,N94) -> 298365.21 | P94: =N94-O94 -> 0 | Q94: =L94*Inputs!B6/12 -> 215625 | R94: =MIN(MAX(B94-O94,0),Q94) -> 211830.95 | S94: =Q94-R94 -> 3794.0461 | T94: =MAX(B94-O94-R94,0) -> 0 | U94: =MIN(C94,K94) -> 1242398.4 | V94: =MIN(MAX(C94-U94,0),L94) -> 0 | W94: =MIN(MAX(C94-U94-V94,0),M94) -> 0 | X94: =MAX(K94-U94,0) -> 61025123 | Y94: =MAX(L94-V94,0) -> 45000000 | Z94: =MAX(M94-W94,0) -> 9312405 | AA94: =C94-(U94+V94+W94) -> 0 | AB94: =B94-(O94+R94+T94) -> 0 | AC94: =D94-(H94+I94+J94) -> 0
A95: 94 | B95: =LoanPool!L95 -> 504601.69 | C95: =LoanPool!M95 -> 1231231 | D95: =LoanPool!H95 -> 35939.671 | E95: =X94 -> 61025123 | F95: =Y94 -> 45000000 | G95: =Z94 -> 9312405 | H95: =MIN(D95,G95) -> 35939.671 | I95: =MIN(MAX(D95-H95,0),F95) -> 0 | J95: =MIN(MAX(D95-H95-I95,0),E95) -> 0 | K95: =MAX(E95-J95,0) -> 61025123 | L95: =MAX(F95-I95,0) -> 45000000 | M95: =MAX(G95-H95,0) -> 9276465.3 | N95: =K95*Inputs!B6/12 -> 292412.05 | O95: =MIN(B95,N95) -> 292412.05 | P95: =N95-O95 -> 0 | Q95: =L95*Inputs!B6/12 -> 215625 | R95: =MIN(MAX(B95-O95,0),Q95) -> 212189.64 | S95: =Q95-R95 -> 3435.3628 | T95: =MAX(B95-O95-R95,0) -> 0 | U95: =MIN(C95,K95) -> 1231231 | V95: =MIN(MAX(C95-U95,0),L95) -> 0 | W95: =MIN(MAX(C95-U95-V95,0),M95) -> 0 | X95: =MAX(K95-U95,0) -> 59793892 | Y95: =MAX(L95-V95,0) -> 45000000 | Z95: =MAX(M95-W95,0) -> 9276465.3 | AA95: =C95-(U95+V95+W95) -> 0 | AB95: =B95-(O95+R95+T95) -> 0 | AC95: =D95-(H95+I95+J95) -> 0
A96: 95 | B96: =LoanPool!L96 -> 499057.81 | C96: =LoanPool!M96 -> 1220158.5 | D96: =LoanPool!H96 -> 35544.042 | E96: =X95 -> 59793892 | F96: =Y95 -> 45000000 | G96: =Z95 -> 9276465.3 | H96: =MIN(D96,G96) -> 35544.042 | I96: =MIN(MAX(D96-H96,0),F96) -> 0 | J96: =MIN(MAX(D96-H96-I96,0),E96) -> 0 | K96: =MAX(E96-J96,0) -> 59793892 | L96: =MAX(F96-I96,0) -> 45000000 | M96: =MAX(G96-H96,0) -> 9240921.3 | N96: =K96*Inputs!B6/12 -> 286512.4 | O96: =MIN(B96,N96) -> 286512.4 | P96: =N96-O96 -> 0 | Q96: =L96*Inputs!B6/12 -> 215625 | R96: =MIN(MAX(B96-O96,0),Q96) -> 212545.41 | S96: =Q96-R96 -> 3079.586 | T96: =MAX(B96-O96-R96,0) -> 0 | U96: =MIN(C96,K96) -> 1220158.5 | V96: =MIN(MAX(C96-U96,0),L96) -> 0 | W96: =MIN(MAX(C96-U96-V96,0),M96) -> 0 | X96: =MAX(K96-U96,0) -> 58573734 | Y96: =MAX(L96-V96,0) -> 45000000 | Z96: =MAX(M96-W96,0) -> 9240921.3 | AA96: =C96-(U96+V96+W96) -> 0 | AB96: =B96-(O96+R96+T96) -> 0 | AC96: =D96-(H96+I96+J96) -> 0
A97: 96 | B97: =LoanPool!L97 -> 493564.12 | C97: =LoanPool!M97 -> 1209179.8 | D97: =LoanPool!H97 -> 35151.995 | E97: =X96 -> 58573734 | F97: =Y96 -> 45000000 | G97: =Z96 -> 9240921.3 | H97: =MIN(D97,G97) -> 35151.995 | I97: =MIN(MAX(D97-H97,0),F97) -> 0 | J97: =MIN(MAX(D97-H97-I97,0),E97) -> 0 | K97: =MAX(E97-J97,0) -> 58573734 | L97: =MAX(F97-I97,0) -> 45000000 | M97: =MAX(G97-H97,0) -> 9205769.3 | N97: =K97*Inputs!B6/12 -> 280665.81 | O97: =MIN(B97,N97) -> 280665.81 | P97: =N97-O97 -> 0 | Q97: =L97*Inputs!B6/12 -> 215625 | R97: =MIN(MAX(B97-O97,0),Q97) -> 212898.31 | S97: =Q97-R97 -> 2726.6918 | T97: =MAX(B97-O97-R97,0) -> 0 | U97: =MIN(C97,K97) -> 1209179.8 | V97: =MIN(MAX(C97-U97,0),L97) -> 0 | W97: =MIN(MAX(C97-U97-V97,0),M97) -> 0 | X97: =MAX(K97-U97,0) -> 57364554 | Y97: =MAX(L97-V97,0) -> 45000000 | Z97: =MAX(M97-W97,0) -> 9205769.3 | AA97: =C97-(U97+V97+W97) -> 0 | AB97: =B97-(O97+R97+T97) -> 0 | AC97: =D97-(H97+I97+J97) -> 0
A98: 97 | B98: =LoanPool!L98 -> 488120.16 | C98: =LoanPool!M98 -> 1198294.4 | D98: =LoanPool!H98 -> 34763.501 | E98: =X97 -> 57364554 | F98: =Y97 -> 45000000 | G98: =Z97 -> 9205769.3 | H98: =MIN(D98,G98) -> 34763.501 | I98: =MIN(MAX(D98-H98,0),F98) -> 0 | J98: =MIN(MAX(D98-H98-I98,0),E98) -> 0 | K98: =MAX(E98-J98,0) -> 57364554 | L98: =MAX(F98-I98,0) -> 45000000 | M98: =MAX(G98-H98,0) -> 9171005.8 | N98: =K98*Inputs!B6/12 -> 274871.82 | O98: =MIN(B98,N98) -> 274871.82 | P98: =N98-O98 -> 0 | Q98: =L98*Inputs!B6/12 -> 215625 | R98: =MIN(MAX(B98-O98,0),Q98) -> 213248.34 | S98: =Q98-R98 -> 2376.6568 | T98: =MAX(B98-O98-R98,0) -> 0 | U98: =MIN(C98,K98) -> 1198294.4 | V98: =MIN(MAX(C98-U98,0),L98) -> 0 | W98: =MIN(MAX(C98-U98-V98,0),M98) -> 0 | X98: =MAX(K98-U98,0) -> 56166260 | Y98: =MAX(L98-V98,0) -> 45000000 | Z98: =MAX(M98-W98,0) -> 9171005.8 | AA98: =C98-(U98+V98+W98) -> 0 | AB98: =B98-(O98+R98+T98) -> 0 | AC98: =D98-(H98+I98+J98) -> 0
A99: 98 | B99: =LoanPool!L99 -> 482725.54 | C99: =LoanPool!M99 -> 1187501.4 | D99: =LoanPool!H99 -> 34378.528 | E99: =X98 -> 56166260 | F99: =Y98 -> 45000000 | G99: =Z98 -> 9171005.8 | H99: =MIN(D99,G99) -> 34378.528 | I99: =MIN(MAX(D99-H99,0),F99) -> 0 | J99: =MIN(MAX(D99-H99-I99,0),E99) -> 0 | K99: =MAX(E99-J99,0) -> 56166260 | L99: =MAX(F99-I99,0) -> 45000000 | M99: =MAX(G99-H99,0) -> 9136627.3 | N99: =K99*Inputs!B6/12 -> 269129.99 | O99: =MIN(B99,N99) -> 269129.99 | P99: =N99-O99 -> 0 | Q99: =L99*Inputs!B6/12 -> 215625 | R99: =MIN(MAX(B99-O99,0),Q99) -> 213595.54 | S99: =Q99-R99 -> 2029.4578 | T99: =MAX(B99-O99-R99,0) -> 0 | U99: =MIN(C99,K99) -> 1187501.4 | V99: =MIN(MAX(C99-U99,0),L99) -> 0 | W99: =MIN(MAX(C99-U99-V99,0),M99) -> 0 | X99: =MAX(K99-U99,0) -> 54978758 | Y99: =MAX(L99-V99,0) -> 45000000 | Z99: =MAX(M99-W99,0) -> 9136627.3 | AA99: =C99-(U99+V99+W99) -> 0 | AB99: =B99-(O99+R99+T99) -> 0 | AC99: =D99-(H99+I99+J99) -> 0
A100: 99 | B100: =LoanPool!L100 -> 477379.81 | C100: =LoanPool!M100 -> 1176800 | D100: =LoanPool!H100 -> 33997.048 | E100: =X99 -> 54978758 | F100: =Y99 -> 45000000 | G100: =Z99 -> 9136627.3 | H100: =MIN(D100,G100) -> 33997.048 | I100: =MIN(MAX(D100-H100,0),F100) -> 0 | J100: =MIN(MAX(D100-H100-I100,0),E100) -> 0 | K100: =MAX(E100-J100,0) -> 54978758 | L100: =MAX(F100-I100,0) -> 45000000 | M100: =MAX(G100-H100,0) -> 9102630.2 | N100: =K100*Inputs!B6/12 -> 263439.88 | O100: =MIN(B100,N100) -> 263439.88 | P100: =N100-O100 -> 0 | Q100: =L100*Inputs!B6/12 -> 215625 | R100: =MIN(MAX(B100-O100,0),Q100) -> 213939.93 | S100: =Q100-R100 -> 1685.0716 | T100: =MAX(B100-O100-R100,0) -> 0 | U100: =MIN(C100,K100) -> 1176800 | V100: =MIN(MAX(C100-U100,0),L100) -> 0 | W100: =MIN(MAX(C100-U100-V100,0),M100) -> 0 | X100: =MAX(K100-U100,0) -> 53801958 | Y100: =MAX(L100-V100,0) -> 45000000 | Z100: =MAX(M100-W100,0) -> 9102630.2 | AA100: =C100-(U100+V100+W100) -> 0 | AB100: =B100-(O100+R100+T100) -> 0 | AC100: =D100-(H100+I100+J100) -> 0
...

Sheet Scenarios
A1: Scenario | B1: CPR_Annual | C1: CDR_Annual | D1: Severity
A2: Base | B2: 0.08 | C2: 0.015 | D2: 0.25
A3: Mild_Stress | B3: 0.05 | C3: 0.03 | D3: 0.35
A4: Severe_Stress | B4: 0.03 | C4: 0.05 | D4: 0.45
A6: Active scenario output
A7: Scenario | B7: =Inputs!B14 -> Base
A8: Cumulative Loss | B8: =SUM(LoanPool!H2:H361) -> 8240256.2
A9: Final Class A Balance | B9: =Waterfall!X361 -> 0
A10: Final Class B Balance | B10: =Waterfall!Y361 -> 0
A11: Final Equity Balance | B11: =Waterfall!Z361 -> 1.2834789e-08
A12: First Month Class A = 0 | B12: =IFERROR(MATCH(TRUE,Waterfall!X2:X361<=0.01,0),"Not Paid") -> Not Paid

Sheet Checks
A1: Check | B1: Metric | C1: Status | D1: Target
A2: Principal allocation closes | B2: =MAX(MAX(Waterfall!AA2:AA361),-MIN(Waterfall!AA2:AA361)) -> 0 | C2: =IF(B2<=0.01,"PASS","FAIL") -> PASS | D2: <= 0.01
A3: Interest allocation closes | B3: =MAX(MAX(Waterfall!AB2:AB361),-MIN(Waterfall!AB2:AB361)) -> 0 | C3: =IF(B3<=0.01,"PASS","FAIL") -> PASS | D3: <= 0.01
A4: Loss allocation closes | B4: =MAX(MAX(Waterfall!AC2:AC361),-MIN(Waterfall!AC2:AC361)) -> 0 | C4: =IF(B4<=0.01,"PASS","FAIL") -> PASS | D4: <= 0.01
A5: No negative balances | B5: =MIN(LoanPool!J2:J361,Waterfall!X2:X361,Waterfall!Y2:Y361,Waterfall!Z2:Z361) -> 0 | C5: =IF(B5>=-0.01,"PASS","FAIL") -> PASS | D5: >= -0.01
A6: Scenario ordering (stress increases credit loss params) | B6: =IF(AND(Scenarios!B2>=Scenarios!B3,Scenarios!B3>=Scenarios!B4,Scenarios!C2<=Scenarios!C3,Scenarios!C3<=Scenarios!C4,Scenarios!D2<=Scenarios!D3,Scenarios!D3<=Scenarios!D4),1,0) -> 1 | C6: =IF(B6=1,"PASS","FAIL") -> PASS | D6: 1
A8: How to use
A9: 1) Choose scenario in Inputs!B12.
A10: 2) Recalculate workbook.
A11: 3) Review this tab and Scenarios tab outputs.

Sheet Scenarios_V2
A1: Scenario | B1: CPR_Annual | C1: Severity | D1: RollTo30_Annual | E1: DefaultFrom60_Annual | F1: Cure30_Monthly | G1: Roll30To60_Monthly | H1: Cure60_Monthly
A2: Base | B2: 0.08 | C2: 0.25 | D2: 0.04 | E2: 0.1 | F2: 0.35 | G2: 0.2 | H2: 0.12
A3: Mild_Stress | B3: 0.05 | C3: 0.35 | D3: 0.07 | E3: 0.18 | F3: 0.25 | G3: 0.28 | H3: 0.08
A4: Severe_Stress | B4: 0.03 | C4: 0.45 | D4: 0.1 | E4: 0.28 | F4: 0.18 | G4: 0.35 | H4: 0.05
A6: Active scenario output
A7: Scenario | B7: =Inputs!B14 -> Base
A8: Cumulative Loss (V2) | B8: =SUM(PoolStates_V2!Q2:Q361) -> 81618.467
A9: Max DQ Ratio (of initial) | B9: =MAX(PoolStates_V2!Z2:Z361) -> 0.013934426
A10: First Trigger Month | B10: =IFERROR(MATCH(TRUE,PoolStates_V2!B2:B361=1,0),"Not Triggered") -> Not Triggered
A11: Final Class A Balance | B11: =Waterfall_V2!AP361 -> 0
A12: Final Class B Balance | B12: =Waterfall_V2!AQ361 -> 0

Sheet PoolStates_V2
A1: Month | B1: Trigger_On | C1: Pool_Begin | D1: Current_Begin | E1: DQ30_Begin | F1: DQ60_Begin | G1: Remaining_Term | H1: Sched_Payment | I1: Interest | J1: Sched_Principal | K1: Prepay | L1: Roll_to_30 | M1: Cure30 | N1: Roll30_to_60 | O1: Cure60 | P1: Default | Q1: Loss | R1: Fee | S1: Interest_Available | T1: Principal_From_Pool | U1: Current_End | V1: DQ30_End | W1: DQ60_End | X1: Pool_End | Y1: Cum_Loss | Z1: DQ_Ratio_Init | AA1: Trigger_Event | AB1: Pool_Roll_Diff
A2: 1 | B2: =AA2 -> 0 | C2: =Inputs!B3 -> 300000000 | D2: =Inputs!B3*(1-Inputs!B25-Inputs!B26) -> 295500000 | E2: =Inputs!B3*Inputs!B25 -> 3000000 | F2: =Inputs!B3*Inputs!B26 -> 1500000 | G2: =MAX(Inputs!B7-A2+1,0) -> 300 | H2: =IF(AND(A2<=Inputs!B7,D2>0),-PMT(Inputs!B6/12,G2,D2),0) -> 1859009.4 | I2: =IF(AND(A2<=Inputs!B7,D2>0),D2*Inputs!B6/12,0) -> 1415937.5 | J2: =MAX(H2-I2,0) -> 443071.92 | K2: =MAX((D2-J2)*Inputs!B32,0) -> 23604554 | L2: =MAX((D2-J2-K2)*Inputs!B33,0) -> 921866.7 | M2: =MIN(E2*Inputs!B29,E2) -> 1050000 | N2: =MIN((E2-M2)*Inputs!B30,E2-M2) -> 390000 | O2: =MIN(F2*Inputs!B31,F2) -> 180000 | P2: =MIN((F2-O2)*Inputs!B34,F2-O2) -> 11538.926 | Q2: =P2*Inputs!B35 -> 2884.7316 | R2: =C2*Inputs!B8/12 -> 125000 | S2: =MAX(I2-R2,0) -> 1290937.5 | T2: =MAX(J2+K2+P2-Q2,0) -> 24056280 | U2: =MAX(D2-J2-K2-L2+M2+O2,0) -> 2.7176051e+08 | V2: =MAX(E2-M2-N2+L2,0) -> 2481866.7 | W2: =MAX(F2-O2-P2+N2,0) -> 1698461.1 | X2: =U2+V2+W2 -> 2.7594083e+08 | Y2: =Q2 -> 2884.7316 | Z2: =IF(Inputs!B3>0,(V2+W2)/Inputs!B3,0) -> 0.013934426 | AA2: =IF(OR(Y2/Inputs!B3>=Inputs!B23,Z2>=Inputs!B24),1,0) -> 0 | AB2: =MAX(C2-J2-K2-P2,0)-X2 -> 0
A3: 2 | B3: =MAX(B2,AA3) -> 0 | C3: =X2 -> 2.7594083e+08 | D3: =U2 -> 2.7176051e+08 | E3: =V2 -> 2481866.7 | F3: =W2 -> 1698461.1 | G3: =MAX(Inputs!B7-A3+1,0) -> 299 | H3: =IF(AND(A3<=Inputs!B7,D3>0),-PMT(Inputs!B6/12,G3,D3),0) -> 1712230.1 | I3: =IF(AND(A3<=Inputs!B7,D3>0),D3*Inputs!B6/12,0) -> 1302185.8 | J3: =MAX(H3-I3,0) -> 410044.3 | K3: =MAX((D3-J3)*Inputs!B32,0) -> 21708037 | L3: =MAX((D3-J3-K3)*Inputs!B33,0) -> 847798.96 | M3: =MIN(E3*Inputs!B29,E3) -> 868653.35 | N3: =MIN((E3-M3)*Inputs!B30,E3-M3) -> 322642.67 | O3: =MIN(F3*Inputs!B31,F3) -> 203815.33 | P3: =MIN((F3-O3)*Inputs!B34,F3-O3) -> 13065.612 | Q3: =P3*Inputs!B35 -> 3266.4029 | R3: =C3*Inputs!B8/12 -> 114975.35 | S3: =MAX(I3-R3,0) -> 1187210.4 | T3: =MAX(J3+K3+P3-Q3,0) -> 22127881 | U3: =MAX(D3-J3-K3-L3+M3+O3,0) -> 2.498671e+08 | V3: =MAX(E3-M3-N3+L3,0) -> 2138369.6 | W3: =MAX(F3-O3-P3+N3,0) -> 1804222.8 | X3: =U3+V3+W3 -> 2.5380969e+08 | Y3: =Y2+Q3 -> 6151.1345 | Z3: =IF(Inputs!B3>0,(V3+W3)/Inputs!B3,0) -> 0.013141975 | AA3: =IF(OR(Y3/Inputs!B3>=Inputs!B23,Z3>=Inputs!B24),1,0) -> 0 | AB3: =MAX(C3-J3-K3-P3,0)-X3 -> 0
A4: 3 | B4: =MAX(B3,AA4) -> 0 | C4: =X3 -> 2.5380969e+08 | D4: =U3 -> 2.498671e+08 | E4: =V3 -> 2138369.6 | F4: =W3 -> 1804222.8 | G4: =MAX(Inputs!B7-A4+1,0) -> 298 | H4: =IF(AND(A4<=Inputs!B7,D4>0),-PMT(Inputs!B6/12,G4,D4),0) -> 1576669.3 | I4: =IF(AND(A4<=Inputs!B7,D4>0),D4*Inputs!B6/12,0) -> 1197279.8 | J4: =MAX(H4-I4,0) -> 379389.5 | K4: =MAX((D4-J4)*Inputs!B32,0) -> 19959016 | L4: =MAX((D4-J4-K4)*Inputs!B33,0) -> 779491.64 | M4: =MIN(E4*Inputs!B29,E4) -> 748429.38 | N4: =MIN((E4-M4)*Inputs!B30,E4-M4) -> 277988.05 | O4: =MIN(F4*Inputs!B31,F4) -> 216506.74 | P4: =MIN((F4-O4)*Inputs!B34,F4-O4) -> 13879.196 | Q4: =P4*Inputs!B35 -> 3469.799 | R4: =C4*Inputs!B8/12 -> 105754.04 | S4: =MAX(I4-R4,0) -> 1091525.8 | T4: =MAX(J4+K4+P4-Q4,0) -> 20348815 | U4: =MAX(D4-J4-K4-L4+M4+O4,0) -> 2.2971413e+08 | V4: =MAX(E4-M4-N4+L4,0) -> 1891443.9 | W4: =MAX(F4-O4-P4+N4,0) -> 1851824.9 | X4: =U4+V4+W4 -> 2.334574e+08 | Y4: =Y3+Q4 -> 9620.9336 | Z4: =IF(Inputs!B3>0,(V4+W4)/Inputs!B3,0) -> 0.012477563 | AA4: =IF(OR(Y4/Inputs!B3>=Inputs!B23,Z4>=Inputs!B24),1,0) -> 0 | AB4: =MAX(C4-J4-K4-P4,0)-X4 -> 0
A5: 4 | B5: =MAX(B4,AA5) -> 0 | C5: =X4 -> 2.334574e+08 | D5: =U4 -> 2.2971413e+08 | E5: =V4 -> 1891443.9 | F5: =W4 -> 1851824.9 | G5: =MAX(Inputs!B7-A5+1,0) -> 297 | H5: =IF(AND(A5<=Inputs!B7,D5>0),-PMT(Inputs!B6/12,G5,D5),0) -> 1451707.7 | I5: =IF(AND(A5<=Inputs!B7,D5>0),D5*Inputs!B6/12,0) -> 1100713.6 | J5: =MAX(H5-I5,0) -> 350994.17 | K5: =MAX((D5-J5)*Inputs!B32,0) -> 18349051 | L5: =MAX((D5-J5-K5)*Inputs!B33,0) -> 716615.07 | M5: =MIN(E5*Inputs!B29,E5) -> 662005.35 | N5: =MIN((E5-M5)*Inputs!B30,E5-M5) -> 245887.7 | O5: =MIN(F5*Inputs!B31,F5) -> 222218.99 | P5: =MIN((F5-O5)*Inputs!B34,F5-O5) -> 14245.381 | Q5: =P5*Inputs!B35 -> 3561.3453 | R5: =C5*Inputs!B8/12 -> 97273.918 | S5: =MAX(I5-R5,0) -> 1003439.6 | T5: =MAX(J5+K5+P5-Q5,0) -> 18710729 | U5: =MAX(D5-J5-K5-L5+M5+O5,0) -> 2.111817e+08 | V5: =MAX(E5-M5-N5+L5,0) -> 1700165.9 | W5: =MAX(F5-O5-P5+N5,0) -> 1861248.3 | X5: =U5+V5+W5 -> 2.1474311e+08 | Y5: =Y4+Q5 -> 13182.279 | Z5: =IF(Inputs!B3>0,(V5+W5)/Inputs!B3,0) -> 0.01187138 | AA5: =IF(OR(Y5/Inputs!B3>=Inputs!B23,Z5>=Inputs!B24),1,0) -> 0 | AB5: =MAX(C5-J5-K5-P5,0)-X5 -> 0
A6: 5 | B6: =MAX(B5,AA6) -> 0 | C6: =X5 -> 2.1474311e+08 | D6: =U5 -> 2.111817e+08 | E6: =V5 -> 1700165.9 | F6: =W5 -> 1861248.3 | G6: =MAX(Inputs!B7-A6+1,0) -> 296 | H6: =IF(AND(A6<=Inputs!B7,D6>0),-PMT(Inputs!B6/12,G6,D6),0) -> 1336632 | I6: =IF(AND(A6<=Inputs!B7,D6>0),D6*Inputs!B6/12,0) -> 1011912.3 | J6: =MAX(H6-I6,0) -> 324719.65 | K6: =MAX((D6-J6)*Inputs!B32,0) -> 16868558 | L6: =MAX((D6-J6-K6)*Inputs!B33,0) -> 658794.99 | M6: =MIN(E6*Inputs!B29,E6) -> 595058.06 | N6: =MIN((E6-M6)*Inputs!B30,E6-M6) -> 221021.56 | O6: =MIN(F6*Inputs!B31,F6) -> 223349.79 | P6: =MIN((F6-O6)*Inputs!B34,F6-O6) -> 14317.871 | Q6: =P6*Inputs!B35 -> 3579.4678 | R6: =C6*Inputs!B8/12 -> 89476.297 | S6: =MAX(I6-R6,0) -> 922436.01 | T6: =MAX(J6+K6+P6-Q6,0) -> 17204016 | U6: =MAX(D6-J6-K6-L6+M6+O6,0) -> 1.9414803e+08 | V6: =MAX(E6-M6-N6+L6,0) -> 1542881.2 | W6: =MAX(F6-O6-P6+N6,0) -> 1844602.2 | X6: =U6+V6+W6 -> 1.9753552e+08 | Y6: =Y5+Q6 -> 16761.747 | Z6: =IF(Inputs!B3>0,(V6+W6)/Inputs!B3,0) -> 0.011291611 | AA6: =IF(OR(Y6/Inputs!B3>=Inputs!B23,Z6>=Inputs!B24),1,0) -> 0 | AB6: =MAX(C6-J6-K6-P6,0)-X6 -> 0
A7: 6 | B7: =MAX(B6,AA7) -> 0 | C7: =X6 -> 1.9753552e+08 | D7: =U6 -> 1.9414803e+08 | E7: =V6 -> 1542881.2 | F7: =W6 -> 1844602.2 | G7: =MAX(Inputs!B7-A7+1,0) -> 295 | H7: =IF(AND(A7<=Inputs!B7,D7>0),-PMT(Inputs!B6/12,G7,D7),0) -> 1230713.2 | I7: =IF(AND(A7<=Inputs!B7,D7>0),D7*Inputs!B6/12,0) -> 930292.66 | J7: =MAX(H7-I7,0) -> 300420.53 | K7: =MAX((D7-J7)*Inputs!B32,0) -> 15507809 | L7: =MAX((D7-J7-K7)*Inputs!B33,0) -> 605651.46 | M7: =MIN(E7*Inputs!B29,E7) -> 540008.44 | N7: =MIN((E7-M7)*Inputs!B30,E7-M7) -> 200574.56 | O7: =MIN(F7*Inputs!B31,F7) -> 221352.26 | P7: =MIN((F7-O7)*Inputs!B34,F7-O7) -> 14189.819 | Q7: =P7*Inputs!B35 -> 3547.4548 | R7: =C7*Inputs!B8/12 -> 82306.465 | S7: =MAX(I7-R7,0) -> 847986.19 | T7: =MAX(J7+K7+P7-Q7,0) -> 15818872 | U7: =MAX(D7-J7-K7-L7+M7+O7,0) -> 1.7849551e+08 | V7: =MAX(E7-M7-N7+L7,0) -> 1407949.7 | W7: =MAX(F7-O7-P7+N7,0) -> 1809634.6 | X7: =U7+V7+W7 -> 1.817131e+08 | Y7: =Y6+Q7 -> 20309.201 | Z7: =IF(Inputs!B3>0,(V7+W7)/Inputs!B3,0) -> 0.010725281 | AA7: =IF(OR(Y7/Inputs!B3>=Inputs!B23,Z7>=Inputs!B24),1,0) -> 0 | AB7: =MAX(C7-J7-K7-P7,0)-X7 -> 0
A8: 7 | B8: =MAX(B7,AA8) -> 0 | C8: =X7 -> 1.817131e+08 | D8: =U7 -> 1.7849551e+08 | E8: =V7 -> 1407949.7 | F8: =W7 -> 1809634.6 | G8: =MAX(Inputs!B7-A8+1,0) -> 294 | H8: =IF(AND(A8<=Inputs!B7,D8>0),-PMT(Inputs!B6/12,G8,D8),0) -> 1133244.7 | I8: =IF(AND(A8<=Inputs!B7,D8>0),D8*Inputs!B6/12,0) -> 855291 | J8: =MAX(H8-I8,0) -> 277953.72 | K8: =MAX((D8-J8)*Inputs!B32,0) -> 14257405 | L8: =MAX((D8-J8-K8)*Inputs!B33,0) -> 556817.41 | M8: =MIN(E8*Inputs!B29,E8) -> 492782.4 | N8: =MIN((E8-M8)*Inputs!B30,E8-M8) -> 183033.46 | O8: =MIN(F8*Inputs!B31,F8) -> 217156.16 | P8: =MIN((F8-O8)*Inputs!B34,F8-O8) -> 13920.827 | Q8: =P8*Inputs!B35 -> 3480.2068 | R8: =C8*Inputs!B8/12 -> 75713.79 | S8: =MAX(I8-R8,0) -> 779577.21 | T8: =MAX(J8+K8+P8-Q8,0) -> 14545799 | U8: =MAX(D8-J8-K8-L8+M8+O8,0) -> 1.6411328e+08 | V8: =MAX(E8-M8-N8+L8,0) -> 1288951.3 | W8: =MAX(F8-O8-P8+N8,0) -> 1761591.1 | X8: =U8+V8+W8 -> 1.6716382e+08 | Y8: =Y7+Q8 -> 23789.408 | Z8: =IF(Inputs!B3>0,(V8+W8)/Inputs!B3,0) -> 0.010168475 | AA8: =IF(OR(Y8/Inputs!B3>=Inputs!B23,Z8>=Inputs!B24),1,0) -> 0 | AB8: =MAX(C8-J8-K8-P8,0)-X8 -> 0
A9: 8 | B9: =MAX(B8,AA9) -> 0 | C9: =X8 -> 1.6716382e+08 | D9: =U8 -> 1.6411328e+08 | E9: =V8 -> 1288951.3 | F9: =W8 -> 1761591.1 | G9: =MAX(Inputs!B7-A9+1,0) -> 293 | H9: =IF(AND(A9<=Inputs!B7,D9>0),-PMT(Inputs!B6/12,G9,D9),0) -> 1043558.8 | I9: =IF(AND(A9<=Inputs!B7,D9>0),D9*Inputs!B6/12,0) -> 786376.11 | J9: =MAX(H9-I9,0) -> 257182.69 | K9: =MAX((D9-J9)*Inputs!B32,0) -> 13108487 | L9: =MAX((D9-J9-K9)*Inputs!B33,0) -> 511946.89 | M9: =MIN(E9*Inputs!B29,E9) -> 451132.94 | N9: =MIN((E9-M9)*Inputs!B30,E9-M9) -> 167563.66 | O9: =MIN(F9*Inputs!B31,F9) -> 211390.93 | P9: =MIN((F9-O9)*Inputs!B34,F9-O9) -> 13551.247 | Q9: =P9*Inputs!B35 -> 3387.8117 | R9: =C9*Inputs!B8/12 -> 69651.591 | S9: =MAX(I9-R9,0) -> 716724.52 | T9: =MAX(J9+K9+P9-Q9,0) -> 13375834 | U9: =MAX(D9-J9-K9-L9+M9+O9,0) -> 1.5089818e+08 | V9: =MAX(E9-M9-N9+L9,0) -> 1182201.5 | W9: =MAX(F9-O9-P9+N9,0) -> 1704212.6 | X9: =U9+V9+W9 -> 1.537846e+08 | Y9: =Y8+Q9 -> 27177.22 | Z9: =IF(Inputs!B3>0,(V9+W9)/Inputs!B3,0) -> 0.0096213805 | AA9: =IF(OR(Y9/Inputs!B3>=Inputs!B23,Z9>=Inputs!B24),1,0) -> 0 | AB9: =MAX(C9-J9-K9-P9,0)-X9 -> 0
A10: 9 | B10: =MAX(B9,AA10) -> 0 | C10: =X9 -> 1.537846e+08 | D10: =U9 -> 1.5089818e+08 | E10: =V9 -> 1182201.5 | F10: =W9 -> 1704212.6 | G10: =MAX(Inputs!B7-A10+1,0) -> 292 | H10: =IF(AND(A10<=Inputs!B7,D10>0),-PMT(Inputs!B6/12,G10,D10),0) -> 961033.08 | I10: =IF(AND(A10<=Inputs!B7,D10>0),D10*Inputs!B6/12,0) -> 723053.79 | J10: =MAX(H10-I10,0) -> 237979.29 | K10: =MAX((D10-J10)*Inputs!B32,0) -> 12052816 | L10: =MAX((D10-J10-K10)*Inputs!B33,0) -> 470718.06 | M10: =MIN(E10*Inputs!B29,E10) -> 413770.54 | N10: =MIN((E10-M10)*Inputs!B30,E10-M10) -> 153686.2 | O10: =MIN(F10*Inputs!B31,F10) -> 204505.51 | P10: =MIN((F10-O10)*Inputs!B34,F10-O10) -> 13109.856 | Q10: =P10*Inputs!B35 -> 3277.464 | R10: =C10*Inputs!B8/12 -> 64076.915 | S10: =MAX(I10-R10,0) -> 658976.87 | T10: =MAX(J10+K10+P10-Q10,0) -> 12300628 | U10: =MAX(D10-J10-K10-L10+M10+O10,0) -> 1.3875494e+08 | V10: =MAX(E10-M10-N10+L10,0) -> 1085462.9 | W10: =MAX(F10-O10-P10+N10,0) -> 1640283.4 | X10: =U10+V10+W10 -> 1.4148069e+08 | Y10: =Y9+Q10 -> 30454.684 | Z10: =IF(Inputs!B3>0,(V10+W10)/Inputs!B3,0) -> 0.009085821 | AA10: =IF(OR(Y10/Inputs!B3>=Inputs!B23,Z10>=Inputs!B24),1,0) -> 0 | AB10: =MAX(C10-J10-K10-P10,0)-X10 -> 0
A11: 10 | B11: =MAX(B10,AA11) -> 0 | C11: =X10 -> 1.4148069e+08 | D11: =U10 -> 1.3875494e+08 | E11: =V10 -> 1085462.9 | F11: =W10 -> 1640283.4 | G11: =MAX(Inputs!B7-A11+1,0) -> 291 | H11: =IF(AND(A11<=Inputs!B7,D11>0),-PMT(Inputs!B6/12,G11,D11),0) -> 885091.68 | I11: =IF(AND(A11<=Inputs!B7,D11>0),D11*Inputs!B6/12,0) -> 664867.44 | J11: =MAX(H11-I11,0) -> 220224.24 | K11: =MAX((D11-J11)*Inputs!B32,0) -> 11082778 | L11: =MAX((D11-J11-K11)*Inputs!B33,0) -> 432833.58 | M11: =MIN(E11*Inputs!B29,E11) -> 379912 | N11: =MIN((E11-M11)*Inputs!B30,E11-M11) -> 141110.17 | O11: =MIN(F11*Inputs!B31,F11) -> 196834.01 | P11: =MIN((F11-O11)*Inputs!B34,F11-O11) -> 12618.073 | Q11: =P11*Inputs!B35 -> 3154.5183 | R11: =C11*Inputs!B8/12 -> 58950.288 | S11: =MAX(I11-R11,0) -> 605917.16 | T11: =MAX(J11+K11+P11-Q11,0) -> 11312465 | U11: =MAX(D11-J11-K11-L11+M11+O11,0) -> 1.2759586e+08 | V11: =MAX(E11-M11-N11+L11,0) -> 997274.26 | W11: =MAX(F11-O11-P11+N11,0) -> 1571941.5 | X11: =U11+V11+W11 -> 1.3016507e+08 | Y11: =Y10+Q11 -> 33609.202 | Z11: =IF(Inputs!B3>0,(V11+W11)/Inputs!B3,0) -> 0.0085640526 | AA11: =IF(OR(Y11/Inputs!B3>=Inputs!B23,Z11>=Inputs!B24),1,0) -> 0 | AB11: =MAX(C11-J11-K11-P11,0)-X11 -> 0
A12: 11 | B12: =MAX(B11,AA12) -> 0 | C12: =X11 -> 1.3016507e+08 | D12: =U11 -> 1.2759586e+08 | E12: =V11 -> 997274.26 | F12: =W11 -> 1571941.5 | G12: =MAX(Inputs!B7-A12+1,0) -> 290 | H12: =IF(AND(A12<=Inputs!B7,D12>0),-PMT(Inputs!B6/12,G12,D12),0) -> 815203.8 | I12: =IF(AND(A12<=Inputs!B7,D12>0),D12*Inputs!B6/12,0) -> 611396.81 | J12: =MAX(H12-I12,0) -> 203806.99 | K12: =MAX((D12-J12)*Inputs!B32,0) -> 10191364 | L12: =MAX((D12-J12-K12)*Inputs!B33,0) -> 398019.76 | M12: =MIN(E12*Inputs!B29,E12) -> 349045.99 | N12: =MIN((E12-M12)*Inputs!B30,E12-M12) -> 129645.65 | O12: =MIN(F12*Inputs!B31,F12) -> 188632.98 | P12: =MIN((F12-O12)*Inputs!B34,F12-O12) -> 12092.345 | Q12: =P12*Inputs!B35 -> 3023.0863 | R12: =C12*Inputs!B8/12 -> 54235.446 | S12: =MAX(I12-R12,0) -> 557161.36 | T12: =MAX(J12+K12+P12-Q12,0) -> 10404240 | U12: =MAX(D12-J12-K12-L12+M12+O12,0) -> 1.1734034e+08 | V12: =MAX(E12-M12-N12+L12,0) -> 916602.38 | W12: =MAX(F12-O12-P12+N12,0) -> 1500861.8 | X12: =U12+V12+W12 -> 1.1975781e+08 | Y12: =Y11+Q12 -> 36632.289 | Z12: =IF(Inputs!B3>0,(V12+W12)/Inputs!B3,0) -> 0.0080582141 | AA12: =IF(OR(Y12/Inputs!B3>=Inputs!B23,Z12>=Inputs!B24),1,0) -> 0 | AB12: =MAX(C12-J12-K12-P12,0)-X12 -> 0
A13: 12 | B13: =MAX(B12,AA13) -> 0 | C13: =X12 -> 1.1975781e+08 | D13: =U12 -> 1.1734034e+08 | E13: =V12 -> 916602.38 | F13: =W12 -> 1500861.8 | G13: =MAX(Inputs!B7-A13+1,0) -> 289 | H13: =IF(AND(A13<=Inputs!B7,D13>0),-PMT(Inputs!B6/12,G13,D13),0) -> 750881.2 | I13: =IF(AND(A13<=Inputs!B7,D13>0),D13*Inputs!B6/12,0) -> 562255.81 | J13: =MAX(H13-I13,0) -> 188625.38 | K13: =MAX((D13-J13)*Inputs!B32,0) -> 9372137.5 | L13: =MAX((D13-J13-K13)*Inputs!B33,0) -> 366025.19 | M13: =MIN(E13*Inputs!B29,E13) -> 320810.83 | N13: =MIN((E13-M13)*Inputs!B30,E13-M13) -> 119158.31 | O13: =MIN(F13*Inputs!B31,F13) -> 180103.42 | P13: =MIN((F13-O13)*Inputs!B34,F13-O13) -> 11545.556 | Q13: =P13*Inputs!B35 -> 2886.3891 | R13: =C13*Inputs!B8/12 -> 49899.087 | S13: =MAX(I13-R13,0) -> 512356.73 | T13: =MAX(J13+K13+P13-Q13,0) -> 9569422 | U13: =MAX(D13-J13-K13-L13+M13+O13,0) -> 1.0791447e+08 | V13: =MAX(E13-M13-N13+L13,0) -> 842658.43 | W13: =MAX(F13-O13-P13+N13,0) -> 1428371.2 | X13: =U13+V13+W13 -> 1.101855e+08 | Y13: =Y12+Q13 -> 39518.678 | Z13: =IF(Inputs!B3>0,(V13+W13)/Inputs!B3,0) -> 0.0075700987 | AA13: =IF(OR(Y13/Inputs!B3>=Inputs!B23,Z13>=Inputs!B24),1,0) -> 0 | AB13: =MAX(C13-J13-K13-P13,0)-X13 -> 0
A14: 13 | B14: =MAX(B13,AA14) -> 0 | C14: =X13 -> 1.101855e+08 | D14: =U13 -> 1.0791447e+08 | E14: =V13 -> 842658.43 | F14: =W13 -> 1428371.2 | G14: =MAX(Inputs!B7-A14+1,0) -> 288 | H14: =IF(AND(A14<=Inputs!B7,D14>0),-PMT(Inputs!B6/12,G14,D14),0) -> 691675.27 | I14: =IF(AND(A14<=Inputs!B7,D14>0),D14*Inputs!B6/12,0) -> 517090.17 | J14: =MAX(H14-I14,0) -> 174585.1 | K14: =MAX((D14-J14)*Inputs!B32,0) -> 8619190.8 | L14: =MAX((D14-J14-K14)*Inputs!B33,0) -> 336619.15 | M14: =MIN(E14*Inputs!B29,E14) -> 294930.45 | N14: =MIN((E14-M14)*Inputs!B30,E14-M14) -> 109545.6 | O14: =MIN(F14*Inputs!B31,F14) -> 171404.54 | P14: =MIN((F14-O14)*Inputs!B34,F14-O14) -> 10987.913 | Q14: =P14*Inputs!B35 -> 2746.9783 | R14: =C14*Inputs!B8/12 -> 45910.625 | S14: =MAX(I14-R14,0) -> 471179.54 | T14: =MAX(J14+K14+P14-Q14,0) -> 8802016.8 | U14: =MAX(D14-J14-K14-L14+M14+O14,0) -> 99250410 | V14: =MAX(E14-M14-N14+L14,0) -> 774801.53 | W14: =MAX(F14-O14-P14+N14,0) -> 1355524.3 | X14: =U14+V14+W14 -> 1.0138074e+08 | Y14: =Y13+Q14 -> 42265.656 | Z14: =IF(Inputs!B3>0,(V14+W14)/Inputs!B3,0) -> 0.0071010862 | AA14: =IF(OR(Y14/Inputs!B3>=Inputs!B23,Z14>=Inputs!B24),1,0) -> 0 | AB14: =MAX(C14-J14-K14-P14,0)-X14 -> 0
A15: 14 | B15: =MAX(B14,AA15) -> 0 | C15: =X14 -> 1.0138074e+08 | D15: =U14 -> 99250410 | E15: =V14 -> 774801.53 | F15: =W14 -> 1355524.3 | G15: =MAX(Inputs!B7-A15+1,0) -> 287 | H15: =IF(AND(A15<=Inputs!B7,D15>0),-PMT(Inputs!B6/12,G15,D15),0) -> 637174.01 | I15: =IF(AND(A15<=Inputs!B7,D15>0),D15*Inputs!B6/12,0) -> 475574.88 | J15: =MAX(H15-I15,0) -> 161599.12 | K15: =MAX((D15-J15)*Inputs!B32,0) -> 7927104.9 | L15: =MAX((D15-J15-K15)*Inputs!B33,0) -> 309590 | M15: =MIN(E15*Inputs!B29,E15) -> 271180.54 | N15: =MIN((E15-M15)*Inputs!B30,E15-M15) -> 100724.2 | O15: =MIN(F15*Inputs!B31,F15) -> 162662.92 | P15: =MIN((F15-O15)*Inputs!B34,F15-O15) -> 10427.53 | Q15: =P15*Inputs!B35 -> 2606.8826 | R15: =C15*Inputs!B8/12 -> 42241.973 | S15: =MAX(I15-R15,0) -> 433332.91 | T15: =MAX(J15+K15+P15-Q15,0) -> 8096524.6 | U15: =MAX(D15-J15-K15-L15+M15+O15,0) -> 91285959 | V15: =MAX(E15-M15-N15+L15,0) -> 712486.8 | W15: =MAX(F15-O15-P15+N15,0) -> 1283158.1 | X15: =U15+V15+W15 -> 93281604 | Y15: =Y14+Q15 -> 44872.539 | Z15: =IF(Inputs!B3>0,(V15+W15)/Inputs!B3,0) -> 0.0066521496 | AA15: =IF(OR(Y15/Inputs!B3>=Inputs!B23,Z15>=Inputs!B24),1,0) -> 0 | AB15: =MAX(C15-J15-K15-P15,0)-X15 -> 0
A16: 15 | B16: =MAX(B15,AA16) -> 0 | C16: =X15 -> 93281604 | D16: =U15 -> 91285959 | E16: =V15 -> 712486.8 | F16: =W15 -> 1283158.1 | G16: =MAX(Inputs!B7-A16+1,0) -> 286 | H16: =IF(AND(A16<=Inputs!B7,D16>0),-PMT(Inputs!B6/12,G16,D16),0) -> 586999.08 | I16: =IF(AND(A16<=Inputs!B7,D16>0),D16*Inputs!B6/12,0) -> 437411.89 | J16: =MAX(H16-I16,0) -> 149587.19 | K16: =MAX((D16-J16)*Inputs!B32,0) -> 7290909.8 | L16: =MAX((D16-J16-K16)*Inputs!B33,0) -> 284743.65 | M16: =MIN(E16*Inputs!B29,E16) -> 249370.38 | N16: =MIN((E16-M16)*Inputs!B30,E16-M16) -> 92623.284 | O16: =MIN(F16*Inputs!B31,F16) -> 153978.97 | P16: =MIN((F16-O16)*Inputs!B34,F16-O16) -> 9870.8444 | Q16: =P16*Inputs!B35 -> 2467.7111 | R16: =C16*Inputs!B8/12 -> 38867.335 | S16: =MAX(I16-R16,0) -> 398544.55 | T16: =MAX(J16+K16+P16-Q16,0) -> 7447900.1 | U16: =MAX(D16-J16-K16-L16+M16+O16,0) -> 83964068 | V16: =MAX(E16-M16-N16+L16,0) -> 655236.79 | W16: =MAX(F16-O16-P16+N16,0) -> 1211931.5 | X16: =U16+V16+W16 -> 85831236 | Y16: =Y15+Q16 -> 47340.25 | Z16: =IF(Inputs!B3>0,(V16+W16)/Inputs!B3,0) -> 0.0062238944 | AA16: =IF(OR(Y16/Inputs!B3>=Inputs!B23,Z16>=Inputs!B24),1,0) -> 0 | AB16: =MAX(C16-J16-K16-P16,0)-X16 -> 0
A17: 16 | B17: =MAX(B16,AA17) -> 0 | C17: =X16 -> 85831236 | D17: =U16 -> 83964068 | E17: =V16 -> 655236.79 | F17: =W16 -> 1211931.5 | G17: =MAX(Inputs!B7-A17+1,0) -> 285 | H17: =IF(AND(A17<=Inputs!B7,D17>0),-PMT(Inputs!B6/12,G17,D17),0) -> 540803.08 | I17: =IF(AND(A17<=Inputs!B7,D17>0),D17*Inputs!B6/12,0) -> 402327.83 | J17: =MAX(H17-I17,0) -> 138475.25 | K17: =MAX((D17-J17)*Inputs!B32,0) -> 6706047.4 | L17: =MAX((D17-J17-K17)*Inputs!B33,0) -> 261902.08 | M17: =MIN(E17*Inputs!B29,E17) -> 229332.88 | N17: =MIN((E17-M17)*Inputs!B30,E17-M17) -> 85180.782 | O17: =MIN(F17*Inputs!B31,F17) -> 145431.78 | P17: =MIN((F17-O17)*Inputs!B34,F17-O17) -> 9322.9259 | Q17: =P17*Inputs!B35 -> 2330.7315 | R17: =C17*Inputs!B8/12 -> 35763.015 | S17: =MAX(I17-R17,0) -> 366564.81 | T17: =MAX(J17+K17+P17-Q17,0) -> 6851514.9 | U17: =MAX(D17-J17-K17-L17+M17+O17,0) -> 77232408 | V17: =MAX(E17-M17-N17+L17,0) -> 602625.21 | W17: =MAX(F17-O17-P17+N17,0) -> 1142357.6 | X17: =U17+V17+W17 -> 78977391 | Y17: =Y16+Q17 -> 49670.981 | Z17: =IF(Inputs!B3>0,(V17+W17)/Inputs!B3,0) -> 0.0058166094 | AA17: =IF(OR(Y17/Inputs!B3>=Inputs!B23,Z17>=Inputs!B24),1,0) -> 0 | AB17: =MAX(C17-J17-K17-P17,0)-X17 -> 0
A18: 17 | B18: =MAX(B17,AA18) -> 0 | C18: =X17 -> 78977391 | D18: =U17 -> 77232408 | E18: =V17 -> 602625.21 | F18: =W17 -> 1142357.6 | G18: =MAX(Inputs!B7-A18+1,0) -> 284 | H18: =IF(AND(A18<=Inputs!B7,D18>0),-PMT(Inputs!B6/12,G18,D18),0) -> 498266.97 | I18: =IF(AND(A18<=Inputs!B7,D18>0),D18*Inputs!B6/12,0) -> 370071.95 | J18: =MAX(H18-I18,0) -> 128195.01 | K18: =MAX((D18-J18)*Inputs!B32,0) -> 6168337 | L18: =MAX((D18-J18-K18)*Inputs!B33,0) -> 240902.01 | M18: =MIN(E18*Inputs!B29,E18) -> 210918.82 | N18: =MIN((E18-M18)*Inputs!B30,E18-M18) -> 78341.277 | O18: =MIN(F18*Inputs!B31,F18) -> 137082.91 | P18: =MIN((F18-O18)*Inputs!B34,F18-O18) -> 8787.7203 | Q18: =P18*Inputs!B35 -> 2196.9301 | R18: =C18*Inputs!B8/12 -> 32907.246 | S18: =MAX(I18-R18,0) -> 337164.71 | T18: =MAX(J18+K18+P18-Q18,0) -> 6303122.8 | U18: =MAX(D18-J18-K18-L18+M18+O18,0) -> 71042976 | V18: =MAX(E18-M18-N18+L18,0) -> 554267.12 | W18: =MAX(F18-O18-P18+N18,0) -> 1074828.3 | X18: =U18+V18+W18 -> 72672071 | Y18: =Y17+Q18 -> 51867.911 | Z18: =IF(Inputs!B3>0,(V18+W18)/Inputs!B3,0) -> 0.0054303179 | AA18: =IF(OR(Y18/Inputs!B3>=Inputs!B23,Z18>=Inputs!B24),1,0) -> 0 | AB18: =MAX(C18-J18-K18-P18,0)-X18 -> 0
A19: 18 | B19: =MAX(B18,AA19) -> 0 | C19: =X18 -> 72672071 | D19: =U18 -> 71042976 | E19: =V18 -> 554267.12 | F19: =W18 -> 1074828.3 | G19: =MAX(Inputs!B7-A19+1,0) -> 283 | H19: =IF(AND(A19<=Inputs!B7,D19>0),-PMT(Inputs!B6/12,G19,D19),0) -> 459097.71 | I19: =IF(AND(A19<=Inputs!B7,D19>0),D19*Inputs!B6/12,0) -> 340414.26 | J19: =MAX(H19-I19,0) -> 118683.46 | K19: =MAX((D19-J19)*Inputs!B32,0) -> 5673943.4 | L19: =MAX((D19-J19-K19)*Inputs!B33,0) -> 221593.66 | M19: =MIN(E19*Inputs!B29,E19) -> 193993.49 | N19: =MIN((E19-M19)*Inputs!B30,E19-M19) -> 72054.725 | O19: =MIN(F19*Inputs!B31,F19) -> 128979.39 | P19: =MIN((F19-O19)*Inputs!B34,F19-O19) -> 8268.2428 | Q19: =P19*Inputs!B35 -> 2067.0607 | R19: =C19*Inputs!B8/12 -> 30280.03 | S19: =MAX(I19-R19,0) -> 310134.23 | T19: =MAX(J19+K19+P19-Q19,0) -> 5798828 | U19: =MAX(D19-J19-K19-L19+M19+O19,0) -> 65351728 | V19: =MAX(E19-M19-N19+L19,0) -> 509812.56 | W19: =MAX(F19-O19-P19+N19,0) -> 1009635.3 | X19: =U19+V19+W19 -> 66871176 | Y19: =Y18+Q19 -> 53934.972 | Z19: =IF(Inputs!B3>0,(V19+W19)/Inputs!B3,0) -> 0.0050648263 | AA19: =IF(OR(Y19/Inputs!B3>=Inputs!B23,Z19>=Inputs!B24),1,0) -> 0 | AB19: =MAX(C19-J19-K19-P19,0)-X19 -> 0
A20: 19 | B20: =MAX(B19,AA20) -> 0 | C20: =X19 -> 66871176 | D20: =U19 -> 65351728 | E20: =V19 -> 509812.56 | F20: =W19 -> 1009635.3 | G20: =MAX(Inputs!B7-A20+1,0) -> 282 | H20: =IF(AND(A20<=Inputs!B7,D20>0),-PMT(Inputs!B6/12,G20,D20),0) -> 423026.13 | I20: =IF(AND(A20<=Inputs!B7,D20>0),D20*Inputs!B6/12,0) -> 313143.7 | J20: =MAX(H20-I20,0) -> 109882.43 | K20: =MAX((D20-J20)*Inputs!B32,0) -> 5219347.6 | L20: =MAX((D20-J20-K20)*Inputs!B33,0) -> 203839.6 | M20: =MIN(E20*Inputs!B29,E20) -> 178434.39 | N20: =MIN((E20-M20)*Inputs!B30,E20-M20) -> 66275.632 | O20: =MIN(F20*Inputs!B31,F20) -> 121156.24 | P20: =MIN((F20-O20)*Inputs!B34,F20-O20) -> 7766.7387 | Q20: =P20*Inputs!B35 -> 1941.6847 | R20: =C20*Inputs!B8/12 -> 27862.99 | S20: =MAX(I20-R20,0) -> 285280.71 | T20: =MAX(J20+K20+P20-Q20,0) -> 5335055.1 | U20: =MAX(D20-J20-K20-L20+M20+O20,0) -> 60118249 | V20: =MAX(E20-M20-N20+L20,0) -> 468942.13 | W20: =MAX(F20-O20-P20+N20,0) -> 946988 | X20: =U20+V20+W20 -> 61534179 | Y20: =Y19+Q20 -> 55876.657 | Z20: =IF(Inputs!B3>0,(V20+W20)/Inputs!B3,0) -> 0.0047197671 | AA20: =IF(OR(Y20/Inputs!B3>=Inputs!B23,Z20>=Inputs!B24),1,0) -> 0 | AB20: =MAX(C20-J20-K20-P20,0)-X20 -> 0
A21: 20 | B21: =MAX(B20,AA21) -> 0 | C21: =X20 -> 61534179 | D21: =U20 -> 60118249 | E21: =V20 -> 468942.13 | F21: =W20 -> 946988 | G21: =MAX(Inputs!B7-A21+1,0) -> 281 | H21: =IF(AND(A21<=Inputs!B7,D21>0),-PMT(Inputs!B6/12,G21,D21),0) -> 389804.89 | I21: =IF(AND(A21<=Inputs!B7,D21>0),D21*Inputs!B6/12,0) -> 288066.61 | J21: =MAX(H21-I21,0) -> 101738.28 | K21: =MAX((D21-J21)*Inputs!B32,0) -> 4801320.9 | L21: =MAX((D21-J21-K21)*Inputs!B33,0) -> 187513.72 | M21: =MIN(E21*Inputs!B29,E21) -> 164129.74 | N21: =MIN((E21-M21)*Inputs!B30,E21-M21) -> 60962.476 | O21: =MIN(F21*Inputs!B31,F21) -> 113638.56 | P21: =MIN((F21-O21)*Inputs!B34,F21-O21) -> 7284.8166 | Q21: =P21*Inputs!B35 -> 1821.2041 | R21: =C21*Inputs!B8/12 -> 25639.241 | S21: =MAX(I21-R21,0) -> 262427.37 | T21: =MAX(J21+K21+P21-Q21,0) -> 4908522.7 | U21: =MAX(D21-J21-K21-L21+M21+O21,0) -> 55305444 | V21: =MAX(E21-M21-N21+L21,0) -> 431363.63 | W21: =MAX(F21-O21-P21+N21,0) -> 887027.1 | X21: =U21+V21+W21 -> 56623835 | Y21: =Y20+Q21 -> 57697.861 | Z21: =IF(Inputs!B3>0,(V21+W21)/Inputs!B3,0) -> 0.0043946358 | AA21: =IF(OR(Y21/Inputs!B3>=Inputs!B23,Z21>=Inputs!B24),1,0) -> 0 | AB21: =MAX(C21-J21-K21-P21,0)-X21 -> 0
A22: 21 | B22: =MAX(B21,AA22) -> 0 | C22: =X21 -> 56623835 | D22: =U21 -> 55305444 | E22: =V21 -> 431363.63 | F22: =W21 -> 887027.1 | G22: =MAX(Inputs!B7-A22+1,0) -> 280 | H22: =IF(AND(A22<=Inputs!B7,D22>0),-PMT(Inputs!B6/12,G22,D22),0) -> 359206.7 | I22: =IF(AND(A22<=Inputs!B7,D22>0),D22*Inputs!B6/12,0) -> 265005.25 | J22: =MAX(H22-I22,0) -> 94201.442 | K22: =MAX((D22-J22)*Inputs!B32,0) -> 4416899.4 | L22: =MAX((D22-J22-K22)*Inputs!B33,0) -> 172500.29 | M22: =MIN(E22*Inputs!B29,E22) -> 150977.27 | N22: =MIN((E22-M22)*Inputs!B30,E22-M22) -> 56077.272 | O22: =MIN(F22*Inputs!B31,F22) -> 106443.25 | P22: =MIN((F22-O22)*Inputs!B34,F22-O22) -> 6823.5603 | Q22: =P22*Inputs!B35 -> 1705.8901 | R22: =C22*Inputs!B8/12 -> 23593.265 | S22: =MAX(I22-R22,0) -> 241411.99 | T22: =MAX(J22+K22+P22-Q22,0) -> 4516218.5 | U22: =MAX(D22-J22-K22-L22+M22+O22,0) -> 50879264 | V22: =MAX(E22-M22-N22+L22,0) -> 396809.38 | W22: =MAX(F22-O22-P22+N22,0) -> 829837.56 | X22: =U22+V22+W22 -> 52105911 | Y22: =Y21+Q22 -> 59403.751 | Z22: =IF(Inputs!B3>0,(V22+W22)/Inputs!B3,0) -> 0.0040888231 | AA22: =IF(OR(Y22/Inputs!B3>=Inputs!B23,Z22>=Inputs!B24),1,0) -> 0 | AB22: =MAX(C22-J22-K22-P22,0)-X22 -> 0
A23: 22 | B23: =MAX(B22,AA23) -> 0 | C23: =X22 -> 52105911 | D23: =U22 -> 50879264 | E23: =V22 -> 396809.38 | F23: =W22 -> 829837.56 | G23: =MAX(Inputs!B7-A23+1,0) -> 279 | H23: =IF(AND(A23<=Inputs!B7,D23>0),-PMT(Inputs!B6/12,G23,D23),0) -> 331022.66 | I23: =IF(AND(A23<=Inputs!B7,D23>0),D23*Inputs!B6/12,0) -> 243796.47 | J23: =MAX(H23-I23,0) -> 87226.183 | K23: =MAX((D23-J23)*Inputs!B32,0) -> 4063363 | L23: =MAX((D23-J23-K23)*Inputs!B33,0) -> 158693.06 | M23: =MIN(E23*Inputs!B29,E23) -> 138883.28 | N23: =MIN((E23-M23)*Inputs!B30,E23-M23) -> 51585.219 | O23: =MIN(F23*Inputs!B31,F23) -> 99580.507 | P23: =MIN((F23-O23)*Inputs!B34,F23-O23) -> 6383.623 | Q23: =P23*Inputs!B35 -> 1595.9058 | R23: =C23*Inputs!B8/12 -> 21710.796 | S23: =MAX(I23-R23,0) -> 222085.68 | T23: =MAX(J23+K23+P23-Q23,0) -> 4155376.9 | U23: =MAX(D23-J23-K23-L23+M23+O23,0) -> 46808445 | V23: =MAX(E23-M23-N23+L23,0) -> 365033.94 | W23: =MAX(F23-O23-P23+N23,0) -> 775458.65 | X23: =U23+V23+W23 -> 47948938 | Y23: =Y22+Q23 -> 60999.657 | Z23: =IF(Inputs!B3>0,(V23+W23)/Inputs!B3,0) -> 0.003801642 | AA23: =IF(OR(Y23/Inputs!B3>=Inputs!B23,Z23>=Inputs!B24),1,0) -> 0 | AB23: =MAX(C23-J23-K23-P23,0)-X23 -> 0
A24: 23 | B24: =MAX(B23,AA24) -> 0 | C24: =X23 -> 47948938 | D24: =U23 -> 46808445 | E24: =V23 -> 365033.94 | F24: =W23 -> 775458.65 | G24: =MAX(Inputs!B7-A24+1,0) -> 278 | H24: =IF(AND(A24<=Inputs!B7,D24>0),-PMT(Inputs!B6/12,G24,D24),0) -> 305060.73 | I24: =IF(AND(A24<=Inputs!B7,D24>0),D24*Inputs!B6/12,0) -> 224290.47 | J24: =MAX(H24-I24,0) -> 80770.259 | K24: =MAX((D24-J24)*Inputs!B32,0) -> 3738214 | L24: =MAX((D24-J24-K24)*Inputs!B33,0) -> 145994.5 | M24: =MIN(E24*Inputs!B29,E24) -> 127761.88 | N24: =MIN((E24-M24)*Inputs!B30,E24-M24) -> 47454.412 | O24: =MIN(F24*Inputs!B31,F24) -> 93055.038 | P24: =MIN((F24-O24)*Inputs!B34,F24-O24) -> 5965.3069 | Q24: =P24*Inputs!B35 -> 1491.3267 | R24: =C24*Inputs!B8/12 -> 19978.724 | S24: =MAX(I24-R24,0) -> 204311.74 | T24: =MAX(J24+K24+P24-Q24,0) -> 3823458.2 | U24: =MAX(D24-J24-K24-L24+M24+O24,0) -> 43064283 | V24: =MAX(E24-M24-N24+L24,0) -> 335812.15 | W24: =MAX(F24-O24-P24+N24,0) -> 723892.71 | X24: =U24+V24+W24 -> 44123988 | Y24: =Y23+Q24 -> 62490.983 | Z24: =IF(Inputs!B3>0,(V24+W24)/Inputs!B3,0) -> 0.0035323495 | AA24: =IF(OR(Y24/Inputs!B3>=Inputs!B23,Z24>=Inputs!B24),1,0) -> 0 | AB24: =MAX(C24-J24-K24-P24,0)-X24 -> 0
A25: 24 | B25: =MAX(B24,AA25) -> 0 | C25: =X24 -> 44123988 | D25: =U24 -> 43064283 | E25: =V24 -> 335812.15 | F25: =W24 -> 723892.71 | G25: =MAX(Inputs!B7-A25+1,0) -> 277 | H25: =IF(AND(A25<=Inputs!B7,D25>0),-PMT(Inputs!B6/12,G25,D25),0) -> 281144.34 | I25: =IF(AND(A25<=Inputs!B7,D25>0),D25*Inputs!B6/12,0) -> 206349.69 | J25: =MAX(H25-I25,0) -> 74794.653 | K25: =MAX((D25-J25)*Inputs!B32,0) -> 3439159.1 | L25: =MAX((D25-J25-K25)*Inputs!B33,0) -> 134315.02 | M25: =MIN(E25*Inputs!B29,E25) -> 117534.25 | N25: =MIN((E25-M25)*Inputs!B30,E25-M25) -> 43655.579 | O25: =MIN(F25*Inputs!B31,F25) -> 86867.126 | P25: =MIN((F25-O25)*Inputs!B34,F25-O25) -> 5568.6299 | Q25: =P25*Inputs!B35 -> 1392.1575 | R25: =C25*Inputs!B8/12 -> 18384.995 | S25: =MAX(I25-R25,0) -> 187964.7 | T25: =MAX(J25+K25+P25-Q25,0) -> 3518130.2 | U25: =MAX(D25-J25-K25-L25+M25+O25,0) -> 39620416 | V25: =MAX(E25-M25-N25+L25,0) -> 308937.34 | W25: =MAX(F25-O25-P25+N25,0) -> 675112.54 | X25: =U25+V25+W25 -> 40604466 | Y25: =Y24+Q25 -> 63883.141 | Z25: =IF(Inputs!B3>0,(V25+W25)/Inputs!B3,0) -> 0.0032801663 | AA25: =IF(OR(Y25/Inputs!B3>=Inputs!B23,Z25>=Inputs!B24),1,0) -> 0 | AB25: =MAX(C25-J25-K25-P25,0)-X25 -> 0
A26: 25 | B26: =MAX(B25,AA26) -> 0 | C26: =X25 -> 40604466 | D26: =U25 -> 39620416 | E26: =V25 -> 308937.34 | F26: =W25 -> 675112.54 | G26: =MAX(Inputs!B7-A26+1,0) -> 276 | H26: =IF(AND(A26<=Inputs!B7,D26>0),-PMT(Inputs!B6/12,G26,D26),0) -> 259111.15 | I26: =IF(AND(A26<=Inputs!B7,D26>0),D26*Inputs!B6/12,0) -> 189847.83 | J26: =MAX(H26-I26,0) -> 69263.324 | K26: =MAX((D26-J26)*Inputs!B32,0) -> 3164092.2 | L26: =MAX((D26-J26-K26)*Inputs!B33,0) -> 123572.39 | M26: =MIN(E26*Inputs!B29,E26) -> 108128.07 | N26: =MIN((E26-M26)*Inputs!B30,E26-M26) -> 40161.854 | O26: =MIN(F26*Inputs!B31,F26) -> 81013.505 | P26: =MIN((F26-O26)*Inputs!B34,F26-O26) -> 5193.3826 | Q26: =P26*Inputs!B35 -> 1298.3457 | R26: =C26*Inputs!B8/12 -> 16918.527 | S26: =MAX(I26-R26,0) -> 172929.3 | T26: =MAX(J26+K26+P26-Q26,0) -> 3237250.6 | U26: =MAX(D26-J26-K26-L26+M26+O26,0) -> 36452630 | V26: =MAX(E26-M26-N26+L26,0) -> 284219.81 | W26: =MAX(F26-O26-P26+N26,0) -> 629067.51 | X26: =U26+V26+W26 -> 37365917 | Y26: =Y25+Q26 -> 65181.486 | Z26: =IF(Inputs!B3>0,(V26+W26)/Inputs!B3,0) -> 0.0030442911 | AA26: =IF(OR(Y26/Inputs!B3>=Inputs!B23,Z26>=Inputs!B24),1,0) -> 0 | AB26: =MAX(C26-J26-K26-P26,0)-X26 -> 0
A27: 26 | B27: =MAX(B26,AA27) -> 0 | C27: =X26 -> 37365917 | D27: =U26 -> 36452630 | E27: =V26 -> 284219.81 | F27: =W26 -> 629067.51 | G27: =MAX(Inputs!B7-A27+1,0) -> 275 | H27: =IF(AND(A27<=Inputs!B7,D27>0),-PMT(Inputs!B6/12,G27,D27),0) -> 238811.82 | I27: =IF(AND(A27<=Inputs!B7,D27>0),D27*Inputs!B6/12,0) -> 174668.85 | J27: =MAX(H27-I27,0) -> 64142.971 | K27: =MAX((D27-J27)*Inputs!B32,0) -> 2911078.9 | L27: =MAX((D27-J27-K27)*Inputs!B33,0) -> 113691.06 | M27: =MIN(E27*Inputs!B29,E27) -> 99476.933 | N27: =MIN((E27-M27)*Inputs!B30,E27-M27) -> 36948.575 | O27: =MIN(F27*Inputs!B31,F27) -> 75488.101 | P27: =MIN((F27-O27)*Inputs!B34,F27-O27) -> 4839.1758 | Q27: =P27*Inputs!B35 -> 1209.7939 | R27: =C27*Inputs!B8/12 -> 15569.132 | S27: =MAX(I27-R27,0) -> 159099.72 | T27: =MAX(J27+K27+P27-Q27,0) -> 2978851.3 | U27: =MAX(D27-J27-K27-L27+M27+O27,0) -> 33538682 | V27: =MAX(E27-M27-N27+L27,0) -> 261485.36 | W27: =MAX(F27-O27-P27+N27,0) -> 585688.8 | X27: =U27+V27+W27 -> 34385856 | Y27: =Y26+Q27 -> 66391.28 | Z27: =IF(Inputs!B3>0,(V27+W27)/Inputs!B3,0) -> 0.0028239139 | AA27: =IF(OR(Y27/Inputs!B3>=Inputs!B23,Z27>=Inputs!B24),1,0) -> 0 | AB27: =MAX(C27-J27-K27-P27,0)-X27 -> 0
A28: 27 | B28: =MAX(B27,AA28) -> 0 | C28: =X27 -> 34385856 | D28: =U27 -> 33538682 | E28: =V27 -> 261485.36 | F28: =W27 -> 585688.8 | G28: =MAX(Inputs!B7-A28+1,0) -> 274 | H28: =IF(AND(A28<=Inputs!B7,D28>0),-PMT(Inputs!B6/12,G28,D28),0) -> 220109.01 | I28: =IF(AND(A28<=Inputs!B7,D28>0),D28*Inputs!B6/12,0) -> 160706.18 | J28: =MAX(H28-I28,0) -> 59402.824 | K28: =MAX((D28-J28)*Inputs!B32,0) -> 2678342.3 | L28: =MAX((D28-J28-K28)*Inputs!B33,0) -> 104601.62 | M28: =MIN(E28*Inputs!B29,E28) -> 91519.876 | N28: =MIN((E28-M28)*Inputs!B30,E28-M28) -> 33993.097 | O28: =MIN(F28*Inputs!B31,F28) -> 70282.656 | P28: =MIN((F28-O28)*Inputs!B34,F28-O28) -> 4505.48 | Q28: =P28*Inputs!B35 -> 1126.37 | R28: =C28*Inputs!B8/12 -> 14327.44 | S28: =MAX(I28-R28,0) -> 146378.74 | T28: =MAX(J28+K28+P28-Q28,0) -> 2741124.2 | U28: =MAX(D28-J28-K28-L28+M28+O28,0) -> 30858138 | V28: =MAX(E28-M28-N28+L28,0) -> 240574.01 | W28: =MAX(F28-O28-P28+N28,0) -> 544893.76 | X28: =U28+V28+W28 -> 31643605 | Y28: =Y27+Q28 -> 67517.65 | Z28: =IF(Inputs!B3>0,(V28+W28)/Inputs!B3,0) -> 0.0026182259 | AA28: =IF(OR(Y28/Inputs!B3>=Inputs!B23,Z28>=Inputs!B24),1,0) -> 0 | AB28: =MAX(C28-J28-K28-P28,0)-X28 -> 0
A29: 28 | B29: =MAX(B28,AA29) -> 0 | C29: =X28 -> 31643605 | D29: =U28 -> 30858138 | E29: =V28 -> 240574.01 | F29: =W28 -> 544893.76 | G29: =MAX(Inputs!B7-A29+1,0) -> 273 | H29: =IF(AND(A29<=Inputs!B7,D29>0),-PMT(Inputs!B6/12,G29,D29),0) -> 202876.35 | I29: =IF(AND(A29<=Inputs!B7,D29>0),D29*Inputs!B6/12,0) -> 147861.91 | J29: =MAX(H29-I29,0) -> 55014.444 | K29: =MAX((D29-J29)*Inputs!B32,0) -> 2464249.8 | L29: =MAX((D29-J29-K29)*Inputs!B33,0) -> 96240.321 | M29: =MIN(E29*Inputs!B29,E29) -> 84200.902 | N29: =MIN((E29-M29)*Inputs!B30,E29-M29) -> 31274.621 | O29: =MIN(F29*Inputs!B31,F29) -> 65387.252 | P29: =MIN((F29-O29)*Inputs!B34,F29-O29) -> 4191.6594 | Q29: =P29*Inputs!B35 -> 1047.9148 | R29: =C29*Inputs!B8/12 -> 13184.836 | S29: =MAX(I29-R29,0) -> 134677.07 | T29: =MAX(J29+K29+P29-Q29,0) -> 2522408 | U29: =MAX(D29-J29-K29-L29+M29+O29,0) -> 28392221 | V29: =MAX(E29-M29-N29+L29,0) -> 221338.8 | W29: =MAX(F29-O29-P29+N29,0) -> 506589.47 | X29: =U29+V29+W29 -> 29120149 | Y29: =Y28+Q29 -> 68565.565 | Z29: =IF(Inputs!B3>0,(V29+W29)/Inputs!B3,0) -> 0.0024264276 | AA29: =IF(OR(Y29/Inputs!B3>=Inputs!B23,Z29>=Inputs!B24),1,0) -> 0 | AB29: =MAX(C29-J29-K29-P29,0)-X29 -> 0
A30: 29 | B30: =MAX(B29,AA30) -> 0 | C30: =X29 -> 29120149 | D30: =U29 -> 28392221 | E30: =V29 -> 221338.8 | F30: =W29 -> 506589.47 | G30: =MAX(Inputs!B7-A30+1,0) -> 272 | H30: =IF(AND(A30<=Inputs!B7,D30>0),-PMT(Inputs!B6/12,G30,D30),0) -> 186997.61 | I30: =IF(AND(A30<=Inputs!B7,D30>0),D30*Inputs!B6/12,0) -> 136046.06 | J30: =MAX(H30-I30,0) -> 50951.546 | K30: =MAX((D30-J30)*Inputs!B32,0) -> 2267301.6 | L30: =MAX((D30-J30-K30)*Inputs!B33,0) -> 88548.582 | M30: =MIN(E30*Inputs!B29,E30) -> 77468.581 | N30: =MIN((E30-M30)*Inputs!B30,E30-M30) -> 28774.045 | O30: =MIN(F30*Inputs!B31,F30) -> 60790.737 | P30: =MIN((F30-O30)*Inputs!B34,F30-O30) -> 3896.9991 | Q30: =P30*Inputs!B35 -> 974.24978 | R30: =C30*Inputs!B8/12 -> 12133.396 | S30: =MAX(I30-R30,0) -> 123912.66 | T30: =MAX(J30+K30+P30-Q30,0) -> 2321175.9 | U30: =MAX(D30-J30-K30-L30+M30+O30,0) -> 26123679 | V30: =MAX(E30-M30-N30+L30,0) -> 203644.76 | W30: =MAX(F30-O30-P30+N30,0) -> 470675.78 | X30: =U30+V30+W30 -> 26797999 | Y30: =Y29+Q30 -> 69539.815 | Z30: =IF(Inputs!B3>0,(V30+W30)/Inputs!B3,0) -> 0.0022477351 | AA30: =IF(OR(Y30/Inputs!B3>=Inputs!B23,Z30>=Inputs!B24),1,0) -> 0 | AB30: =MAX(C30-J30-K30-P30,0)-X30 -> 0
A31: 30 | B31: =MAX(B30,AA31) -> 0 | C31: =X30 -> 26797999 | D31: =U30 -> 26123679 | E31: =V30 -> 203644.76 | F31: =W30 -> 470675.78 | G31: =MAX(Inputs!B7-A31+1,0) -> 271 | H31: =IF(AND(A31<=Inputs!B7,D31>0),-PMT(Inputs!B6/12,G31,D31),0) -> 172365.79 | I31: =IF(AND(A31<=Inputs!B7,D31>0),D31*Inputs!B6/12,0) -> 125175.96 | J31: =MAX(H31-I31,0) -> 47189.832 | K31: =MAX((D31-J31)*Inputs!B32,0) -> 2086119.1 | L31: =MAX((D31-J31-K31)*Inputs!B33,0) -> 81472.572 | M31: =MIN(E31*Inputs!B29,E31) -> 71275.666 | N31: =MIN((E31-M31)*Inputs!B30,E31-M31) -> 26473.819 | O31: =MIN(F31*Inputs!B31,F31) -> 56481.094 | P31: =MIN((F31-O31)*Inputs!B34,F31-O31) -> 3620.7288 | Q31: =P31*Inputs!B35 -> 905.18221 | R31: =C31*Inputs!B8/12 -> 11165.833 | S31: =MAX(I31-R31,0) -> 114010.13 | T31: =MAX(J31+K31+P31-Q31,0) -> 2136024.5 | U31: =MAX(D31-J31-K31-L31+M31+O31,0) -> 24036654 | V31: =MAX(E31-M31-N31+L31,0) -> 187367.85 | W31: =MAX(F31-O31-P31+N31,0) -> 437047.78 | X31: =U31+V31+W31 -> 24661070 | Y31: =Y30+Q31 -> 70444.997 | Z31: =IF(Inputs!B3>0,(V31+W31)/Inputs!B3,0) -> 0.0020813854 | AA31: =IF(OR(Y31/Inputs!B3>=Inputs!B23,Z31>=Inputs!B24),1,0) -> 0 | AB31: =MAX(C31-J31-K31-P31,0)-X31 -> 0
A32: 31 | B32: =MAX(B31,AA32) -> 0 | C32: =X31 -> 24661070 | D32: =U31 -> 24036654 | E32: =V31 -> 187367.85 | F32: =W31 -> 437047.78 | G32: =MAX(Inputs!B7-A32+1,0) -> 270 | H32: =IF(AND(A32<=Inputs!B7,D32>0),-PMT(Inputs!B6/12,G32,D32),0) -> 158882.47 | I32: =IF(AND(A32<=Inputs!B7,D32>0),D32*Inputs!B6/12,0) -> 115175.63 | J32: =MAX(H32-I32,0) -> 43706.834 | K32: =MAX((D32-J32)*Inputs!B32,0) -> 1919435.8 | L32: =MAX((D32-J32-K32)*Inputs!B33,0) -> 74962.819 | M32: =MIN(E32*Inputs!B29,E32) -> 65578.747 | N32: =MIN((E32-M32)*Inputs!B30,E32-M32) -> 24357.82 | O32: =MIN(F32*Inputs!B31,F32) -> 52445.733 | P32: =MIN((F32-O32)*Inputs!B34,F32-O32) -> 3362.0415 | Q32: =P32*Inputs!B35 -> 840.51036 | R32: =C32*Inputs!B8/12 -> 10275.446 | S32: =MAX(I32-R32,0) -> 104900.19 | T32: =MAX(J32+K32+P32-Q32,0) -> 1965664.1 | U32: =MAX(D32-J32-K32-L32+M32+O32,0) -> 22116573 | V32: =MAX(E32-M32-N32+L32,0) -> 172394.1 | W32: =MAX(F32-O32-P32+N32,0) -> 405597.82 | X32: =U32+V32+W32 -> 22694565 | Y32: =Y31+Q32 -> 71285.508 | Z32: =IF(Inputs!B3>0,(V32+W32)/Inputs!B3,0) -> 0.0019266397 | AA32: =IF(OR(Y32/Inputs!B3>=Inputs!B23,Z32>=Inputs!B24),1,0) -> 0 | AB32: =MAX(C32-J32-K32-P32,0)-X32 -> 0
A33: 32 | B33: =MAX(B32,AA33) -> 0 | C33: =X32 -> 22694565 | D33: =U32 -> 22116573 | E33: =V32 -> 172394.1 | F33: =W32 -> 405597.82 | G33: =MAX(Inputs!B7-A33+1,0) -> 269 | H33: =IF(AND(A33<=Inputs!B7,D33>0),-PMT(Inputs!B6/12,G33,D33),0) -> 146457.03 | I33: =IF(AND(A33<=Inputs!B7,D33>0),D33*Inputs!B6/12,0) -> 105975.25 | J33: =MAX(H33-I33,0) -> 40481.781 | K33: =MAX((D33-J33)*Inputs!B32,0) -> 1766087.3 | L33: =MAX((D33-J33-K33)*Inputs!B33,0) -> 68973.854 | M33: =MIN(E33*Inputs!B29,E33) -> 60337.935 | N33: =MIN((E33-M33)*Inputs!B30,E33-M33) -> 22411.233 | O33: =MIN(F33*Inputs!B31,F33) -> 48671.739 | P33: =MIN((F33-O33)*Inputs!B34,F33-O33) -> 3120.109 | Q33: =P33*Inputs!B35 -> 780.02724 | R33: =C33*Inputs!B8/12 -> 9456.0687 | S33: =MAX(I33-R33,0) -> 96519.177 | T33: =MAX(J33+K33+P33-Q33,0) -> 1808909.2 | U33: =MAX(D33-J33-K33-L33+M33+O33,0) -> 20350040 | V33: =MAX(E33-M33-N33+L33,0) -> 158618.79 | W33: =MAX(F33-O33-P33+N33,0) -> 376217.21 | X33: =U33+V33+W33 -> 20884876 | Y33: =Y32+Q33 -> 72065.535 | Z33: =IF(Inputs!B3>0,(V33+W33)/Inputs!B3,0) -> 0.0017827866 | AA33: =IF(OR(Y33/Inputs!B3>=Inputs!B23,Z33>=Inputs!B24),1,0) -> 0 | AB33: =MAX(C33-J33-K33-P33,0)-X33 -> 0
A34: 33 | B34: =MAX(B33,AA34) -> 0 | C34: =X33 -> 20884876 | D34: =U33 -> 20350040 | E34: =V33 -> 158618.79 | F34: =W33 -> 376217.21 | G34: =MAX(Inputs!B7-A34+1,0) -> 268 | H34: =IF(AND(A34<=Inputs!B7,D34>0),-PMT(Inputs!B6/12,G34,D34),0) -> 135006.07 | I34: =IF(AND(A34<=Inputs!B7,D34>0),D34*Inputs!B6/12,0) -> 97510.607 | J34: =MAX(H34-I34,0) -> 37495.463 | K34: =MAX((D34-J34)*Inputs!B32,0) -> 1625003.5 | L34: =MAX((D34-J34-K34)*Inputs!B33,0) -> 63463.883 | M34: =MIN(E34*Inputs!B29,E34) -> 55516.575 | N34: =MIN((E34-M34)*Inputs!B30,E34-M34) -> 20620.442 | O34: =MIN(F34*Inputs!B31,F34) -> 45146.065 | P34: =MIN((F34-O34)*Inputs!B34,F34-O34) -> 2894.0951 | Q34: =P34*Inputs!B35 -> 723.52378 | R34: =C34*Inputs!B8/12 -> 8702.0316 | S34: =MAX(I34-R34,0) -> 88808.576 | T34: =MAX(J34+K34+P34-Q34,0) -> 1664669.6 | U34: =MAX(D34-J34-K34-L34+M34+O34,0) -> 18724739 | V34: =MAX(E34-M34-N34+L34,0) -> 145945.65 | W34: =MAX(F34-O34-P34+N34,0) -> 348797.49 | X34: =U34+V34+W34 -> 19219483 | Y34: =Y33+Q34 -> 72789.059 | Z34: =IF(Inputs!B3>0,(V34+W34)/Inputs!B3,0) -> 0.0016491438 | AA34: =IF(OR(Y34/Inputs!B3>=Inputs!B23,Z34>=Inputs!B24),1,0) -> 0 | AB34: =MAX(C34-J34-K34-P34,0)-X34 -> 0
A35: 34 | B35: =MAX(B34,AA35) -> 0 | C35: =X34 -> 19219483 | D35: =U34 -> 18724739 | E35: =V34 -> 145945.65 | F35: =W34 -> 348797.49 | G35: =MAX(Inputs!B7-A35+1,0) -> 267 | H35: =IF(AND(A35<=Inputs!B7,D35>0),-PMT(Inputs!B6/12,G35,D35),0) -> 124452.82 | I35: =IF(AND(A35<=Inputs!B7,D35>0),D35*Inputs!B6/12,0) -> 89722.71 | J35: =MAX(H35-I35,0) -> 34730.113 | K35: =MAX((D35-J35)*Inputs!B32,0) -> 1495200.8 | L35: =MAX((D35-J35-K35)*Inputs!B33,0) -> 58394.485 | M35: =MIN(E35*Inputs!B29,E35) -> 51080.978 | N35: =MIN((E35-M35)*Inputs!B30,E35-M35) -> 18972.935 | O35: =MIN(F35*Inputs!B31,F35) -> 41855.699 | P35: =MIN((F35-O35)*Inputs!B34,F35-O35) -> 2683.1657 | Q35: =P35*Inputs!B35 -> 670.79143 | R35: =C35*Inputs!B8/12 -> 8008.1178 | S35: =MAX(I35-R35,0) -> 81714.592 | T35: =MAX(J35+K35+P35-Q35,0) -> 1531943.2 | U35: =MAX(D35-J35-K35-L35+M35+O35,0) -> 17229351 | V35: =MAX(E35-M35-N35+L35,0) -> 134286.22 | W35: =MAX(F35-O35-P35+N35,0) -> 323231.56 | X35: =U35+V35+W35 -> 17686869 | Y35: =Y34+Q35 -> 73459.85 | Z35: =IF(Inputs!B3>0,(V35+W35)/Inputs!B3,0) -> 0.0015250593 | AA35: =IF(OR(Y35/Inputs!B3>=Inputs!B23,Z35>=Inputs!B24),1,0) -> 0 | AB35: =MAX(C35-J35-K35-P35,0)-X35 -> 0
A36: 35 | B36: =MAX(B35,AA36) -> 0 | C36: =X35 -> 17686869 | D36: =U35 -> 17229351 | E36: =V35 -> 134286.22 | F36: =W35 -> 323231.56 | G36: =MAX(Inputs!B7-A36+1,0) -> 266 | H36: =IF(AND(A36<=Inputs!B7,D36>0),-PMT(Inputs!B6/12,G36,D36),0) -> 114726.61 | I36: =IF(AND(A36<=Inputs!B7,D36>0),D36*Inputs!B6/12,0) -> 82557.306 | J36: =MAX(H36-I36,0) -> 32169.301 | K36: =MAX((D36-J36)*Inputs!B32,0) -> 1375774.5 | L36: =MAX((D36-J36-K36)*Inputs!B33,0) -> 53730.34 | M36: =MIN(E36*Inputs!B29,E36) -> 47000.178 | N36: =MIN((E36-M36)*Inputs!B30,E36-M36) -> 17457.209 | O36: =MIN(F36*Inputs!B31,F36) -> 38787.787 | P36: =MIN((F36-O36)*Inputs!B34,F36-O36) -> 2486.4968 | Q36: =P36*Inputs!B35 -> 621.6242 | R36: =C36*Inputs!B8/12 -> 7369.5286 | S36: =MAX(I36-R36,0) -> 75187.777 | T36: =MAX(J36+K36+P36-Q36,0) -> 1409808.7 | U36: =MAX(D36-J36-K36-L36+M36+O36,0) -> 15853465 | V36: =MAX(E36-M36-N36+L36,0) -> 123559.18 | W36: =MAX(F36-O36-P36+N36,0) -> 299414.49 | X36: =U36+V36+W36 -> 16276438 | Y36: =Y35+Q36 -> 74081.474 | Z36: =IF(Inputs!B3>0,(V36+W36)/Inputs!B3,0) -> 0.0014099122 | AA36: =IF(OR(Y36/Inputs!B3>=Inputs!B23,Z36>=Inputs!B24),1,0) -> 0 | AB36: =MAX(C36-J36-K36-P36,0)-X36 -> 0
A37: 36 | B37: =MAX(B36,AA37) -> 0 | C37: =X36 -> 16276438 | D37: =U36 -> 15853465 | E37: =V36 -> 123559.18 | F37: =W36 -> 299414.49 | G37: =MAX(Inputs!B7-A37+1,0) -> 265 | H37: =IF(AND(A37<=Inputs!B7,D37>0),-PMT(Inputs!B6/12,G37,D37),0) -> 105762.34 | I37: =IF(AND(A37<=Inputs!B7,D37>0),D37*Inputs!B6/12,0) -> 75964.518 | J37: =MAX(H37-I37,0) -> 29797.824 | K37: =MAX((D37-J37)*Inputs!B32,0) -> 1265893.3 | L37: =MAX((D37-J37-K37)*Inputs!B33,0) -> 49438.973 | M37: =MIN(E37*Inputs!B29,E37) -> 43245.712 | N37: =MIN((E37-M37)*Inputs!B30,E37-M37) -> 16062.693 | O37: =MIN(F37*Inputs!B31,F37) -> 35929.738 | P37: =MIN((F37-O37)*Inputs!B34,F37-O37) -> 2303.2812 | Q37: =P37*Inputs!B35 -> 575.82029 | R37: =C37*Inputs!B8/12 -> 6781.8493 | S37: =MAX(I37-R37,0) -> 69182.669 | T37: =MAX(J37+K37+P37-Q37,0) -> 1297418.6 | U37: =MAX(D37-J37-K37-L37+M37+O37,0) -> 14587510 | V37: =MAX(E37-M37-N37+L37,0) -> 113689.74 | W37: =MAX(F37-O37-P37+N37,0) -> 277244.16 | X37: =U37+V37+W37 -> 14978444 | Y37: =Y36+Q37 -> 74657.294 | Z37: =IF(Inputs!B3>0,(V37+W37)/Inputs!B3,0) -> 0.001303113 | AA37: =IF(OR(Y37/Inputs!B3>=Inputs!B23,Z37>=Inputs!B24),1,0) -> 0 | AB37: =MAX(C37-J37-K37-P37,0)-X37 -> 0
A38: 37 | B38: =MAX(B37,AA38) -> 0 | C38: =X37 -> 14978444 | D38: =U37 -> 14587510 | E38: =V37 -> 113689.74 | F38: =W37 -> 277244.16 | G38: =MAX(Inputs!B7-A38+1,0) -> 264 | H38: =IF(AND(A38<=Inputs!B7,D38>0),-PMT(Inputs!B6/12,G38,D38),0) -> 97500.108 | I38: =IF(AND(A38<=Inputs!B7,D38>0),D38*Inputs!B6/12,0) -> 69898.485 | J38: =MAX(H38-I38,0) -> 27601.623 | K38: =MAX((D38-J38)*Inputs!B32,0) -> 1164792.7 | L38: =MAX((D38-J38-K38)*Inputs!B33,0) -> 45490.525 | M38: =MIN(E38*Inputs!B29,E38) -> 39791.411 | N38: =MIN((E38-M38)*Inputs!B30,E38-M38) -> 14779.667 | O38: =MIN(F38*Inputs!B31,F38) -> 33269.299 | P38: =MIN((F38-O38)*Inputs!B34,F38-O38) -> 2132.7333 | Q38: =P38*Inputs!B35 -> 533.18333 | R38: =C38*Inputs!B8/12 -> 6241.0183 | S38: =MAX(I38-R38,0) -> 63657.467 | T38: =MAX(J38+K38+P38-Q38,0) -> 1193993.8 | U38: =MAX(D38-J38-K38-L38+M38+O38,0) -> 13422686 | V38: =MAX(E38-M38-N38+L38,0) -> 104609.19 | W38: =MAX(F38-O38-P38+N38,0) -> 256621.79 | X38: =U38+V38+W38 -> 13783917 | Y38: =Y37+Q38 -> 75190.478 | Z38: =IF(Inputs!B3>0,(V38+W38)/Inputs!B3,0) -> 0.0012041033 | AA38: =IF(OR(Y38/Inputs!B3>=Inputs!B23,Z38>=Inputs!B24),1,0) -> 0 | AB38: =MAX(C38-J38-K38-P38,0)-X38 -> 0
A39: 38 | B39: =MAX(B38,AA39) -> 0 | C39: =X38 -> 13783917 | D39: =U38 -> 13422686 | E39: =V38 -> 104609.19 | F39: =W38 -> 256621.79 | G39: =MAX(Inputs!B7-A39+1,0) -> 263 | H39: =IF(AND(A39<=Inputs!B7,D39>0),-PMT(Inputs!B6/12,G39,D39),0) -> 89884.722 | I39: =IF(AND(A39<=Inputs!B7,D39>0),D39*Inputs!B6/12,0) -> 64317.036 | J39: =MAX(H39-I39,0) -> 25567.686 | K39: =MAX((D39-J39)*Inputs!B32,0) -> 1071769.5 | L39: =MAX((D39-J39-K39)*Inputs!B33,0) -> 41857.54 | M39: =MIN(E39*Inputs!B29,E39) -> 36613.217 | N39: =MIN((E39-M39)*Inputs!B30,E39-M39) -> 13599.195 | O39: =MIN(F39*Inputs!B31,F39) -> 30794.615 | P39: =MIN((F39-O39)*Inputs!B34,F39-O39) -> 1974.0933 | Q39: =P39*Inputs!B35 -> 493.52333 | R39: =C39*Inputs!B8/12 -> 5743.2987 | S39: =MAX(I39-R39,0) -> 58573.738 | T39: =MAX(J39+K39+P39-Q39,0) -> 1098817.7 | U39: =MAX(D39-J39-K39-L39+M39+O39,0) -> 12350899 | V39: =MAX(E39-M39-N39+L39,0) -> 96254.32 | W39: =MAX(F39-O39-P39+N39,0) -> 237452.28 | X39: =U39+V39+W39 -> 12684606 | Y39: =Y38+Q39 -> 75684.001 | Z39: =IF(Inputs!B3>0,(V39+W39)/Inputs!B3,0) -> 0.0011123553 | AA39: =IF(OR(Y39/Inputs!B3>=Inputs!B23,Z39>=Inputs!B24),1,0) -> 0 | AB39: =MAX(C39-J39-K39-P39,0)-X39 -> 0
A40: 39 | B40: =MAX(B39,AA40) -> 0 | C40: =X39 -> 12684606 | D40: =U39 -> 12350899 | E40: =V39 -> 96254.32 | F40: =W39 -> 237452.28 | G40: =MAX(Inputs!B7-A40+1,0) -> 262 | H40: =IF(AND(A40<=Inputs!B7,D40>0),-PMT(Inputs!B6/12,G40,D40),0) -> 82865.368 | I40: =IF(AND(A40<=Inputs!B7,D40>0),D40*Inputs!B6/12,0) -> 59181.391 | J40: =MAX(H40-I40,0) -> 23683.977 | K40: =MAX((D40-J40)*Inputs!B32,0) -> 986177.2 | L40: =MAX((D40-J40-K40)*Inputs!B33,0) -> 38514.768 | M40: =MIN(E40*Inputs!B29,E40) -> 33689.012 | N40: =MIN((E40-M40)*Inputs!B30,E40-M40) -> 12513.062 | O40: =MIN(F40*Inputs!B31,F40) -> 28494.274 | P40: =MIN((F40-O40)*Inputs!B34,F40-O40) -> 1826.6296 | Q40: =P40*Inputs!B35 -> 456.6574 | R40: =C40*Inputs!B8/12 -> 5285.2523 | S40: =MAX(I40-R40,0) -> 53896.139 | T40: =MAX(J40+K40+P40-Q40,0) -> 1011231.2 | U40: =MAX(D40-J40-K40-L40+M40+O40,0) -> 11364706 | V40: =MAX(E40-M40-N40+L40,0) -> 88567.014 | W40: =MAX(F40-O40-P40+N40,0) -> 219644.44 | X40: =U40+V40+W40 -> 11672918 | Y40: =Y39+Q40 -> 76140.659 | Z40: =IF(Inputs!B3>0,(V40+W40)/Inputs!B3,0) -> 0.0010273715 | AA40: =IF(OR(Y40/Inputs!B3>=Inputs!B23,Z40>=Inputs!B24),1,0) -> 0 | AB40: =MAX(C40-J40-K40-P40,0)-X40 -> 0
A41: 40 | B41: =MAX(B40,AA41) -> 0 | C41: =X40 -> 11672918 | D41: =U40 -> 11364706 | E41: =V40 -> 88567.014 | F41: =W40 -> 219644.44 | G41: =MAX(Inputs!B7-A41+1,0) -> 261 | H41: =IF(AND(A41<=Inputs!B7,D41>0),-PMT(Inputs!B6/12,G41,D41),0) -> 76395.242 | I41: =IF(AND(A41<=Inputs!B7,D41>0),D41*Inputs!B6/12,0) -> 54455.884 | J41: =MAX(H41-I41,0) -> 21939.357 | K41: =MAX((D41-J41)*Inputs!B32,0) -> 907421.36 | L41: =MAX((D41-J41-K41)*Inputs!B33,0) -> 35438.989 | M41: =MIN(E41*Inputs!B29,E41) -> 30998.455 | N41: =MIN((E41-M41)*Inputs!B30,E41-M41) -> 11513.712 | O41: =MIN(F41*Inputs!B31,F41) -> 26357.333 | P41: =MIN((F41-O41)*Inputs!B34,F41-O41) -> 1689.6407 | Q41: =P41*Inputs!B35 -> 422.41017 | R41: =C41*Inputs!B8/12 -> 4863.7157 | S41: =MAX(I41-R41,0) -> 49592.169 | T41: =MAX(J41+K41+P41-Q41,0) -> 930627.95 | U41: =MAX(D41-J41-K41-L41+M41+O41,0) -> 10457262 | V41: =MAX(E41-M41-N41+L41,0) -> 81493.836 | W41: =MAX(F41-O41-P41+N41,0) -> 203111.18 | X41: =U41+V41+W41 -> 10741867 | Y41: =Y40+Q41 -> 76563.069 | Z41: =IF(Inputs!B3>0,(V41+W41)/Inputs!B3,0) -> 0.00094868338 | AA41: =IF(OR(Y41/Inputs!B3>=Inputs!B23,Z41>=Inputs!B24),1,0) -> 0 | AB41: =MAX(C41-J41-K41-P41,0)-X41 -> 0
